Workbook
Name a: #REF!
Name a: #REF!
Name a: #REF!
Name adfads: #REF!
Name adfads: #REF!
Name adfads: #REF!
Name DATA1: #REF!
Name DATA1: #REF!
Name DATA1: #REF!
Name DATA10: #REF!
Name DATA10: #REF!
Name DATA10: #REF!
Name DATA11: #REF!
Name DATA11: #REF!
Name DATA11: #REF!
Name DATA12: #REF!
Name DATA12: #REF!
Name DATA12: #REF!
Name DATA13: #REF!
Name DATA13: #REF!
Name DATA13: #REF!
Name DATA14: #REF!
Name DATA14: #REF!
Name DATA14: #REF!
Name DATA15: #REF!
Name DATA15: #REF!
Name DATA15: #REF!
Name DATA16: #REF!
Name DATA16: #REF!
Name DATA16: #REF!
Name DATA17: #REF!
Name DATA17: #REF!
Name DATA17: #REF!
Name DATA18: #REF!
Name DATA18: #REF!
Name DATA18: #REF!
Name DATA19: #REF!
Name DATA19: #REF!
Name DATA19: #REF!
Name DATA2: #REF!
Name DATA2: #REF!
Name DATA2: #REF!
Name DATA21: #REF!
Name DATA21: #REF!
Name DATA21: #REF!
Name DATA22: #REF!
Name DATA22: #REF!
Name DATA22: #REF!
Name DATA3: #REF!
Name DATA3: #REF!
Name DATA3: #REF!
Name DATA4: #REF!
Name DATA4: #REF!
Name DATA4: #REF!
Name DATA5: #REF!
Name DATA5: #REF!
Name DATA5: #REF!
Name DATA6: #REF!
Name DATA6: #REF!
Name DATA6: #REF!

Sheet COVER
A3: Company Name: | D3: PT. Indomobil Global Transportasi Cab Pasar Minggu
B6: SPARE PARTS MONTHLY REPORT
B7: 46054
B13: DLR OPERATION INFORMATION
A16: PERFORMANCE RESULT | F16: TARGET | H16: ACTUAL | J16: DIFFERENCE | K16: % Ach.
A17: Retail Sales By Customer | E17: End User | J17: =H17-F17 -> 0 | K17: =H17/F17 -> #DIV/0!
E18: Workshop | J18: =H18-F18 -> 0 | K18: =H18/F18 -> #DIV/0!
E19: Partshop | J19: =H19-F19 -> 0 | K19: =H19/F19 -> #DIV/0!
E20: TOTAL | F20: =SUM(F17:G19) -> 0 | H20: =SUM(H17:I19) -> 0 | J20: =H20-F20 -> 0 | K20: =H20/F20 -> #DIV/0!
A21: Retail Sales By Category | E21: Cat.2 | J21: =H21-F21 -> 0 | K21: =H21/F21 -> #DIV/0!
E22: Cat.3 | J22: =H22-F22 -> 0 | K22: =H22/F22 -> #DIV/0!
E23: Cat.5 | J23: =H23-F23 -> 0 | K23: =H23/F23 -> #DIV/0!
E24: Oil & Acc | J24: =H24-F24 -> 0 | K24: =H24/F24 -> #DIV/0!
A31: DLR OUTLETS
A32: No. | B32: H/O or BRANCH | D32: OUTLET NAME | H32: No. of Fleet Sales | J32: No. of Partshop Sales | K32: Keterangan
A33: 1 | B33: H/O | D33: HEAD OFFICE A
A34: 2 | B34: BRANCH | D34: BRANCH A
A35: 3 | B35: BRANCH | D35: BRANCH B
A36: 4 | B36: BRANCH | D36: BRANCH C
A37: 5 | B37: BRANCH
A38: 6 | B38: BRANCH
A39: 7 | B39: BRANCH
A40: 8 | B40: BRANCH
A41: 9 | B41: BRANCH
A42: 10 | B42: BRANCH

Sheet DETAIL SALES
A2: LAPORAN HARIAN PENJUALAN SPARE PARTS | J2: RETAIL SALES | K2: Pick UP | L2: CDE | M2: CDD | N2: OIL & ACC | O2: TOTAL | P2: % | R2: Fill Rate All Item By Category | S2: Pick UP | T2: CDE | U2: CDD | V2: OIL & ACC | W2: TOTAL | Y2: Fill Rate All Item By Customer | AA2: END USER | AB2: WORKSHOP | AC2: PARTSHOP | AD2: TOTAL
A3: NAMA DEALER | E3: : | J3: End User | K3: =SUMIFS($Y$10:$Y$7501,$N$10:$N$7501,"End User",$P$10:$P$7501,"CAT.2") -> 0 | L3: =SUMIFS($Y$10:$Y$7501,$N$10:$N$7501,"End User",$P$10:$P$7501,"CAT.3") -> 0 | M3: =SUMIFS($Y$10:$Y$7501,$N$10:$N$7501,"End User",$P$10:$P$7501,"CAT.5") -> 0 | N3: =SUMIFS($Y$10:$Y$7501,$N$10:$N$7501,"End User",$P$10:$P$7501,"OIL & ACC") -> 0 | O3: =SUM(K3:N3) -> 0 | P3: =O3/O6 -> #DIV/0!
A4: PERIODE | E4: : | F4: 46054 | J4: Workshop | K4: =SUMIFS($Y$10:$Y$7501,$N$10:$N$7501,"Workshop",$P$10:$P$7501,"CAT.2") -> 0 | L4: =SUMIFS($Y$10:$Y$7501,$N$10:$N$7501,"Workshop",$P$10:$P$7501,"CAT.3") -> 0 | M4: =SUMIFS($Y$10:$Y$7501,$N$10:$N$7501,"Workshop",$P$10:$P$7501,"CAT.5") -> 0 | N4: =SUMIFS($Y$10:$Y$7501,$N$10:$N$7501,"Workshop",$P$10:$P$7501,"OIL & ACC") -> 0 | O4: =SUM(K4:N4) -> 0 | P4: =O4/O6 -> #DIV/0! | R4: Line Order | S4: =COUNTIF($P$10:$P$7501,S2) -> 0 | T4: =COUNTIF($P$10:$P$7501,T2) -> 0 | U4: =COUNTIF($P$10:$P$7501,U2) -> 0 | V4: =COUNTIF($P$10:$P$7501,V2) -> 0 | W4: =SUM(S4:V4) -> 0 | Y4: No. of Item Order | AA4: =COUNTIF($N$10:$N$7501,"End User") -> 0 | AB4: =COUNTIF($N$10:$N$7501,"Workshop") -> 0 | AC4: =COUNTIF($N$10:$N$7501,"Partshop") -> 0 | AD4: =AA4+AB4+AC4 -> 0
A5: JUMLAH HARI KERJA | E5: : | J5: Partshop | K5: =SUMIFS($Y$10:$Y$7501,$N$10:$N$7501,"Partshop",$P$10:$P$7501,"CAT.2") -> 0 | L5: =SUMIFS($Y$10:$Y$7501,$N$10:$N$7501,"Partshop",$P$10:$P$7501,"CAT.3") -> 0 | M5: =SUMIFS($Y$10:$Y$7501,$N$10:$N$7501,"Partshop",$P$10:$P$7501,"CAT.5") -> 0 | N5: =SUMIFS($Y$10:$Y$7501,$N$10:$N$7501,"Partshop",$P$10:$P$7501,"OIL & ACC") -> 0 | O5: =SUM(K5:N5) -> 0 | P5: =O5/O6 -> #DIV/0! | R5: Full Supply | S5: =COUNTIFS($P$10:$P$7501,$S$2,$AB$10:$AB$7501,"Full") -> 0 | T5: =COUNTIFS($P$10:$P$7501,T2,$AB$10:$AB$7501,"Full") -> 0 | U5: =COUNTIFS($P$10:$P$7501,U2,$AB$10:$AB$7501,"Full") -> 0 | V5: =COUNTIFS($P$10:$P$7501,V2,$AB$10:$AB$7501,"Full") -> 0 | W5: =SUM(S5:V5) -> 0 | Y5: Full Supply | AA5: =COUNTIFS($N$10:$N$7501,"End User",$AB$10:$AB$7501,"Full") -> 0 | AB5: =COUNTIFS($N$10:$N$7501,"Workshop",$AB$10:$AB$7501,"Full") -> 0 | AC5: =COUNTIFS($N$10:$N$7501,"Partshop",$AB$10:$AB$7501,"Full") -> 0 | AD5: =AA5+AB5+AC5 -> 0
J6: Total | K6: =SUM(K3:K5) -> 0 | L6: =SUM(L3:L5) -> 0 | M6: =SUM(M3:M5) -> 0 | N6: =SUM(N3:N5) -> 0 | O6: =SUM(O3:O5) -> 0 | P6: =SUM(P3:P5) -> #DIV/0! | R6: Supply Rate | S6: =S5/S4 -> #DIV/0! | T6: =T5/T4 -> #DIV/0! | U6: =U5/U4 -> #DIV/0! | V6: =V5/V4 -> #DIV/0! | W6: =W5/W4 -> #DIV/0! | Y6: Supply Rate | AA6: =AA5/AA4 -> #DIV/0! | AB6: =AB5/AB4 -> #DIV/0! | AC6: =AC5/AC4 -> #DIV/0! | AD6: =AD5/AD4 -> #DIV/0!
J7: % | K7: =K6/$O$6 -> #DIV/0! | L7: =L6/$O$6 -> #DIV/0! | M7: =M6/$O$6 -> #DIV/0! | N7: =N6/$O$6 -> #DIV/0! | O7: =O6/$O$6 -> #DIV/0!
A9: No. | B9: (1) Tanggal | C9: Date | D9: Month | E9: Year | F9: (2) Nama Customer | G9: (3) Segmen Bisnis | H9: (4) Lokasi Customer (Kab/Kota) | I9: (5) Lokasi Customer (Provinsi) | J9: (6) Nomor Sales Order | K9: (7) Nomor Invoice | L9: (8) Penjualan HO/Branch | M9: (9) Status Customer New : Baru, Continue : Lama | N9: (10) Customer Type (end User, Workshop, Partshop) | O9: (11) Nama Sales | P9: (12) Category Spare Parts (Cat.2, Cat.3, Cat.5, Oil & Acc) | Q9: (13) No. Parts | R9: (14) Nama Parts | S9: (15) Qty Order | T9: (16) Qty Allocate | U9: (17) Qty Supply | V9: (18) Qty BO | W9: (19) Harga Satuan | X9: (20) @ Harga Setelah Discount | Y9: (21) Total Harga Sebelum PPN | Z9: (22) Total Harga Setelah PPN | AA9: (23) Program/Non Program | AB9: (24) Fill Rate | AC9: (25) Lost Sales | AD9: (26) Qty Lost | AE9: (27) Alasan Lost Sales | AF9: (28) Keterangan | AQ9: 2018 | BD9: Group | BE9: No. | BF9: Parts Name | BG9: Model | BH9: Parts Number | BI9: Category | BJ9: Interval Change (KM) | BK9: Qty /Unit | BL9: Mandatory Stock | BM9: SUPPLY DATE
A10: 1 | C10: =DAY(B10) -> 0 | D10: =MONTH(B10) -> 1 | E10: =YEAR(B10) -> 1900 | Y10: =X10*U10 -> 0 | Z10: =Y10*1.1 -> 0 | AB10: =IF(S10="","",IF(S10-U10=0,"Full","No")) | AC10: =IF(AND(S10>U10,V10=0),"Lost",IF(AND(S10>U10,V10<(S10-U10)),"Lost","")) | AD10: =IF(AND(S10>U10,V10=0),S10-U10,IF(AND(S10>U10,V10<(S10-U10)),S10-(U10+V10),"")) | AQ10: RETAIL SALES | BM10: 1 | BO10: 2 | BQ10: 3 | BS10: 4 | BU10: 5 | BW10: 6 | BY10: 7 | CA10: 8 | CC10: 9 | CE10: 10 | CG10: 11 | CI10: 12 | CK10: 13 | CM10: 14 | CO10: 15 | CQ10: 16 | CS10: 17 | CU10: 18 | CW10: 19 | CY10: 20 | DA10: 21 | DC10: 22 | DE10: 23 | DG10: 24 | DI10: 25 | DK10: 26 | DM10: 27 | DO10: 28 | DQ10: 29 | DS10: 30 | DU10: 31 | DW10: TOTAL
A11: 2 | C11: =DAY(B11) -> 0 | D11: =MONTH(B11) -> 1 | E11: =YEAR(B11) -> 1900 | Y11: =X11*U11 -> 0 | Z11: =Y11*1.1 -> 0 | AB11: =IF(S11="","",IF(S11-U11=0,"Full","No")) | AC11: =IF(AND(S11>U11,V11=0),"Lost",IF(AND(S11>U11,V11<(S11-U11)),"Lost","")) | AD11: =IF(AND(S11>U11,V11=0),S11-U11,IF(AND(S11>U11,V11<(S11-U11)),S11-(U11+V11),"")) | AJ11: No. | AK11: Segmen Bisnis | AL11: Keterangan | AN11: Nama Dealer | AR11: CAT.2 | AS11: CAT.3 | AT11: CAT.5 | AU11: OIL & ACC | AV11: TOTAL | AW11: % | BM11: Full | BN11: No | BO11: Full | BP11: No | BQ11: Full | BR11: No | BS11: Full | BT11: No | BU11: Full | BV11: No | BW11: Full | BX11: No | BY11: Full | BZ11: No | CA11: Full | CB11: No | CC11: Full | CD11: No | CE11: Full | CF11: No | CG11: Full | CH11: No | CI11: Full | CJ11: No | CK11: Full | CL11: No | CM11: Full | CN11: No | CO11: Full | CP11: No | CQ11: Full | CR11: No | CS11: Full | CT11: No | CU11: Full | CV11: No | CW11: Full | CX11: No | CY11: Full | CZ11: No | DA11: Full | DB11: No | DC11: Full | DD11: No | DE11: Full | DF11: No | DG11: Full | DH11: No | DI11: Full | DJ11: No | DK11: Full | DL11: No | DM11: Full | DN11: No | DO11: Full | DP11: No | DQ11: Full | DR11: No | DS11: Full | DT11: No | DU11: Full | DV11: No | DW11: Full | DX11: No | DY11: Total | DZ11: % Fill Rate
A12: 3 | C12: =DAY(B12) -> 0 | D12: =MONTH(B12) -> 1 | E12: =YEAR(B12) -> 1900 | Y12: =X12*U12 -> 0 | Z12: =Y12*1.1 -> 0 | AB12: =IF(S12="","",IF(S12-U12=0,"Full","No")) | AC12: =IF(AND(S12>U12,V12=0),"Lost",IF(AND(S12>U12,V12<(S12-U12)),"Lost","")) | AD12: =IF(AND(S12>U12,V12=0),S12-U12,IF(AND(S12>U12,V12<(S12-U12)),S12-(U12+V12),"")) | AJ12: 1 | AK12: Food Industry | AL12: Indofood, Wingsfood | AN12: PT. ANTASENA AGUNG JAYA | AQ12: End User | AR12: =SUMIFS($Y$10:$Y$7501,$N$10:$N$7501,"End User",$P$10:$P$7501,"CAT.2") -> 0 | AS12: =SUMIFS($Y$10:$Y$7501,$N$10:$N$7501,"End User",$P$10:$P$7501,"CAT.3") -> 0 | AT12: =SUMIFS($Y$10:$Y$7501,$N$10:$N$7501,"End User",$P$10:$P$7501,"CAT.5") -> 0 | AU12: =SUMIFS($Y$10:$Y$7501,$N$10:$N$7501,"End User",$P$10:$P$7501,"OIL & ACC") -> 0 | AV12: =SUM(AR12:AU12) -> 0 | AW12: =AV12/AV15 -> #DIV/0! | BD12: F S P (39) | BE12: 1 | BF12: GREASE CHASISS (16 KG) | BG12: ALL MODEL | BH12: S041041024 | BI12: =VLOOKUP(BH12,#REF!,8,FALSE) -> #REF! | BJ12: 10000 | BK12: 3 | BL12: 0 | BM12: =COUNTIFS('DETAIL SALES'!$Q$10:$Q$7501,'FILL RATE MANDATORY STOCK'!BK12,'DETAIL SALES'!$AB$10:$AB$7501,"Full",'DETAIL SALES'!$C$10:$C$7501,"1") -> 0 | BN12: =COUNTIFS('DETAIL SALES'!$Q$10:$Q$7501,'FILL RATE MANDATORY STOCK'!BK12,'DETAIL SALES'!$AB$10:$AB$7501,"No",'DETAIL SALES'!$C$10:$C$7501,"1") -> 0 | BO12: =COUNTIFS('DETAIL SALES'!$Q$10:$Q$7501,'FILL RATE MANDATORY STOCK'!BK12,'DETAIL SALES'!$AB$10:$AB$7501,"Full",'DETAIL SALES'!$C$10:$C$7501,"2") -> 0 | BP12: =COUNTIFS('DETAIL SALES'!$Q$10:$Q$7501,'FILL RATE MANDATORY STOCK'!BK12,'DETAIL SALES'!$AB$10:$AB$7501,"No",'DETAIL SALES'!$C$10:$C$7501,"2") -> 0 | BQ12: =COUNTIFS('DETAIL SALES'!$Q$10:$Q$7501,'FILL RATE MANDATORY STOCK'!BK12,'DETAIL SALES'!$AB$10:$AB$7501,"Full",'DETAIL SALES'!$C$10:$C$7501,"3") -> 0 | BR12: =COUNTIFS('DETAIL SALES'!$Q$10:$Q$7501,'FILL RATE MANDATORY STOCK'!BK12,'DETAIL SALES'!$AB$10:$AB$7501,"No",'DETAIL SALES'!$C$10:$C$7501,"3") -> 0 | BS12: =COUNTIFS('DETAIL SALES'!$Q$10:$Q$7501,'FILL RATE MANDATORY STOCK'!BK12,'DETAIL SALES'!$AB$10:$AB$7501,"Full",'DETAIL SALES'!$C$10:$C$7501,"4") -> 0 | BT12: =COUNTIFS('DETAIL SALES'!$Q$10:$Q$7501,'FILL RATE MANDATORY STOCK'!BK12,'DETAIL SALES'!$AB$10:$AB$7501,"No",'DETAIL SALES'!$C$10:$C$7501,"4") -> 0 | BU12: =COUNTIFS('DETAIL SALES'!$Q$10:$Q$7501,'FILL RATE MANDATORY STOCK'!BK12,'DETAIL SALES'!$AB$10:$AB$7501,"Full",'DETAIL SALES'!$C$10:$C$7501,"5") -> 0 | BV12: =COUNTIFS('DETAIL SALES'!$Q$10:$Q$7501,'FILL RATE MANDATORY STOCK'!BK12,'DETAIL SALES'!$AB$10:$AB$7501,"No",'DETAIL SALES'!$C$10:$C$7501,"5") -> 0 | BW12: =COUNTIFS('DETAIL SALES'!$Q$10:$Q$7501,'FILL RATE MANDATORY STOCK'!BK12,'DETAIL SALES'!$AB$10:$AB$7501,"Full",'DETAIL SALES'!$C$10:$C$7501,"6") -> 0 | BX12: =COUNTIFS('DETAIL SALES'!$Q$10:$Q$7501,'FILL RATE MANDATORY STOCK'!BK12,'DETAIL SALES'!$AB$10:$AB$7501,"No",'DETAIL SALES'!$C$10:$C$7501,"6") -> 0 | BY12: =COUNTIFS('DETAIL SALES'!$Q$10:$Q$7501,'FILL RATE MANDATORY STOCK'!BK12,'DETAIL SALES'!$AB$10:$AB$7501,"Full",'DETAIL SALES'!$C$10:$C$7501,"7") -> 0 | BZ12: =COUNTIFS('DETAIL SALES'!$Q$10:$Q$7501,'FILL RATE MANDATORY STOCK'!BK12,'DETAIL SALES'!$AB$10:$AB$7501,"No",'DETAIL SALES'!$C$10:$C$7501,"7") -> 0 | CA12: =COUNTIFS('DETAIL SALES'!$Q$10:$Q$7501,'FILL RATE MANDATORY STOCK'!BK12,'DETAIL SALES'!$AB$10:$AB$7501,"Full",'DETAIL SALES'!$C$10:$C$7501,"8") -> 0 | CB12: =COUNTIFS('DETAIL SALES'!$Q$10:$Q$7501,'FILL RATE MANDATORY STOCK'!BK12,'DETAIL SALES'!$AB$10:$AB$7501,"No",'DETAIL SALES'!$C$10:$C$7501,"8") -> 0 | CC12: =COUNTIFS('DETAIL SALES'!$Q$10:$Q$7501,'FILL RATE MANDATORY STOCK'!BK12,'DETAIL SALES'!$AB$10:$AB$7501,"Full",'DETAIL SALES'!$C$10:$C$7501,"9") -> 0 | CD12: =COUNTIFS('DETAIL SALES'!$Q$10:$Q$7501,'FILL RATE MANDATORY STOCK'!BK12,'DETAIL SALES'!$AB$10:$AB$7501,"No",'DETAIL SALES'!$C$10:$C$7501,"9") -> 0 | CE12: =COUNTIFS('DETAIL SALES'!$Q$10:$Q$7501,'FILL RATE MANDATORY STOCK'!BK12,'DETAIL SALES'!$AB$10:$AB$7501,"Full",'DETAIL SALES'!$C$10:$C$7501,"10") -> 0 | CF12: =COUNTIFS('DETAIL SALES'!$Q$10:$Q$7501,'FILL RATE MANDATORY STOCK'!BK12,'DETAIL SALES'!$AB$10:$AB$7501,"No",'DETAIL SALES'!$C$10:$C$7501,"10") -> 0 | CG12: =COUNTIFS('DETAIL SALES'!$Q$10:$Q$7501,'FILL RATE MANDATORY STOCK'!BK12,'DETAIL SALES'!$AB$10:$AB$7501,"Full",'DETAIL SALES'!$C$10:$C$7501,"11") -> 0 | CH12: =COUNTIFS('DETAIL SALES'!$Q$10:$Q$7501,'FILL RATE MANDATORY STOCK'!BK12,'DETAIL SALES'!$AB$10:$AB$7501,"No",'DETAIL SALES'!$C$10:$C$7501,"11") -> 0 | CI12: =COUNTIFS('DETAIL SALES'!$Q$10:$Q$7501,'FILL RATE MANDATORY STOCK'!BK12,'DETAIL SALES'!$AB$10:$AB$7501,"Full",'DETAIL SALES'!$C$10:$C$7501,"12") -> 0 | CJ12: =COUNTIFS('DETAIL SALES'!$Q$10:$Q$7501,'FILL RATE MANDATORY STOCK'!BK12,'DETAIL SALES'!$AB$10:$AB$7501,"No",'DETAIL SALES'!$C$10:$C$7501,"12") -> 0 | CK12: =COUNTIFS('DETAIL SALES'!$Q$10:$Q$7501,'FILL RATE MANDATORY STOCK'!BK12,'DETAIL SALES'!$AB$10:$AB$7501,"Full",'DETAIL SALES'!$C$10:$C$7501,"13") -> 0 | CL12: =COUNTIFS('DETAIL SALES'!$Q$10:$Q$7501,'FILL RATE MANDATORY STOCK'!BK12,'DETAIL SALES'!$AB$10:$AB$7501,"No",'DETAIL SALES'!$C$10:$C$7501,"13") -> 0 | CM12: =COUNTIFS('DETAIL SALES'!$Q$10:$Q$7501,'FILL RATE MANDATORY STOCK'!BK12,'DETAIL SALES'!$AB$10:$AB$7501,"Full",'DETAIL SALES'!$C$10:$C$7501,"14") -> 0 | CN12: =COUNTIFS('DETAIL SALES'!$Q$10:$Q$7501,'FILL RATE MANDATORY STOCK'!BK12,'DETAIL SALES'!$AB$10:$AB$7501,"No",'DETAIL SALES'!$C$10:$C$7501,"14") -> 0 | CO12: =COUNTIFS('DETAIL SALES'!$Q$10:$Q$7501,'FILL RATE MANDATORY STOCK'!BK12,'DETAIL SALES'!$AB$10:$AB$7501,"Full",'DETAIL SALES'!$C$10:$C$7501,"15") -> 0 | CP12: =COUNTIFS('DETAIL SALES'!$Q$10:$Q$7501,'FILL RATE MANDATORY STOCK'!BK12,'DETAIL SALES'!$AB$10:$AB$7501,"No",'DETAIL SALES'!$C$10:$C$7501,"15") -> 0 | CQ12: =COUNTIFS('DETAIL SALES'!$Q$10:$Q$7501,'FILL RATE MANDATORY STOCK'!BK12,'DETAIL SALES'!$AB$10:$AB$7501,"Full",'DETAIL SALES'!$C$10:$C$7501,"16") -> 0 | CR12: =COUNTIFS('DETAIL SALES'!$Q$10:$Q$7501,'FILL RATE MANDATORY STOCK'!BK12,'DETAIL SALES'!$AB$10:$AB$7501,"No",'DETAIL SALES'!$C$10:$C$7501,"16") -> 0 | CS12: =COUNTIFS('DETAIL SALES'!$Q$10:$Q$7501,'FILL RATE MANDATORY STOCK'!BK12,'DETAIL SALES'!$AB$10:$AB$7501,"Full",'DETAIL SALES'!$C$10:$C$7501,"17") -> 0 | CT12: =COUNTIFS('DETAIL SALES'!$Q$10:$Q$7501,'FILL RATE MANDATORY STOCK'!BK12,'DETAIL SALES'!$AB$10:$AB$7501,"No",'DETAIL SALES'!$C$10:$C$7501,"17") -> 0 | CU12: =COUNTIFS('DETAIL SALES'!$Q$10:$Q$7501,'FILL RATE MANDATORY STOCK'!BK12,'DETAIL SALES'!$AB$10:$AB$7501,"Full",'DETAIL SALES'!$C$10:$C$7501,"18") -> 0 | CV12: =COUNTIFS('DETAIL SALES'!$Q$10:$Q$7501,'FILL RATE MANDATORY STOCK'!BK12,'DETAIL SALES'!$AB$10:$AB$7501,"No",'DETAIL SALES'!$C$10:$C$7501,"18") -> 0 | CW12: =COUNTIFS('DETAIL SALES'!$Q$10:$Q$7501,'FILL RATE MANDATORY STOCK'!BK12,'DETAIL SALES'!$AB$10:$AB$7501,"Full",'DETAIL SALES'!$C$10:$C$7501,"19") -> 0 | CX12: =COUNTIFS('DETAIL SALES'!$Q$10:$Q$7501,'FILL RATE MANDATORY STOCK'!BK12,'DETAIL SALES'!$AB$10:$AB$7501,"No",'DETAIL SALES'!$C$10:$C$7501,"19") -> 0 | CY12: =COUNTIFS('DETAIL SALES'!$Q$10:$Q$7501,'FILL RATE MANDATORY STOCK'!BK12,'DETAIL SALES'!$AB$10:$AB$7501,"Full",'DETAIL SALES'!$C$10:$C$7501,"20") -> 0 | CZ12: =COUNTIFS('DETAIL SALES'!$Q$10:$Q$7501,'FILL RATE MANDATORY STOCK'!BK12,'DETAIL SALES'!$AB$10:$AB$7501,"No",'DETAIL SALES'!$C$10:$C$7501,"20") -> 0 | DA12: =COUNTIFS('DETAIL SALES'!$Q$10:$Q$7501,'FILL RATE MANDATORY STOCK'!BK12,'DETAIL SALES'!$AB$10:$AB$7501,"Full",'DETAIL SALES'!$C$10:$C$7501,"21") -> 0 | DB12: =COUNTIFS('DETAIL SALES'!$Q$10:$Q$7501,'FILL RATE MANDATORY STOCK'!BK12,'DETAIL SALES'!$AB$10:$AB$7501,"No",'DETAIL SALES'!$C$10:$C$7501,"21") -> 0 | DC12: =COUNTIFS('DETAIL SALES'!$Q$10:$Q$7501,'FILL RATE MANDATORY STOCK'!BK12,'DETAIL SALES'!$AB$10:$AB$7501,"Full",'DETAIL SALES'!$C$10:$C$7501,"22") -> 0 | DD12: =COUNTIFS('DETAIL SALES'!$Q$10:$Q$7501,'FILL RATE MANDATORY STOCK'!BK12,'DETAIL SALES'!$AB$10:$AB$7501,"No",'DETAIL SALES'!$C$10:$C$7501,"22") -> 0 | DE12: =COUNTIFS('DETAIL SALES'!$Q$10:$Q$7501,'FILL RATE MANDATORY STOCK'!BK12,'DETAIL SALES'!$AB$10:$AB$7501,"Full",'DETAIL SALES'!$C$10:$C$7501,"23") -> 0 | DF12: =COUNTIFS('DETAIL SALES'!$Q$10:$Q$7501,'FILL RATE MANDATORY STOCK'!BK12,'DETAIL SALES'!$AB$10:$AB$7501,"No",'DETAIL SALES'!$C$10:$C$7501,"23") -> 0 | DG12: =COUNTIFS('DETAIL SALES'!$Q$10:$Q$7501,'FILL RATE MANDATORY STOCK'!BK12,'DETAIL SALES'!$AB$10:$AB$7501,"Full",'DETAIL SALES'!$C$10:$C$7501,"24") -> 0 | DH12: =COUNTIFS('DETAIL SALES'!$Q$10:$Q$7501,'FILL RATE MANDATORY STOCK'!BK12,'DETAIL SALES'!$AB$10:$AB$7501,"No",'DETAIL SALES'!$C$10:$C$7501,"24") -> 0 | DI12: =COUNTIFS('DETAIL SALES'!$Q$10:$Q$7501,'FILL RATE MANDATORY STOCK'!BK12,'DETAIL SALES'!$AB$10:$AB$7501,"Full",'DETAIL SALES'!$C$10:$C$7501,"25") -> 0 | DJ12: =COUNTIFS('DETAIL SALES'!$Q$10:$Q$7501,'FILL RATE MANDATORY STOCK'!BK12,'DETAIL SALES'!$AB$10:$AB$7501,"No",'DETAIL SALES'!$C$10:$C$7501,"25") -> 0 | DK12: =COUNTIFS('DETAIL SALES'!$Q$10:$Q$7501,'FILL RATE MANDATORY STOCK'!BK12,'DETAIL SALES'!$AB$10:$AB$7501,"Full",'DETAIL SALES'!$C$10:$C$7501,"26") -> 0 | DL12: =COUNTIFS('DETAIL SALES'!$Q$10:$Q$7501,'FILL RATE MANDATORY STOCK'!BK12,'DETAIL SALES'!$AB$10:$AB$7501,"No",'DETAIL SALES'!$C$10:$C$7501,"26") -> 0 | DM12: =COUNTIFS('DETAIL SALES'!$Q$10:$Q$7501,'FILL RATE MANDATORY STOCK'!BK12,'DETAIL SALES'!$AB$10:$AB$7501,"Full",'DETAIL SALES'!$C$10:$C$7501,"27") -> 0 | DN12: =COUNTIFS('DETAIL SALES'!$Q$10:$Q$7501,'FILL RATE MANDATORY STOCK'!BK12,'DETAIL SALES'!$AB$10:$AB$7501,"No",'DETAIL SALES'!$C$10:$C$7501,"27") -> 0 | DO12: =COUNTIFS('DETAIL SALES'!$Q$10:$Q$7501,'FILL RATE MANDATORY STOCK'!BK12,'DETAIL SALES'!$AB$10:$AB$7501,"Full",'DETAIL SALES'!$C$10:$C$7501,"28") -> 0 | DP12: =COUNTIFS('DETAIL SALES'!$Q$10:$Q$7501,'FILL RATE MANDATORY STOCK'!BK12,'DETAIL SALES'!$AB$10:$AB$7501,"No",'DETAIL SALES'!$C$10:$C$7501,"28") -> 0 | DQ12: =COUNTIFS('DETAIL SALES'!$Q$10:$Q$7501,'FILL RATE MANDATORY STOCK'!BK12,'DETAIL SALES'!$AB$10:$AB$7501,"Full",'DETAIL SALES'!$C$10:$C$7501,"29") -> 0 | DR12: =COUNTIFS('DETAIL SALES'!$Q$10:$Q$7501,'FILL RATE MANDATORY STOCK'!BK12,'DETAIL SALES'!$AB$10:$AB$7501,"No",'DETAIL SALES'!$C$10:$C$7501,"29") -> 0 | DS12: =COUNTIFS('DETAIL SALES'!$Q$10:$Q$7501,'FILL RATE MANDATORY STOCK'!BK12,'DETAIL SALES'!$AB$10:$AB$7501,"Full",'DETAIL SALES'!$C$10:$C$7501,"30") -> 0 | DT12: =COUNTIFS('DETAIL SALES'!$Q$10:$Q$7501,'FILL RATE MANDATORY STOCK'!BK12,'DETAIL SALES'!$AB$10:$AB$7501,"No",'DETAIL SALES'!$C$10:$C$7501,"30") -> 0 | DU12: =COUNTIFS('DETAIL SALES'!$Q$10:$Q$7501,'FILL RATE MANDATORY STOCK'!\,'DETAIL SALES'!$AB$10:$AB$7501,"Full",'DETAIL SALES'!$C$10:$C$7501,"31") -> 0 | DV12: =COUNTIFS('DETAIL SALES'!$Q$10:$Q$7501,'FILL RATE MANDATORY STOCK'!BK12,'DETAIL SALES'!$AB$10:$AB$7501,"No",'DETAIL SALES'!$C$10:$C$7501,"31") -> 0 | DW12: =BM12+BO12+BQ12+BS12+BU12+BW12+BY12+CA12+CC12+CE12+CG12+CI12+CK12+CM12+CO12+CQ12+CS12+CU12+CW12+CY12+DA12+DC12+DE12+DG12+DI12+DK12+DM12+DO12+DQ12+DS12+DU12 -> 0 | DX12: =BN12+BP12+BR12+BT12+BV12+BX12+BZ12+CB12+CD12+CF12+CH12+CJ12+CL12+CN12+CP12+CR12+CT12+CV12+CX12+CZ12+DB12+DD12+DF12+DH12+DJ12+DL12+DN12+DP12+DR12+DT12+DV12 -> 0 | DY12: =DW12+DX12 -> 0 | DZ12: =DW12/DY12 -> #DIV/0!
A13: 4 | C13: =DAY(B13) -> 0 | D13: =MONTH(B13) -> 1 | E13: =YEAR(B13) -> 1900 | Y13: =X13*U13 -> 0 | Z13: =Y13*1.1 -> 0 | AB13: =IF(S13="","",IF(S13-U13=0,"Full","No")) | AC13: =IF(AND(S13>U13,V13=0),"Lost",IF(AND(S13>U13,V13<(S13-U13)),"Lost","")) | AD13: =IF(AND(S13>U13,V13=0),S13-U13,IF(AND(S13>U13,V13<(S13-U13)),S13-(U13+V13),"")) | AJ13: 2 | AK13: Consumer Goods | AL13: Indomaret, Alfamart | AN13: PT. ARIMBI JAYA AGUNG | AQ13: Workshop | AR13: =SUMIFS($Y$10:$Y$7501,$N$10:$N$7501,"Workshop",$P$10:$P$7501,"CAT.2") -> 0 | AS13: =SUMIFS($Y$10:$Y$7501,$N$10:$N$7501,"Workshop",$P$10:$P$7501,"CAT.3") -> 0 | AT13: =SUMIFS($Y$10:$Y$7501,$N$10:$N$7501,"Workshop",$P$10:$P$7501,"CAT.5") -> 0 | AU13: =SUMIFS($Y$10:$Y$7501,$N$10:$N$7501,"Workshop",$P$10:$P$7501,"OIL & ACC") -> 0 | AV13: =SUM(AR13:AU13) -> 0 | AW13: =AV13/AV15 -> #DIV/0! | BE13: =BE12+1 -> 2 | BF13: GREASE WHEEL BEARING ( 16 KG ) | BG13: ALL MODEL | BH13: S041040024 | BI13: =VLOOKUP(BH13,#REF!,8,FALSE) -> #REF! | BJ13: 60000 | BK13: 1 | BL13: 0 | BM13: =COUNTIFS('DETAIL SALES'!$Q$10:$Q$7501,'FILL RATE MANDATORY STOCK'!BK13,'DETAIL SALES'!$AB$10:$AB$7501,"Full",'DETAIL SALES'!$C$10:$C$7501,"1") -> 0 | BN13: =COUNTIFS('DETAIL SALES'!$Q$10:$Q$7501,'FILL RATE MANDATORY STOCK'!BK13,'DETAIL SALES'!$AB$10:$AB$7501,"No",'DETAIL SALES'!$C$10:$C$7501,"1") -> 0 | BO13: =COUNTIFS('DETAIL SALES'!$Q$10:$Q$7501,'FILL RATE MANDATORY STOCK'!BK13,'DETAIL SALES'!$AB$10:$AB$7501,"Full",'DETAIL SALES'!$C$10:$C$7501,"2") -> 0 | BP13: =COUNTIFS('DETAIL SALES'!$Q$10:$Q$7501,'FILL RATE MANDATORY STOCK'!BK13,'DETAIL SALES'!$AB$10:$AB$7501,"No",'DETAIL SALES'!$C$10:$C$7501,"2") -> 0 | BQ13: =COUNTIFS('DETAIL SALES'!$Q$10:$Q$7501,'FILL RATE MANDATORY STOCK'!BK13,'DETAIL SALES'!$AB$10:$AB$7501,"Full",'DETAIL SALES'!$C$10:$C$7501,"3") -> 0 | BR13: =COUNTIFS('DETAIL SALES'!$Q$10:$Q$7501,'FILL RATE MANDATORY STOCK'!BK13,'DETAIL SALES'!$AB$10:$AB$7501,"No",'DETAIL SALES'!$C$10:$C$7501,"3") -> 0 | BS13: =COUNTIFS('DETAIL SALES'!$Q$10:$Q$7501,'FILL RATE MANDATORY STOCK'!BK13,'DETAIL SALES'!$AB$10:$AB$7501,"Full",'DETAIL SALES'!$C$10:$C$7501,"4") -> 0 | BT13: =COUNTIFS('DETAIL SALES'!$Q$10:$Q$7501,'FILL RATE MANDATORY STOCK'!BK13,'DETAIL SALES'!$AB$10:$AB$7501,"No",'DETAIL SALES'!$C$10:$C$7501,"4") -> 0 | BU13: =COUNTIFS('DETAIL SALES'!$Q$10:$Q$7501,'FILL RATE MANDATORY STOCK'!BK13,'DETAIL SALES'!$AB$10:$AB$7501,"Full",'DETAIL SALES'!$C$10:$C$7501,"5") -> 0 | BV13: =COUNTIFS('DETAIL SALES'!$Q$10:$Q$7501,'FILL RATE MANDATORY STOCK'!BK13,'DETAIL SALES'!$AB$10:$AB$7501,"No",'DETAIL SALES'!$C$10:$C$7501,"5") -> 0 | BW13: =COUNTIFS('DETAIL SALES'!$Q$10:$Q$7501,'FILL RATE MANDATORY STOCK'!BK13,'DETAIL SALES'!$AB$10:$AB$7501,"Full",'DETAIL SALES'!$C$10:$C$7501,"6") -> 0 | BX13: =COUNTIFS('DETAIL SALES'!$Q$10:$Q$7501,'FILL RATE MANDATORY STOCK'!BK13,'DETAIL SALES'!$AB$10:$AB$7501,"No",'DETAIL SALES'!$C$10:$C$7501,"6") -> 0 | BY13: =COUNTIFS('DETAIL SALES'!$Q$10:$Q$7501,'FILL RATE MANDATORY STOCK'!BK13,'DETAIL SALES'!$AB$10:$AB$7501,"Full",'DETAIL SALES'!$C$10:$C$7501,"7") -> 0 | BZ13: =COUNTIFS('DETAIL SALES'!$Q$10:$Q$7501,'FILL RATE MANDATORY STOCK'!BK13,'DETAIL SALES'!$AB$10:$AB$7501,"No",'DETAIL SALES'!$C$10:$C$7501,"7") -> 0 | CA13: =COUNTIFS('DETAIL SALES'!$Q$10:$Q$7501,'FILL RATE MANDATORY STOCK'!BK13,'DETAIL SALES'!$AB$10:$AB$7501,"Full",'DETAIL SALES'!$C$10:$C$7501,"8") -> 0 | CB13: =COUNTIFS('DETAIL SALES'!$Q$10:$Q$7501,'FILL RATE MANDATORY STOCK'!BK13,'DETAIL SALES'!$AB$10:$AB$7501,"No",'DETAIL SALES'!$C$10:$C$7501,"8") -> 0 | CC13: =COUNTIFS('DETAIL SALES'!$Q$10:$Q$7501,'FILL RATE MANDATORY STOCK'!BK13,'DETAIL SALES'!$AB$10:$AB$7501,"Full",'DETAIL SALES'!$C$10:$C$7501,"9") -> 0 | CD13: =COUNTIFS('DETAIL SALES'!$Q$10:$Q$7501,'FILL RATE MANDATORY STOCK'!BK13,'DETAIL SALES'!$AB$10:$AB$7501,"No",'DETAIL SALES'!$C$10:$C$7501,"9") -> 0 | CE13: =COUNTIFS('DETAIL SALES'!$Q$10:$Q$7501,'FILL RATE MANDATORY STOCK'!BK13,'DETAIL SALES'!$AB$10:$AB$7501,"Full",'DETAIL SALES'!$C$10:$C$7501,"10") -> 0 | CF13: =COUNTIFS('DETAIL SALES'!$Q$10:$Q$7501,'FILL RATE MANDATORY STOCK'!BK13,'DETAIL SALES'!$AB$10:$AB$7501,"No",'DETAIL SALES'!$C$10:$C$7501,"10") -> 0 | CG13: =COUNTIFS('DETAIL SALES'!$Q$10:$Q$7501,'FILL RATE MANDATORY STOCK'!BK13,'DETAIL SALES'!$AB$10:$AB$7501,"Full",'DETAIL SALES'!$C$10:$C$7501,"11") -> 0 | CH13: =COUNTIFS('DETAIL SALES'!$Q$10:$Q$7501,'FILL RATE MANDATORY STOCK'!BK13,'DETAIL SALES'!$AB$10:$AB$7501,"No",'DETAIL SALES'!$C$10:$C$7501,"11") -> 0 | CI13: =COUNTIFS('DETAIL SALES'!$Q$10:$Q$7501,'FILL RATE MANDATORY STOCK'!BK13,'DETAIL SALES'!$AB$10:$AB$7501,"Full",'DETAIL SALES'!$C$10:$C$7501,"12") -> 0 | CJ13: =COUNTIFS('DETAIL SALES'!$Q$10:$Q$7501,'FILL RATE MANDATORY STOCK'!BK13,'DETAIL SALES'!$AB$10:$AB$7501,"No",'DETAIL SALES'!$C$10:$C$7501,"12") -> 0 | CK13: =COUNTIFS('DETAIL SALES'!$Q$10:$Q$7501,'FILL RATE MANDATORY STOCK'!BK13,'DETAIL SALES'!$AB$10:$AB$7501,"Full",'DETAIL SALES'!$C$10:$C$7501,"13") -> 0 | CL13: =COUNTIFS('DETAIL SALES'!$Q$10:$Q$7501,'FILL RATE MANDATORY STOCK'!BK13,'DETAIL SALES'!$AB$10:$AB$7501,"No",'DETAIL SALES'!$C$10:$C$7501,"13") -> 0 | CM13: =COUNTIFS('DETAIL SALES'!$Q$10:$Q$7501,'FILL RATE MANDATORY STOCK'!BK13,'DETAIL SALES'!$AB$10:$AB$7501,"Full",'DETAIL SALES'!$C$10:$C$7501,"14") -> 0 | CN13: =COUNTIFS('DETAIL SALES'!$Q$10:$Q$7501,'FILL RATE MANDATORY STOCK'!BK13,'DETAIL SALES'!$AB$10:$AB$7501,"No",'DETAIL SALES'!$C$10:$C$7501,"14") -> 0 | CO13: =COUNTIFS('DETAIL SALES'!$Q$10:$Q$7501,'FILL RATE MANDATORY STOCK'!BK13,'DETAIL SALES'!$AB$10:$AB$7501,"Full",'DETAIL SALES'!$C$10:$C$7501,"15") -> 0 | CP13: =COUNTIFS('DETAIL SALES'!$Q$10:$Q$7501,'FILL RATE MANDATORY STOCK'!BK13,'DETAIL SALES'!$AB$10:$AB$7501,"No",'DETAIL SALES'!$C$10:$C$7501,"15") -> 0 | CQ13: =COUNTIFS('DETAIL SALES'!$Q$10:$Q$7501,'FILL RATE MANDATORY STOCK'!BK13,'DETAIL SALES'!$AB$10:$AB$7501,"Full",'DETAIL SALES'!$C$10:$C$7501,"16") -> 0 | CR13: =COUNTIFS('DETAIL SALES'!$Q$10:$Q$7501,'FILL RATE MANDATORY STOCK'!BK13,'DETAIL SALES'!$AB$10:$AB$7501,"No",'DETAIL SALES'!$C$10:$C$7501,"16") -> 0 | CS13: =COUNTIFS('DETAIL SALES'!$Q$10:$Q$7501,'FILL RATE MANDATORY STOCK'!BK13,'DETAIL SALES'!$AB$10:$AB$7501,"Full",'DETAIL SALES'!$C$10:$C$7501,"17") -> 0 | CT13: =COUNTIFS('DETAIL SALES'!$Q$10:$Q$7501,'FILL RATE MANDATORY STOCK'!BK13,'DETAIL SALES'!$AB$10:$AB$7501,"No",'DETAIL SALES'!$C$10:$C$7501,"17") -> 0 | CU13: =COUNTIFS('DETAIL SALES'!$Q$10:$Q$7501,'FILL RATE MANDATORY STOCK'!BK13,'DETAIL SALES'!$AB$10:$AB$7501,"Full",'DETAIL SALES'!$C$10:$C$7501,"18") -> 0 | CV13: =COUNTIFS('DETAIL SALES'!$Q$10:$Q$7501,'FILL RATE MANDATORY STOCK'!BK13,'DETAIL SALES'!$AB$10:$AB$7501,"No",'DETAIL SALES'!$C$10:$C$7501,"18") -> 0 | CW13: =COUNTIFS('DETAIL SALES'!$Q$10:$Q$7501,'FILL RATE MANDATORY STOCK'!BK13,'DETAIL SALES'!$AB$10:$AB$7501,"Full",'DETAIL SALES'!$C$10:$C$7501,"19") -> 0 | CX13: =COUNTIFS('DETAIL SALES'!$Q$10:$Q$7501,'FILL RATE MANDATORY STOCK'!BK13,'DETAIL SALES'!$AB$10:$AB$7501,"No",'DETAIL SALES'!$C$10:$C$7501,"19") -> 0 | CY13: =COUNTIFS('DETAIL SALES'!$Q$10:$Q$7501,'FILL RATE MANDATORY STOCK'!BK13,'DETAIL SALES'!$AB$10:$AB$7501,"Full",'DETAIL SALES'!$C$10:$C$7501,"20") -> 0 | CZ13: =COUNTIFS('DETAIL SALES'!$Q$10:$Q$7501,'FILL RATE MANDATORY STOCK'!BK13,'DETAIL SALES'!$AB$10:$AB$7501,"No",'DETAIL SALES'!$C$10:$C$7501,"20") -> 0 | DA13: =COUNTIFS('DETAIL SALES'!$Q$10:$Q$7501,'FILL RATE MANDATORY STOCK'!BK13,'DETAIL SALES'!$AB$10:$AB$7501,"Full",'DETAIL SALES'!$C$10:$C$7501,"21") -> 0 | DB13: =COUNTIFS('DETAIL SALES'!$Q$10:$Q$7501,'FILL RATE MANDATORY STOCK'!BK13,'DETAIL SALES'!$AB$10:$AB$7501,"No",'DETAIL SALES'!$C$10:$C$7501,"21") -> 0 | DC13: =COUNTIFS('DETAIL SALES'!$Q$10:$Q$7501,'FILL RATE MANDATORY STOCK'!BK13,'DETAIL SALES'!$AB$10:$AB$7501,"Full",'DETAIL SALES'!$C$10:$C$7501,"22") -> 0 | DD13: =COUNTIFS('DETAIL SALES'!$Q$10:$Q$7501,'FILL RATE MANDATORY STOCK'!BK13,'DETAIL SALES'!$AB$10:$AB$7501,"No",'DETAIL SALES'!$C$10:$C$7501,"22") -> 0 | DE13: =COUNTIFS('DETAIL SALES'!$Q$10:$Q$7501,'FILL RATE MANDATORY STOCK'!BK13,'DETAIL SALES'!$AB$10:$AB$7501,"Full",'DETAIL SALES'!$C$10:$C$7501,"23") -> 0 | DF13: =COUNTIFS('DETAIL SALES'!$Q$10:$Q$7501,'FILL RATE MANDATORY STOCK'!BK13,'DETAIL SALES'!$AB$10:$AB$7501,"No",'DETAIL SALES'!$C$10:$C$7501,"23") -> 0 | DG13: =COUNTIFS('DETAIL SALES'!$Q$10:$Q$7501,'FILL RATE MANDATORY STOCK'!BK13,'DETAIL SALES'!$AB$10:$AB$7501,"Full",'DETAIL SALES'!$C$10:$C$7501,"24") -> 0 | DH13: =COUNTIFS('DETAIL SALES'!$Q$10:$Q$7501,'FILL RATE MANDATORY STOCK'!BK13,'DETAIL SALES'!$AB$10:$AB$7501,"No",'DETAIL SALES'!$C$10:$C$7501,"24") -> 0 | DI13: =COUNTIFS('DETAIL SALES'!$Q$10:$Q$7501,'FILL RATE MANDATORY STOCK'!BK13,'DETAIL SALES'!$AB$10:$AB$7501,"Full",'DETAIL SALES'!$C$10:$C$7501,"25") -> 0 | DJ13: =COUNTIFS('DETAIL SALES'!$Q$10:$Q$7501,'FILL RATE MANDATORY STOCK'!BK13,'DETAIL SALES'!$AB$10:$AB$7501,"No",'DETAIL SALES'!$C$10:$C$7501,"25") -> 0 | DK13: =COUNTIFS('DETAIL SALES'!$Q$10:$Q$7501,'FILL RATE MANDATORY STOCK'!BK13,'DETAIL SALES'!$AB$10:$AB$7501,"Full",'DETAIL SALES'!$C$10:$C$7501,"26") -> 0 | DL13: =COUNTIFS('DETAIL SALES'!$Q$10:$Q$7501,'FILL RATE MANDATORY STOCK'!BK13,'DETAIL SALES'!$AB$10:$AB$7501,"No",'DETAIL SALES'!$C$10:$C$7501,"26") -> 0 | DM13: =COUNTIFS('DETAIL SALES'!$Q$10:$Q$7501,'FILL RATE MANDATORY STOCK'!BK13,'DETAIL SALES'!$AB$10:$AB$7501,"Full",'DETAIL SALES'!$C$10:$C$7501,"27") -> 0 | DN13: =COUNTIFS('DETAIL SALES'!$Q$10:$Q$7501,'FILL RATE MANDATORY STOCK'!BK13,'DETAIL SALES'!$AB$10:$AB$7501,"No",'DETAIL SALES'!$C$10:$C$7501,"27") -> 0 | DO13: =COUNTIFS('DETAIL SALES'!$Q$10:$Q$7501,'FILL RATE MANDATORY STOCK'!BK13,'DETAIL SALES'!$AB$10:$AB$7501,"Full",'DETAIL SALES'!$C$10:$C$7501,"28") -> 0 | DP13: =COUNTIFS('DETAIL SALES'!$Q$10:$Q$7501,'FILL RATE MANDATORY STOCK'!BK13,'DETAIL SALES'!$AB$10:$AB$7501,"No",'DETAIL SALES'!$C$10:$C$7501,"28") -> 0 | DQ13: =COUNTIFS('DETAIL SALES'!$Q$10:$Q$7501,'FILL RATE MANDATORY STOCK'!BK13,'DETAIL SALES'!$AB$10:$AB$7501,"Full",'DETAIL SALES'!$C$10:$C$7501,"29") -> 0 | DR13: =COUNTIFS('DETAIL SALES'!$Q$10:$Q$7501,'FILL RATE MANDATORY STOCK'!BK13,'DETAIL SALES'!$AB$10:$AB$7501,"No",'DETAIL SALES'!$C$10:$C$7501,"29") -> 0 | DS13: =COUNTIFS('DETAIL SALES'!$Q$10:$Q$7501,'FILL RATE MANDATORY STOCK'!BK13,'DETAIL SALES'!$AB$10:$AB$7501,"Full",'DETAIL SALES'!$C$10:$C$7501,"30") -> 0 | DT13: =COUNTIFS('DETAIL SALES'!$Q$10:$Q$7501,'FILL RATE MANDATORY STOCK'!BK13,'DETAIL SALES'!$AB$10:$AB$7501,"No",'DETAIL SALES'!$C$10:$C$7501,"30") -> 0 | DU13: =COUNTIFS('DETAIL SALES'!$Q$10:$Q$7501,'FILL RATE MANDATORY STOCK'!\,'DETAIL SALES'!$AB$10:$AB$7501,"Full",'DETAIL SALES'!$C$10:$C$7501,"31") -> 0 | DV13: =COUNTIFS('DETAIL SALES'!$Q$10:$Q$7501,'FILL RATE MANDATORY STOCK'!BK13,'DETAIL SALES'!$AB$10:$AB$7501,"No",'DETAIL SALES'!$C$10:$C$7501,"31") -> 0 | DW13: =BM13+BO13+BQ13+BS13+BU13+BW13+BY13+CA13+CC13+CE13+CG13+CI13+CK13+CM13+CO13+CQ13+CS13+CU13+CW13+CY13+DA13+DC13+DE13+DG13+DI13+DK13+DM13+DO13+DQ13+DS13+DU13 -> 0 | DX13: =BN13+BP13+BR13+BT13+BV13+BX13+BZ13+CB13+CD13+CF13+CH13+CJ13+CL13+CN13+CP13+CR13+CT13+CV13+CX13+CZ13+DB13+DD13+DF13+DH13+DJ13+DL13+DN13+DP13+DR13+DT13+DV13 -> 0 | DY13: =DW13+DX13 -> 0 | DZ13: =DW13/DY13 -> #DIV/0!
A14: 5 | C14: =DAY(B14) -> 0 | D14: =MONTH(B14) -> 1 | E14: =YEAR(B14) -> 1900 | Y14: =X14*U14 -> 0 | Z14: =Y14*1.1 -> 0 | AB14: =IF(S14="","",IF(S14-U14=0,"Full","No")) | AC14: =IF(AND(S14>U14,V14=0),"Lost",IF(AND(S14>U14,V14<(S14-U14)),"Lost","")) | AD14: =IF(AND(S14>U14,V14=0),S14-U14,IF(AND(S14>U14,V14<(S14-U14)),S14-(U14+V14),"")) | AJ14: 3 | AK14: Government | AL14: Pemerintah Pusat & Daerah | AN14: PT. ARISTA JAYA NIAGA | AQ14: Partshop | AR14: =SUMIFS($Y$10:$Y$7501,$N$10:$N$7501,"Partshop",$P$10:$P$7501,"CAT.2") -> 0 | AS14: =SUMIFS($Y$10:$Y$7501,$N$10:$N$7501,"Partshop",$P$10:$P$7501,"CAT.3") -> 0 | AT14: =SUMIFS($Y$10:$Y$7501,$N$10:$N$7501,"Partshop",$P$10:$P$7501,"CAT.5") -> 0 | AU14: =SUMIFS($Y$10:$Y$7501,$N$10:$N$7501,"Partshop",$P$10:$P$7501,"OIL & ACC") -> 0 | AV14: =SUM(AR14:AU14) -> 0 | AW14: =AV14/AV15 -> #DIV/0! | BE14: =BE13+1 -> 3 | BF14: Hino Genuine Power Steering Oil ( HGPSF) 20 ltr | BG14: ALL MODEL | BH14: 0410721042 | BI14: =VLOOKUP(BH14,#REF!,8,FALSE) -> #REF! | BJ14: 5.000 & 60.000 | BK14: 1 | BL14: 0 | BM14: =COUNTIFS('DETAIL SALES'!$Q$10:$Q$7501,'FILL RATE MANDATORY STOCK'!BK14,'DETAIL SALES'!$AB$10:$AB$7501,"Full",'DETAIL SALES'!$C$10:$C$7501,"1") -> 0 | BN14: =COUNTIFS('DETAIL SALES'!$Q$10:$Q$7501,'FILL RATE MANDATORY STOCK'!BK14,'DETAIL SALES'!$AB$10:$AB$7501,"No",'DETAIL SALES'!$C$10:$C$7501,"1") -> 0 | BO14: =COUNTIFS('DETAIL SALES'!$Q$10:$Q$7501,'FILL RATE MANDATORY STOCK'!BK14,'DETAIL SALES'!$AB$10:$AB$7501,"Full",'DETAIL SALES'!$C$10:$C$7501,"2") -> 0 | BP14: =COUNTIFS('DETAIL SALES'!$Q$10:$Q$7501,'FILL RATE MANDATORY STOCK'!BK14,'DETAIL SALES'!$AB$10:$AB$7501,"No",'DETAIL SALES'!$C$10:$C$7501,"2") -> 0 | BQ14: =COUNTIFS('DETAIL SALES'!$Q$10:$Q$7501,'FILL RATE MANDATORY STOCK'!BK14,'DETAIL SALES'!$AB$10:$AB$7501,"Full",'DETAIL SALES'!$C$10:$C$7501,"3") -> 0 | BR14: =COUNTIFS('DETAIL SALES'!$Q$10:$Q$7501,'FILL RATE MANDATORY STOCK'!BK14,'DETAIL SALES'!$AB$10:$AB$7501,"No",'DETAIL SALES'!$C$10:$C$7501,"3") -> 0 | BS14: =COUNTIFS('DETAIL SALES'!$Q$10:$Q$7501,'FILL RATE MANDATORY STOCK'!BK14,'DETAIL SALES'!$AB$10:$AB$7501,"Full",'DETAIL SALES'!$C$10:$C$7501,"4") -> 0 | BT14: =COUNTIFS('DETAIL SALES'!$Q$10:$Q$7501,'FILL RATE MANDATORY STOCK'!BK14,'DETAIL SALES'!$AB$10:$AB$7501,"No",'DETAIL SALES'!$C$10:$C$7501,"4") -> 0 | BU14: =COUNTIFS('DETAIL SALES'!$Q$10:$Q$7501,'FILL RATE MANDATORY STOCK'!BK14,'DETAIL SALES'!$AB$10:$AB$7501,"Full",'DETAIL SALES'!$C$10:$C$7501,"5") -> 0 | BV14: =COUNTIFS('DETAIL SALES'!$Q$10:$Q$7501,'FILL RATE MANDATORY STOCK'!BK14,'DETAIL SALES'!$AB$10:$AB$7501,"No",'DETAIL SALES'!$C$10:$C$7501,"5") -> 0 | BW14: =COUNTIFS('DETAIL SALES'!$Q$10:$Q$7501,'FILL RATE MANDATORY STOCK'!BK14,'DETAIL SALES'!$AB$10:$AB$7501,"Full",'DETAIL SALES'!$C$10:$C$7501,"6") -> 0 | BX14: =COUNTIFS('DETAIL SALES'!$Q$10:$Q$7501,'FILL RATE MANDATORY STOCK'!BK14,'DETAIL SALES'!$AB$10:$AB$7501,"No",'DETAIL SALES'!$C$10:$C$7501,"6") -> 0 | BY14: =COUNTIFS('DETAIL SALES'!$Q$10:$Q$7501,'FILL RATE MANDATORY STOCK'!BK14,'DETAIL SALES'!$AB$10:$AB$7501,"Full",'DETAIL SALES'!$C$10:$C$7501,"7") -> 0 | BZ14: =COUNTIFS('DETAIL SALES'!$Q$10:$Q$7501,'FILL RATE MANDATORY STOCK'!BK14,'DETAIL SALES'!$AB$10:$AB$7501,"No",'DETAIL SALES'!$C$10:$C$7501,"7") -> 0 | CA14: =COUNTIFS('DETAIL SALES'!$Q$10:$Q$7501,'FILL RATE MANDATORY STOCK'!BK14,'DETAIL SALES'!$AB$10:$AB$7501,"Full",'DETAIL SALES'!$C$10:$C$7501,"8") -> 0 | CB14: =COUNTIFS('DETAIL SALES'!$Q$10:$Q$7501,'FILL RATE MANDATORY STOCK'!BK14,'DETAIL SALES'!$AB$10:$AB$7501,"No",'DETAIL SALES'!$C$10:$C$7501,"8") -> 0 | CC14: =COUNTIFS('DETAIL SALES'!$Q$10:$Q$7501,'FILL RATE MANDATORY STOCK'!BK14,'DETAIL SALES'!$AB$10:$AB$7501,"Full",'DETAIL SALES'!$C$10:$C$7501,"9") -> 0 | CD14: =COUNTIFS('DETAIL SALES'!$Q$10:$Q$7501,'FILL RATE MANDATORY STOCK'!BK14,'DETAIL SALES'!$AB$10:$AB$7501,"No",'DETAIL SALES'!$C$10:$C$7501,"9") -> 0 | CE14: =COUNTIFS('DETAIL SALES'!$Q$10:$Q$7501,'FILL RATE MANDATORY STOCK'!BK14,'DETAIL SALES'!$AB$10:$AB$7501,"Full",'DETAIL SALES'!$C$10:$C$7501,"10") -> 0 | CF14: =COUNTIFS('DETAIL SALES'!$Q$10:$Q$7501,'FILL RATE MANDATORY STOCK'!BK14,'DETAIL SALES'!$AB$10:$AB$7501,"No",'DETAIL SALES'!$C$10:$C$7501,"10") -> 0 | CG14: =COUNTIFS('DETAIL SALES'!$Q$10:$Q$7501,'FILL RATE MANDATORY STOCK'!BK14,'DETAIL SALES'!$AB$10:$AB$7501,"Full",'DETAIL SALES'!$C$10:$C$7501,"11") -> 0 | CH14: =COUNTIFS('DETAIL SALES'!$Q$10:$Q$7501,'FILL RATE MANDATORY STOCK'!BK14,'DETAIL SALES'!$AB$10:$AB$7501,"No",'DETAIL SALES'!$C$10:$C$7501,"11") -> 0 | CI14: =COUNTIFS('DETAIL SALES'!$Q$10:$Q$7501,'FILL RATE MANDATORY STOCK'!BK14,'DETAIL SALES'!$AB$10:$AB$7501,"Full",'DETAIL SALES'!$C$10:$C$7501,"12") -> 0 | CJ14: =COUNTIFS('DETAIL SALES'!$Q$10:$Q$7501,'FILL RATE MANDATORY STOCK'!BK14,'DETAIL SALES'!$AB$10:$AB$7501,"No",'DETAIL SALES'!$C$10:$C$7501,"12") -> 0 | CK14: =COUNTIFS('DETAIL SALES'!$Q$10:$Q$7501,'FILL RATE MANDATORY STOCK'!BK14,'DETAIL SALES'!$AB$10:$AB$7501,"Full",'DETAIL SALES'!$C$10:$C$7501,"13") -> 0 | CL14: =COUNTIFS('DETAIL SALES'!$Q$10:$Q$7501,'FILL RATE MANDATORY STOCK'!BK14,'DETAIL SALES'!$AB$10:$AB$7501,"No",'DETAIL SALES'!$C$10:$C$7501,"13") -> 0 | CM14: =COUNTIFS('DETAIL SALES'!$Q$10:$Q$7501,'FILL RATE MANDATORY STOCK'!BK14,'DETAIL SALES'!$AB$10:$AB$7501,"Full",'DETAIL SALES'!$C$10:$C$7501,"14") -> 0 | CN14: =COUNTIFS('DETAIL SALES'!$Q$10:$Q$7501,'FILL RATE MANDATORY STOCK'!BK14,'DETAIL SALES'!$AB$10:$AB$7501,"No",'DETAIL SALES'!$C$10:$C$7501,"14") -> 0 | CO14: =COUNTIFS('DETAIL SALES'!$Q$10:$Q$7501,'FILL RATE MANDATORY STOCK'!BK14,'DETAIL SALES'!$AB$10:$AB$7501,"Full",'DETAIL SALES'!$C$10:$C$7501,"15") -> 0 | CP14: =COUNTIFS('DETAIL SALES'!$Q$10:$Q$7501,'FILL RATE MANDATORY STOCK'!BK14,'DETAIL SALES'!$AB$10:$AB$7501,"No",'DETAIL SALES'!$C$10:$C$7501,"15") -> 0 | CQ14: =COUNTIFS('DETAIL SALES'!$Q$10:$Q$7501,'FILL RATE MANDATORY STOCK'!BK14,'DETAIL SALES'!$AB$10:$AB$7501,"Full",'DETAIL SALES'!$C$10:$C$7501,"16") -> 0 | CR14: =COUNTIFS('DETAIL SALES'!$Q$10:$Q$7501,'FILL RATE MANDATORY STOCK'!BK14,'DETAIL SALES'!$AB$10:$AB$7501,"No",'DETAIL SALES'!$C$10:$C$7501,"16") -> 0 | CS14: =COUNTIFS('DETAIL SALES'!$Q$10:$Q$7501,'FILL RATE MANDATORY STOCK'!BK14,'DETAIL SALES'!$AB$10:$AB$7501,"Full",'DETAIL SALES'!$C$10:$C$7501,"17") -> 0 | CT14: =COUNTIFS('DETAIL SALES'!$Q$10:$Q$7501,'FILL RATE MANDATORY STOCK'!BK14,'DETAIL SALES'!$AB$10:$AB$7501,"No",'DETAIL SALES'!$C$10:$C$7501,"17") -> 0 | CU14: =COUNTIFS('DETAIL SALES'!$Q$10:$Q$7501,'FILL RATE MANDATORY STOCK'!BK14,'DETAIL SALES'!$AB$10:$AB$7501,"Full",'DETAIL SALES'!$C$10:$C$7501,"18") -> 0 | CV14: =COUNTIFS('DETAIL SALES'!$Q$10:$Q$7501,'FILL RATE MANDATORY STOCK'!BK14,'DETAIL SALES'!$AB$10:$AB$7501,"No",'DETAIL SALES'!$C$10:$C$7501,"18") -> 0 | CW14: =COUNTIFS('DETAIL SALES'!$Q$10:$Q$7501,'FILL RATE MANDATORY STOCK'!BK14,'DETAIL SALES'!$AB$10:$AB$7501,"Full",'DETAIL SALES'!$C$10:$C$7501,"19") -> 0 | CX14: =COUNTIFS('DETAIL SALES'!$Q$10:$Q$7501,'FILL RATE MANDATORY STOCK'!BK14,'DETAIL SALES'!$AB$10:$AB$7501,"No",'DETAIL SALES'!$C$10:$C$7501,"19") -> 0 | CY14: =COUNTIFS('DETAIL SALES'!$Q$10:$Q$7501,'FILL RATE MANDATORY STOCK'!BK14,'DETAIL SALES'!$AB$10:$AB$7501,"Full",'DETAIL SALES'!$C$10:$C$7501,"20") -> 0 | CZ14: =COUNTIFS('DETAIL SALES'!$Q$10:$Q$7501,'FILL RATE MANDATORY STOCK'!BK14,'DETAIL SALES'!$AB$10:$AB$7501,"No",'DETAIL SALES'!$C$10:$C$7501,"20") -> 0 | DA14: =COUNTIFS('DETAIL SALES'!$Q$10:$Q$7501,'FILL RATE MANDATORY STOCK'!BK14,'DETAIL SALES'!$AB$10:$AB$7501,"Full",'DETAIL SALES'!$C$10:$C$7501,"21") -> 0 | DB14: =COUNTIFS('DETAIL SALES'!$Q$10:$Q$7501,'FILL RATE MANDATORY STOCK'!BK14,'DETAIL SALES'!$AB$10:$AB$7501,"No",'DETAIL SALES'!$C$10:$C$7501,"21") -> 0 | DC14: =COUNTIFS('DETAIL SALES'!$Q$10:$Q$7501,'FILL RATE MANDATORY STOCK'!BK14,'DETAIL SALES'!$AB$10:$AB$7501,"Full",'DETAIL SALES'!$C$10:$C$7501,"22") -> 0 | DD14: =COUNTIFS('DETAIL SALES'!$Q$10:$Q$7501,'FILL RATE MANDATORY STOCK'!BK14,'DETAIL SALES'!$AB$10:$AB$7501,"No",'DETAIL SALES'!$C$10:$C$7501,"22") -> 0 | DE14: =COUNTIFS('DETAIL SALES'!$Q$10:$Q$7501,'FILL RATE MANDATORY STOCK'!BK14,'DETAIL SALES'!$AB$10:$AB$7501,"Full",'DETAIL SALES'!$C$10:$C$7501,"23") -> 0 | DF14: =COUNTIFS('DETAIL SALES'!$Q$10:$Q$7501,'FILL RATE MANDATORY STOCK'!BK14,'DETAIL SALES'!$AB$10:$AB$7501,"No",'DETAIL SALES'!$C$10:$C$7501,"23") -> 0 | DG14: =COUNTIFS('DETAIL SALES'!$Q$10:$Q$7501,'FILL RATE MANDATORY STOCK'!BK14,'DETAIL SALES'!$AB$10:$AB$7501,"Full",'DETAIL SALES'!$C$10:$C$7501,"24") -> 0 | DH14: =COUNTIFS('DETAIL SALES'!$Q$10:$Q$7501,'FILL RATE MANDATORY STOCK'!BK14,'DETAIL SALES'!$AB$10:$AB$7501,"No",'DETAIL SALES'!$C$10:$C$7501,"24") -> 0 | DI14: =COUNTIFS('DETAIL SALES'!$Q$10:$Q$7501,'FILL RATE MANDATORY STOCK'!BK14,'DETAIL SALES'!$AB$10:$AB$7501,"Full",'DETAIL SALES'!$C$10:$C$7501,"25") -> 0 | DJ14: =COUNTIFS('DETAIL SALES'!$Q$10:$Q$7501,'FILL RATE MANDATORY STOCK'!BK14,'DETAIL SALES'!$AB$10:$AB$7501,"No",'DETAIL SALES'!$C$10:$C$7501,"25") -> 0 | DK14: =COUNTIFS('DETAIL SALES'!$Q$10:$Q$7501,'FILL RATE MANDATORY STOCK'!BK14,'DETAIL SALES'!$AB$10:$AB$7501,"Full",'DETAIL SALES'!$C$10:$C$7501,"26") -> 0 | DL14: =COUNTIFS('DETAIL SALES'!$Q$10:$Q$7501,'FILL RATE MANDATORY STOCK'!BK14,'DETAIL SALES'!$AB$10:$AB$7501,"No",'DETAIL SALES'!$C$10:$C$7501,"26") -> 0 | DM14: =COUNTIFS('DETAIL SALES'!$Q$10:$Q$7501,'FILL RATE MANDATORY STOCK'!BK14,'DETAIL SALES'!$AB$10:$AB$7501,"Full",'DETAIL SALES'!$C$10:$C$7501,"27") -> 0 | DN14: =COUNTIFS('DETAIL SALES'!$Q$10:$Q$7501,'FILL RATE MANDATORY STOCK'!BK14,'DETAIL SALES'!$AB$10:$AB$7501,"No",'DETAIL SALES'!$C$10:$C$7501,"27") -> 0 | DO14: =COUNTIFS('DETAIL SALES'!$Q$10:$Q$7501,'FILL RATE MANDATORY STOCK'!BK14,'DETAIL SALES'!$AB$10:$AB$7501,"Full",'DETAIL SALES'!$C$10:$C$7501,"28") -> 0 | DP14: =COUNTIFS('DETAIL SALES'!$Q$10:$Q$7501,'FILL RATE MANDATORY STOCK'!BK14,'DETAIL SALES'!$AB$10:$AB$7501,"No",'DETAIL SALES'!$C$10:$C$7501,"28") -> 0 | DQ14: =COUNTIFS('DETAIL SALES'!$Q$10:$Q$7501,'FILL RATE MANDATORY STOCK'!BK14,'DETAIL SALES'!$AB$10:$AB$7501,"Full",'DETAIL SALES'!$C$10:$C$7501,"29") -> 0 | DR14: =COUNTIFS('DETAIL SALES'!$Q$10:$Q$7501,'FILL RATE MANDATORY STOCK'!BK14,'DETAIL SALES'!$AB$10:$AB$7501,"No",'DETAIL SALES'!$C$10:$C$7501,"29") -> 0 | DS14: =COUNTIFS('DETAIL SALES'!$Q$10:$Q$7501,'FILL RATE MANDATORY STOCK'!BK14,'DETAIL SALES'!$AB$10:$AB$7501,"Full",'DETAIL SALES'!$C$10:$C$7501,"30") -> 0 | DT14: =COUNTIFS('DETAIL SALES'!$Q$10:$Q$7501,'FILL RATE MANDATORY STOCK'!BK14,'DETAIL SALES'!$AB$10:$AB$7501,"No",'DETAIL SALES'!$C$10:$C$7501,"30") -> 0 | DU14: =COUNTIFS('DETAIL SALES'!$Q$10:$Q$7501,'FILL RATE MANDATORY STOCK'!\,'DETAIL SALES'!$AB$10:$AB$7501,"Full",'DETAIL SALES'!$C$10:$C$7501,"31") -> 0 | DV14: =COUNTIFS('DETAIL SALES'!$Q$10:$Q$7501,'FILL RATE MANDATORY STOCK'!BK14,'DETAIL SALES'!$AB$10:$AB$7501,"No",'DETAIL SALES'!$C$10:$C$7501,"31") -> 0 | DW14: =BM14+BO14+BQ14+BS14+BU14+BW14+BY14+CA14+CC14+CE14+CG14+CI14+CK14+CM14+CO14+CQ14+CS14+CU14+CW14+CY14+DA14+DC14+DE14+DG14+DI14+DK14+DM14+DO14+DQ14+DS14+DU14 -> 0 | DX14: =BN14+BP14+BR14+BT14+BV14+BX14+BZ14+CB14+CD14+CF14+CH14+CJ14+CL14+CN14+CP14+CR14+CT14+CV14+CX14+CZ14+DB14+DD14+DF14+DH14+DJ14+DL14+DN14+DP14+DR14+DT14+DV14 -> 0 | DY14: =DW14+DX14 -> 0 | DZ14: =DW14/DY14 -> #DIV/0!
A15: 6 | C15: =DAY(B15) -> 0 | D15: =MONTH(B15) -> 1 | E15: =YEAR(B15) -> 1900 | Y15: =X15*U15 -> 0 | Z15: =Y15*1.1 -> 0 | AB15: =IF(S15="","",IF(S15-U15=0,"Full","No")) | AC15: =IF(AND(S15>U15,V15=0),"Lost",IF(AND(S15>U15,V15<(S15-U15)),"Lost","")) | AD15: =IF(AND(S15>U15,V15=0),S15-U15,IF(AND(S15>U15,V15<(S15-U15)),S15-(U15+V15),"")) | AJ15: 4 | AK15: General Cargo | AL15: FedEx | AN15: PT. ARMINDO PERKASA | AQ15: Total | AR15: =SUM(AR12:AR14) -> 0 | AS15: =SUM(AS12:AS14) -> 0 | AT15: =SUM(AT12:AT14) -> 0 | AU15: =SUM(AU12:AU14) -> 0 | AV15: =SUM(AV12:AV14) -> 0 | AW15: =SUM(AW12:AW14) -> #DIV/0! | BE15: =BE14+1 -> 4 | BF15: HGO Oil | BG15: ALL MODEL | BH15: 041001001 | BI15: =VLOOKUP(BH15,#REF!,8,FALSE) -> #REF! | BJ15: 20000 | BK15: 12.7 | BL15: 0 | BM15: =COUNTIFS('DETAIL SALES'!$Q$10:$Q$7501,'FILL RATE MANDATORY STOCK'!BK15,'DETAIL SALES'!$AB$10:$AB$7501,"Full",'DETAIL SALES'!$C$10:$C$7501,"1") -> 0 | BN15: =COUNTIFS('DETAIL SALES'!$Q$10:$Q$7501,'FILL RATE MANDATORY STOCK'!BK15,'DETAIL SALES'!$AB$10:$AB$7501,"No",'DETAIL SALES'!$C$10:$C$7501,"1") -> 0 | BO15: =COUNTIFS('DETAIL SALES'!$Q$10:$Q$7501,'FILL RATE MANDATORY STOCK'!BK15,'DETAIL SALES'!$AB$10:$AB$7501,"Full",'DETAIL SALES'!$C$10:$C$7501,"2") -> 0 | BP15: =COUNTIFS('DETAIL SALES'!$Q$10:$Q$7501,'FILL RATE MANDATORY STOCK'!BK15,'DETAIL SALES'!$AB$10:$AB$7501,"No",'DETAIL SALES'!$C$10:$C$7501,"2") -> 0 | BQ15: =COUNTIFS('DETAIL SALES'!$Q$10:$Q$7501,'FILL RATE MANDATORY STOCK'!BK15,'DETAIL SALES'!$AB$10:$AB$7501,"Full",'DETAIL SALES'!$C$10:$C$7501,"3") -> 0 | BR15: =COUNTIFS('DETAIL SALES'!$Q$10:$Q$7501,'FILL RATE MANDATORY STOCK'!BK15,'DETAIL SALES'!$AB$10:$AB$7501,"No",'DETAIL SALES'!$C$10:$C$7501,"3") -> 0 | BS15: =COUNTIFS('DETAIL SALES'!$Q$10:$Q$7501,'FILL RATE MANDATORY STOCK'!BK15,'DETAIL SALES'!$AB$10:$AB$7501,"Full",'DETAIL SALES'!$C$10:$C$7501,"4") -> 0 | BT15: =COUNTIFS('DETAIL SALES'!$Q$10:$Q$7501,'FILL RATE MANDATORY STOCK'!BK15,'DETAIL SALES'!$AB$10:$AB$7501,"No",'DETAIL SALES'!$C$10:$C$7501,"4") -> 0 | BU15: =COUNTIFS('DETAIL SALES'!$Q$10:$Q$7501,'FILL RATE MANDATORY STOCK'!BK15,'DETAIL SALES'!$AB$10:$AB$7501,"Full",'DETAIL SALES'!$C$10:$C$7501,"5") -> 0 | BV15: =COUNTIFS('DETAIL SALES'!$Q$10:$Q$7501,'FILL RATE MANDATORY STOCK'!BK15,'DETAIL SALES'!$AB$10:$AB$7501,"No",'DETAIL SALES'!$C$10:$C$7501,"5") -> 0 | BW15: =COUNTIFS('DETAIL SALES'!$Q$10:$Q$7501,'FILL RATE MANDATORY STOCK'!BK15,'DETAIL SALES'!$AB$10:$AB$7501,"Full",'DETAIL SALES'!$C$10:$C$7501,"6") -> 0 | BX15: =COUNTIFS('DETAIL SALES'!$Q$10:$Q$7501,'FILL RATE MANDATORY STOCK'!BK15,'DETAIL SALES'!$AB$10:$AB$7501,"No",'DETAIL SALES'!$C$10:$C$7501,"6") -> 0 | BY15: =COUNTIFS('DETAIL SALES'!$Q$10:$Q$7501,'FILL RATE MANDATORY STOCK'!BK15,'DETAIL SALES'!$AB$10:$AB$7501,"Full",'DETAIL SALES'!$C$10:$C$7501,"7") -> 0 | BZ15: =COUNTIFS('DETAIL SALES'!$Q$10:$Q$7501,'FILL RATE MANDATORY STOCK'!BK15,'DETAIL SALES'!$AB$10:$AB$7501,"No",'DETAIL SALES'!$C$10:$C$7501,"7") -> 0 | CA15: =COUNTIFS('DETAIL SALES'!$Q$10:$Q$7501,'FILL RATE MANDATORY STOCK'!BK15,'DETAIL SALES'!$AB$10:$AB$7501,"Full",'DETAIL SALES'!$C$10:$C$7501,"8") -> 0 | CB15: =COUNTIFS('DETAIL SALES'!$Q$10:$Q$7501,'FILL RATE MANDATORY STOCK'!BK15,'DETAIL SALES'!$AB$10:$AB$7501,"No",'DETAIL SALES'!$C$10:$C$7501,"8") -> 0 | CC15: =COUNTIFS('DETAIL SALES'!$Q$10:$Q$7501,'FILL RATE MANDATORY STOCK'!BK15,'DETAIL SALES'!$AB$10:$AB$7501,"Full",'DETAIL SALES'!$C$10:$C$7501,"9") -> 0 | CD15: =COUNTIFS('DETAIL SALES'!$Q$10:$Q$7501,'FILL RATE MANDATORY STOCK'!BK15,'DETAIL SALES'!$AB$10:$AB$7501,"No",'DETAIL SALES'!$C$10:$C$7501,"9") -> 0 | CE15: =COUNTIFS('DETAIL SALES'!$Q$10:$Q$7501,'FILL RATE MANDATORY STOCK'!BK15,'DETAIL SALES'!$AB$10:$AB$7501,"Full",'DETAIL SALES'!$C$10:$C$7501,"10") -> 0 | CF15: =COUNTIFS('DETAIL SALES'!$Q$10:$Q$7501,'FILL RATE MANDATORY STOCK'!BK15,'DETAIL SALES'!$AB$10:$AB$7501,"No",'DETAIL SALES'!$C$10:$C$7501,"10") -> 0 | CG15: =COUNTIFS('DETAIL SALES'!$Q$10:$Q$7501,'FILL RATE MANDATORY STOCK'!BK15,'DETAIL SALES'!$AB$10:$AB$7501,"Full",'DETAIL SALES'!$C$10:$C$7501,"11") -> 0 | CH15: =COUNTIFS('DETAIL SALES'!$Q$10:$Q$7501,'FILL RATE MANDATORY STOCK'!BK15,'DETAIL SALES'!$AB$10:$AB$7501,"No",'DETAIL SALES'!$C$10:$C$7501,"11") -> 0 | CI15: =COUNTIFS('DETAIL SALES'!$Q$10:$Q$7501,'FILL RATE MANDATORY STOCK'!BK15,'DETAIL SALES'!$AB$10:$AB$7501,"Full",'DETAIL SALES'!$C$10:$C$7501,"12") -> 0 | CJ15: =COUNTIFS('DETAIL SALES'!$Q$10:$Q$7501,'FILL RATE MANDATORY STOCK'!BK15,'DETAIL SALES'!$AB$10:$AB$7501,"No",'DETAIL SALES'!$C$10:$C$7501,"12") -> 0 | CK15: =COUNTIFS('DETAIL SALES'!$Q$10:$Q$7501,'FILL RATE MANDATORY STOCK'!BK15,'DETAIL SALES'!$AB$10:$AB$7501,"Full",'DETAIL SALES'!$C$10:$C$7501,"13") -> 0 | CL15: =COUNTIFS('DETAIL SALES'!$Q$10:$Q$7501,'FILL RATE MANDATORY STOCK'!BK15,'DETAIL SALES'!$AB$10:$AB$7501,"No",'DETAIL SALES'!$C$10:$C$7501,"13") -> 0 | CM15: =COUNTIFS('DETAIL SALES'!$Q$10:$Q$7501,'FILL RATE MANDATORY STOCK'!BK15,'DETAIL SALES'!$AB$10:$AB$7501,"Full",'DETAIL SALES'!$C$10:$C$7501,"14") -> 0 | CN15: =COUNTIFS('DETAIL SALES'!$Q$10:$Q$7501,'FILL RATE MANDATORY STOCK'!BK15,'DETAIL SALES'!$AB$10:$AB$7501,"No",'DETAIL SALES'!$C$10:$C$7501,"14") -> 0 | CO15: =COUNTIFS('DETAIL SALES'!$Q$10:$Q$7501,'FILL RATE MANDATORY STOCK'!BK15,'DETAIL SALES'!$AB$10:$AB$7501,"Full",'DETAIL SALES'!$C$10:$C$7501,"15") -> 0 | CP15: =COUNTIFS('DETAIL SALES'!$Q$10:$Q$7501,'FILL RATE MANDATORY STOCK'!BK15,'DETAIL SALES'!$AB$10:$AB$7501,"No",'DETAIL SALES'!$C$10:$C$7501,"15") -> 0 | CQ15: =COUNTIFS('DETAIL SALES'!$Q$10:$Q$7501,'FILL RATE MANDATORY STOCK'!BK15,'DETAIL SALES'!$AB$10:$AB$7501,"Full",'DETAIL SALES'!$C$10:$C$7501,"16") -> 0 | CR15: =COUNTIFS('DETAIL SALES'!$Q$10:$Q$7501,'FILL RATE MANDATORY STOCK'!BK15,'DETAIL SALES'!$AB$10:$AB$7501,"No",'DETAIL SALES'!$C$10:$C$7501,"16") -> 0 | CS15: =COUNTIFS('DETAIL SALES'!$Q$10:$Q$7501,'FILL RATE MANDATORY STOCK'!BK15,'DETAIL SALES'!$AB$10:$AB$7501,"Full",'DETAIL SALES'!$C$10:$C$7501,"17") -> 0 | CT15: =COUNTIFS('DETAIL SALES'!$Q$10:$Q$7501,'FILL RATE MANDATORY STOCK'!BK15,'DETAIL SALES'!$AB$10:$AB$7501,"No",'DETAIL SALES'!$C$10:$C$7501,"17") -> 0 | CU15: =COUNTIFS('DETAIL SALES'!$Q$10:$Q$7501,'FILL RATE MANDATORY STOCK'!BK15,'DETAIL SALES'!$AB$10:$AB$7501,"Full",'DETAIL SALES'!$C$10:$C$7501,"18") -> 0 | CV15: =COUNTIFS('DETAIL SALES'!$Q$10:$Q$7501,'FILL RATE MANDATORY STOCK'!BK15,'DETAIL SALES'!$AB$10:$AB$7501,"No",'DETAIL SALES'!$C$10:$C$7501,"18") -> 0 | CW15: =COUNTIFS('DETAIL SALES'!$Q$10:$Q$7501,'FILL RATE MANDATORY STOCK'!BK15,'DETAIL SALES'!$AB$10:$AB$7501,"Full",'DETAIL SALES'!$C$10:$C$7501,"19") -> 0 | CX15: =COUNTIFS('DETAIL SALES'!$Q$10:$Q$7501,'FILL RATE MANDATORY STOCK'!BK15,'DETAIL SALES'!$AB$10:$AB$7501,"No",'DETAIL SALES'!$C$10:$C$7501,"19") -> 0 | CY15: =COUNTIFS('DETAIL SALES'!$Q$10:$Q$7501,'FILL RATE MANDATORY STOCK'!BK15,'DETAIL SALES'!$AB$10:$AB$7501,"Full",'DETAIL SALES'!$C$10:$C$7501,"20") -> 0 | CZ15: =COUNTIFS('DETAIL SALES'!$Q$10:$Q$7501,'FILL RATE MANDATORY STOCK'!BK15,'DETAIL SALES'!$AB$10:$AB$7501,"No",'DETAIL SALES'!$C$10:$C$7501,"20") -> 0 | DA15: =COUNTIFS('DETAIL SALES'!$Q$10:$Q$7501,'FILL RATE MANDATORY STOCK'!BK15,'DETAIL SALES'!$AB$10:$AB$7501,"Full",'DETAIL SALES'!$C$10:$C$7501,"21") -> 0 | DB15: =COUNTIFS('DETAIL SALES'!$Q$10:$Q$7501,'FILL RATE MANDATORY STOCK'!BK15,'DETAIL SALES'!$AB$10:$AB$7501,"No",'DETAIL SALES'!$C$10:$C$7501,"21") -> 0 | DC15: =COUNTIFS('DETAIL SALES'!$Q$10:$Q$7501,'FILL RATE MANDATORY STOCK'!BK15,'DETAIL SALES'!$AB$10:$AB$7501,"Full",'DETAIL SALES'!$C$10:$C$7501,"22") -> 0 | DD15: =COUNTIFS('DETAIL SALES'!$Q$10:$Q$7501,'FILL RATE MANDATORY STOCK'!BK15,'DETAIL SALES'!$AB$10:$AB$7501,"No",'DETAIL SALES'!$C$10:$C$7501,"22") -> 0 | DE15: =COUNTIFS('DETAIL SALES'!$Q$10:$Q$7501,'FILL RATE MANDATORY STOCK'!BK15,'DETAIL SALES'!$AB$10:$AB$7501,"Full",'DETAIL SALES'!$C$10:$C$7501,"23") -> 0 | DF15: =COUNTIFS('DETAIL SALES'!$Q$10:$Q$7501,'FILL RATE MANDATORY STOCK'!BK15,'DETAIL SALES'!$AB$10:$AB$7501,"No",'DETAIL SALES'!$C$10:$C$7501,"23") -> 0 | DG15: =COUNTIFS('DETAIL SALES'!$Q$10:$Q$7501,'FILL RATE MANDATORY STOCK'!BK15,'DETAIL SALES'!$AB$10:$AB$7501,"Full",'DETAIL SALES'!$C$10:$C$7501,"24") -> 0 | DH15: =COUNTIFS('DETAIL SALES'!$Q$10:$Q$7501,'FILL RATE MANDATORY STOCK'!BK15,'DETAIL SALES'!$AB$10:$AB$7501,"No",'DETAIL SALES'!$C$10:$C$7501,"24") -> 0 | DI15: =COUNTIFS('DETAIL SALES'!$Q$10:$Q$7501,'FILL RATE MANDATORY STOCK'!BK15,'DETAIL SALES'!$AB$10:$AB$7501,"Full",'DETAIL SALES'!$C$10:$C$7501,"25") -> 0 | DJ15: =COUNTIFS('DETAIL SALES'!$Q$10:$Q$7501,'FILL RATE MANDATORY STOCK'!BK15,'DETAIL SALES'!$AB$10:$AB$7501,"No",'DETAIL SALES'!$C$10:$C$7501,"25") -> 0 | DK15: =COUNTIFS('DETAIL SALES'!$Q$10:$Q$7501,'FILL RATE MANDATORY STOCK'!BK15,'DETAIL SALES'!$AB$10:$AB$7501,"Full",'DETAIL SALES'!$C$10:$C$7501,"26") -> 0 | DL15: =COUNTIFS('DETAIL SALES'!$Q$10:$Q$7501,'FILL RATE MANDATORY STOCK'!BK15,'DETAIL SALES'!$AB$10:$AB$7501,"No",'DETAIL SALES'!$C$10:$C$7501,"26") -> 0 | DM15: =COUNTIFS('DETAIL SALES'!$Q$10:$Q$7501,'FILL RATE MANDATORY STOCK'!BK15,'DETAIL SALES'!$AB$10:$AB$7501,"Full",'DETAIL SALES'!$C$10:$C$7501,"27") -> 0 | DN15: =COUNTIFS('DETAIL SALES'!$Q$10:$Q$7501,'FILL RATE MANDATORY STOCK'!BK15,'DETAIL SALES'!$AB$10:$AB$7501,"No",'DETAIL SALES'!$C$10:$C$7501,"27") -> 0 | DO15: =COUNTIFS('DETAIL SALES'!$Q$10:$Q$7501,'FILL RATE MANDATORY STOCK'!BK15,'DETAIL SALES'!$AB$10:$AB$7501,"Full",'DETAIL SALES'!$C$10:$C$7501,"28") -> 0 | DP15: =COUNTIFS('DETAIL SALES'!$Q$10:$Q$7501,'FILL RATE MANDATORY STOCK'!BK15,'DETAIL SALES'!$AB$10:$AB$7501,"No",'DETAIL SALES'!$C$10:$C$7501,"28") -> 0 | DQ15: =COUNTIFS('DETAIL SALES'!$Q$10:$Q$7501,'FILL RATE MANDATORY STOCK'!BK15,'DETAIL SALES'!$AB$10:$AB$7501,"Full",'DETAIL SALES'!$C$10:$C$7501,"29") -> 0 | DR15: =COUNTIFS('DETAIL SALES'!$Q$10:$Q$7501,'FILL RATE MANDATORY STOCK'!BK15,'DETAIL SALES'!$AB$10:$AB$7501,"No",'DETAIL SALES'!$C$10:$C$7501,"29") -> 0 | DS15: =COUNTIFS('DETAIL SALES'!$Q$10:$Q$7501,'FILL RATE MANDATORY STOCK'!BK15,'DETAIL SALES'!$AB$10:$AB$7501,"Full",'DETAIL SALES'!$C$10:$C$7501,"30") -> 0 | DT15: =COUNTIFS('DETAIL SALES'!$Q$10:$Q$7501,'FILL RATE MANDATORY STOCK'!BK15,'DETAIL SALES'!$AB$10:$AB$7501,"No",'DETAIL SALES'!$C$10:$C$7501,"30") -> 0 | DU15: =COUNTIFS('DETAIL SALES'!$Q$10:$Q$7501,'FILL RATE MANDATORY STOCK'!\,'DETAIL SALES'!$AB$10:$AB$7501,"Full",'DETAIL SALES'!$C$10:$C$7501,"31") -> 0 | DV15: =COUNTIFS('DETAIL SALES'!$Q$10:$Q$7501,'FILL RATE MANDATORY STOCK'!BK15,'DETAIL SALES'!$AB$10:$AB$7501,"No",'DETAIL SALES'!$C$10:$C$7501,"31") -> 0 | DW15: =BM15+BO15+BQ15+BS15+BU15+BW15+BY15+CA15+CC15+CE15+CG15+CI15+CK15+CM15+CO15+CQ15+CS15+CU15+CW15+CY15+DA15+DC15+DE15+DG15+DI15+DK15+DM15+DO15+DQ15+DS15+DU15 -> 0 | DX15: =BN15+BP15+BR15+BT15+BV15+BX15+BZ15+CB15+CD15+CF15+CH15+CJ15+CL15+CN15+CP15+CR15+CT15+CV15+CX15+CZ15+DB15+DD15+DF15+DH15+DJ15+DL15+DN15+DP15+DR15+DT15+DV15 -> 0 | DY15: =DW15+DX15 -> 0 | DZ15: =DW15/DY15 -> #DIV/0!
A16: 7 | C16: =DAY(B16) -> 0 | D16: =MONTH(B16) -> 1 | E16: =YEAR(B16) -> 1900 | Y16: =X16*U16 -> 0 | Z16: =Y16*1.1 -> 0 | AB16: =IF(S16="","",IF(S16-U16=0,"Full","No")) | AC16: =IF(AND(S16>U16,V16=0),"Lost",IF(AND(S16>U16,V16<(S16-U16)),"Lost","")) | AD16: =IF(AND(S16>U16,V16=0),S16-U16,IF(AND(S16>U16,V16<(S16-U16)),S16-(U16+V16),"")) | AJ16: 5 | AK16: Cement | AN16: PT. AUTO MOBIL PRIMA | AQ16: % | AR16: =AR15/$O$6 -> #DIV/0! | AS16: =AS15/$O$6 -> #DIV/0! | AT16: =AT15/$O$6 -> #DIV/0! | AU16: =AU15/$O$6 -> #DIV/0! | AV16: =AV15/$O$6 -> #DIV/0! | BE16: =BE15+1 -> 5 | BF16: Brake Fluid 1Lt | BG16: ALL MODEL | BH16: 041101001L | BI16: =VLOOKUP(BH16,#REF!,8,FALSE) -> #REF! | BJ16: 60000 | BK16: 1 | BL16: 34.666667 | BM16: =COUNTIFS('DETAIL SALES'!$Q$10:$Q$7501,'FILL RATE MANDATORY STOCK'!BK16,'DETAIL SALES'!$AB$10:$AB$7501,"Full",'DETAIL SALES'!$C$10:$C$7501,"1") -> 0 | BN16: =COUNTIFS('DETAIL SALES'!$Q$10:$Q$7501,'FILL RATE MANDATORY STOCK'!BK16,'DETAIL SALES'!$AB$10:$AB$7501,"No",'DETAIL SALES'!$C$10:$C$7501,"1") -> 0 | BO16: =COUNTIFS('DETAIL SALES'!$Q$10:$Q$7501,'FILL RATE MANDATORY STOCK'!BK16,'DETAIL SALES'!$AB$10:$AB$7501,"Full",'DETAIL SALES'!$C$10:$C$7501,"2") -> 0 | BP16: =COUNTIFS('DETAIL SALES'!$Q$10:$Q$7501,'FILL RATE MANDATORY STOCK'!BK16,'DETAIL SALES'!$AB$10:$AB$7501,"No",'DETAIL SALES'!$C$10:$C$7501,"2") -> 0 | BQ16: =COUNTIFS('DETAIL SALES'!$Q$10:$Q$7501,'FILL RATE MANDATORY STOCK'!BK16,'DETAIL SALES'!$AB$10:$AB$7501,"Full",'DETAIL SALES'!$C$10:$C$7501,"3") -> 0 | BR16: =COUNTIFS('DETAIL SALES'!$Q$10:$Q$7501,'FILL RATE MANDATORY STOCK'!BK16,'DETAIL SALES'!$AB$10:$AB$7501,"No",'DETAIL SALES'!$C$10:$C$7501,"3") -> 0 | BS16: =COUNTIFS('DETAIL SALES'!$Q$10:$Q$7501,'FILL RATE MANDATORY STOCK'!BK16,'DETAIL SALES'!$AB$10:$AB$7501,"Full",'DETAIL SALES'!$C$10:$C$7501,"4") -> 0 | BT16: =COUNTIFS('DETAIL SALES'!$Q$10:$Q$7501,'FILL RATE MANDATORY STOCK'!BK16,'DETAIL SALES'!$AB$10:$AB$7501,"No",'DETAIL SALES'!$C$10:$C$7501,"4") -> 0 | BU16: =COUNTIFS('DETAIL SALES'!$Q$10:$Q$7501,'FILL RATE MANDATORY STOCK'!BK16,'DETAIL SALES'!$AB$10:$AB$7501,"Full",'DETAIL SALES'!$C$10:$C$7501,"5") -> 0 | BV16: =COUNTIFS('DETAIL SALES'!$Q$10:$Q$7501,'FILL RATE MANDATORY STOCK'!BK16,'DETAIL SALES'!$AB$10:$AB$7501,"No",'DETAIL SALES'!$C$10:$C$7501,"5") -> 0 | BW16: =COUNTIFS('DETAIL SALES'!$Q$10:$Q$7501,'FILL RATE MANDATORY STOCK'!BK16,'DETAIL SALES'!$AB$10:$AB$7501,"Full",'DETAIL SALES'!$C$10:$C$7501,"6") -> 0 | BX16: =COUNTIFS('DETAIL SALES'!$Q$10:$Q$7501,'FILL RATE MANDATORY STOCK'!BK16,'DETAIL SALES'!$AB$10:$AB$7501,"No",'DETAIL SALES'!$C$10:$C$7501,"6") -> 0 | BY16: =COUNTIFS('DETAIL SALES'!$Q$10:$Q$7501,'FILL RATE MANDATORY STOCK'!BK16,'DETAIL SALES'!$AB$10:$AB$7501,"Full",'DETAIL SALES'!$C$10:$C$7501,"7") -> 0 | BZ16: =COUNTIFS('DETAIL SALES'!$Q$10:$Q$7501,'FILL RATE MANDATORY STOCK'!BK16,'DETAIL SALES'!$AB$10:$AB$7501,"No",'DETAIL SALES'!$C$10:$C$7501,"7") -> 0 | CA16: =COUNTIFS('DETAIL SALES'!$Q$10:$Q$7501,'FILL RATE MANDATORY STOCK'!BK16,'DETAIL SALES'!$AB$10:$AB$7501,"Full",'DETAIL SALES'!$C$10:$C$7501,"8") -> 0 | CB16: =COUNTIFS('DETAIL SALES'!$Q$10:$Q$7501,'FILL RATE MANDATORY STOCK'!BK16,'DETAIL SALES'!$AB$10:$AB$7501,"No",'DETAIL SALES'!$C$10:$C$7501,"8") -> 0 | CC16: =COUNTIFS('DETAIL SALES'!$Q$10:$Q$7501,'FILL RATE MANDATORY STOCK'!BK16,'DETAIL SALES'!$AB$10:$AB$7501,"Full",'DETAIL SALES'!$C$10:$C$7501,"9") -> 0 | CD16: =COUNTIFS('DETAIL SALES'!$Q$10:$Q$7501,'FILL RATE MANDATORY STOCK'!BK16,'DETAIL SALES'!$AB$10:$AB$7501,"No",'DETAIL SALES'!$C$10:$C$7501,"9") -> 0 | CE16: =COUNTIFS('DETAIL SALES'!$Q$10:$Q$7501,'FILL RATE MANDATORY STOCK'!BK16,'DETAIL SALES'!$AB$10:$AB$7501,"Full",'DETAIL SALES'!$C$10:$C$7501,"10") -> 0 | CF16: =COUNTIFS('DETAIL SALES'!$Q$10:$Q$7501,'FILL RATE MANDATORY STOCK'!BK16,'DETAIL SALES'!$AB$10:$AB$7501,"No",'DETAIL SALES'!$C$10:$C$7501,"10") -> 0 | CG16: =COUNTIFS('DETAIL SALES'!$Q$10:$Q$7501,'FILL RATE MANDATORY STOCK'!BK16,'DETAIL SALES'!$AB$10:$AB$7501,"Full",'DETAIL SALES'!$C$10:$C$7501,"11") -> 0 | CH16: =COUNTIFS('DETAIL SALES'!$Q$10:$Q$7501,'FILL RATE MANDATORY STOCK'!BK16,'DETAIL SALES'!$AB$10:$AB$7501,"No",'DETAIL SALES'!$C$10:$C$7501,"11") -> 0 | CI16: =COUNTIFS('DETAIL SALES'!$Q$10:$Q$7501,'FILL RATE MANDATORY STOCK'!BK16,'DETAIL SALES'!$AB$10:$AB$7501,"Full",'DETAIL SALES'!$C$10:$C$7501,"12") -> 0 | CJ16: =COUNTIFS('DETAIL SALES'!$Q$10:$Q$7501,'FILL RATE MANDATORY STOCK'!BK16,'DETAIL SALES'!$AB$10:$AB$7501,"No",'DETAIL SALES'!$C$10:$C$7501,"12") -> 0 | CK16: =COUNTIFS('DETAIL SALES'!$Q$10:$Q$7501,'FILL RATE MANDATORY STOCK'!BK16,'DETAIL SALES'!$AB$10:$AB$7501,"Full",'DETAIL SALES'!$C$10:$C$7501,"13") -> 0 | CL16: =COUNTIFS('DETAIL SALES'!$Q$10:$Q$7501,'FILL RATE MANDATORY STOCK'!BK16,'DETAIL SALES'!$AB$10:$AB$7501,"No",'DETAIL SALES'!$C$10:$C$7501,"13") -> 0 | CM16: =COUNTIFS('DETAIL SALES'!$Q$10:$Q$7501,'FILL RATE MANDATORY STOCK'!BK16,'DETAIL SALES'!$AB$10:$AB$7501,"Full",'DETAIL SALES'!$C$10:$C$7501,"14") -> 0 | CN16: =COUNTIFS('DETAIL SALES'!$Q$10:$Q$7501,'FILL RATE MANDATORY STOCK'!BK16,'DETAIL SALES'!$AB$10:$AB$7501,"No",'DETAIL SALES'!$C$10:$C$7501,"14") -> 0 | CO16: =COUNTIFS('DETAIL SALES'!$Q$10:$Q$7501,'FILL RATE MANDATORY STOCK'!BK16,'DETAIL SALES'!$AB$10:$AB$7501,"Full",'DETAIL SALES'!$C$10:$C$7501,"15") -> 0 | CP16: =COUNTIFS('DETAIL SALES'!$Q$10:$Q$7501,'FILL RATE MANDATORY STOCK'!BK16,'DETAIL SALES'!$AB$10:$AB$7501,"No",'DETAIL SALES'!$C$10:$C$7501,"15") -> 0 | CQ16: =COUNTIFS('DETAIL SALES'!$Q$10:$Q$7501,'FILL RATE MANDATORY STOCK'!BK16,'DETAIL SALES'!$AB$10:$AB$7501,"Full",'DETAIL SALES'!$C$10:$C$7501,"16") -> 0 | CR16: =COUNTIFS('DETAIL SALES'!$Q$10:$Q$7501,'FILL RATE MANDATORY STOCK'!BK16,'DETAIL SALES'!$AB$10:$AB$7501,"No",'DETAIL SALES'!$C$10:$C$7501,"16") -> 0 | CS16: =COUNTIFS('DETAIL SALES'!$Q$10:$Q$7501,'FILL RATE MANDATORY STOCK'!BK16,'DETAIL SALES'!$AB$10:$AB$7501,"Full",'DETAIL SALES'!$C$10:$C$7501,"17") -> 0 | CT16: =COUNTIFS('DETAIL SALES'!$Q$10:$Q$7501,'FILL RATE MANDATORY STOCK'!BK16,'DETAIL SALES'!$AB$10:$AB$7501,"No",'DETAIL SALES'!$C$10:$C$7501,"17") -> 0 | CU16: =COUNTIFS('DETAIL SALES'!$Q$10:$Q$7501,'FILL RATE MANDATORY STOCK'!BK16,'DETAIL SALES'!$AB$10:$AB$7501,"Full",'DETAIL SALES'!$C$10:$C$7501,"18") -> 0 | CV16: =COUNTIFS('DETAIL SALES'!$Q$10:$Q$7501,'FILL RATE MANDATORY STOCK'!BK16,'DETAIL SALES'!$AB$10:$AB$7501,"No",'DETAIL SALES'!$C$10:$C$7501,"18") -> 0 | CW16: =COUNTIFS('DETAIL SALES'!$Q$10:$Q$7501,'FILL RATE MANDATORY STOCK'!BK16,'DETAIL SALES'!$AB$10:$AB$7501,"Full",'DETAIL SALES'!$C$10:$C$7501,"19") -> 0 | CX16: =COUNTIFS('DETAIL SALES'!$Q$10:$Q$7501,'FILL RATE MANDATORY STOCK'!BK16,'DETAIL SALES'!$AB$10:$AB$7501,"No",'DETAIL SALES'!$C$10:$C$7501,"19") -> 0 | CY16: =COUNTIFS('DETAIL SALES'!$Q$10:$Q$7501,'FILL RATE MANDATORY STOCK'!BK16,'DETAIL SALES'!$AB$10:$AB$7501,"Full",'DETAIL SALES'!$C$10:$C$7501,"20") -> 0 | CZ16: =COUNTIFS('DETAIL SALES'!$Q$10:$Q$7501,'FILL RATE MANDATORY STOCK'!BK16,'DETAIL SALES'!$AB$10:$AB$7501,"No",'DETAIL SALES'!$C$10:$C$7501,"20") -> 0 | DA16: =COUNTIFS('DETAIL SALES'!$Q$10:$Q$7501,'FILL RATE MANDATORY STOCK'!BK16,'DETAIL SALES'!$AB$10:$AB$7501,"Full",'DETAIL SALES'!$C$10:$C$7501,"21") -> 0 | DB16: =COUNTIFS('DETAIL SALES'!$Q$10:$Q$7501,'FILL RATE MANDATORY STOCK'!BK16,'DETAIL SALES'!$AB$10:$AB$7501,"No",'DETAIL SALES'!$C$10:$C$7501,"21") -> 0 | DC16: =COUNTIFS('DETAIL SALES'!$Q$10:$Q$7501,'FILL RATE MANDATORY STOCK'!BK16,'DETAIL SALES'!$AB$10:$AB$7501,"Full",'DETAIL SALES'!$C$10:$C$7501,"22") -> 0 | DD16: =COUNTIFS('DETAIL SALES'!$Q$10:$Q$7501,'FILL RATE MANDATORY STOCK'!BK16,'DETAIL SALES'!$AB$10:$AB$7501,"No",'DETAIL SALES'!$C$10:$C$7501,"22") -> 0 | DE16: =COUNTIFS('DETAIL SALES'!$Q$10:$Q$7501,'FILL RATE MANDATORY STOCK'!BK16,'DETAIL SALES'!$AB$10:$AB$7501,"Full",'DETAIL SALES'!$C$10:$C$7501,"23") -> 0 | DF16: =COUNTIFS('DETAIL SALES'!$Q$10:$Q$7501,'FILL RATE MANDATORY STOCK'!BK16,'DETAIL SALES'!$AB$10:$AB$7501,"No",'DETAIL SALES'!$C$10:$C$7501,"23") -> 0 | DG16: =COUNTIFS('DETAIL SALES'!$Q$10:$Q$7501,'FILL RATE MANDATORY STOCK'!BK16,'DETAIL SALES'!$AB$10:$AB$7501,"Full",'DETAIL SALES'!$C$10:$C$7501,"24") -> 0 | DH16: =COUNTIFS('DETAIL SALES'!$Q$10:$Q$7501,'FILL RATE MANDATORY STOCK'!BK16,'DETAIL SALES'!$AB$10:$AB$7501,"No",'DETAIL SALES'!$C$10:$C$7501,"24") -> 0 | DI16: =COUNTIFS('DETAIL SALES'!$Q$10:$Q$7501,'FILL RATE MANDATORY STOCK'!BK16,'DETAIL SALES'!$AB$10:$AB$7501,"Full",'DETAIL SALES'!$C$10:$C$7501,"25") -> 0 | DJ16: =COUNTIFS('DETAIL SALES'!$Q$10:$Q$7501,'FILL RATE MANDATORY STOCK'!BK16,'DETAIL SALES'!$AB$10:$AB$7501,"No",'DETAIL SALES'!$C$10:$C$7501,"25") -> 0 | DK16: =COUNTIFS('DETAIL SALES'!$Q$10:$Q$7501,'FILL RATE MANDATORY STOCK'!BK16,'DETAIL SALES'!$AB$10:$AB$7501,"Full",'DETAIL SALES'!$C$10:$C$7501,"26") -> 0 | DL16: =COUNTIFS('DETAIL SALES'!$Q$10:$Q$7501,'FILL RATE MANDATORY STOCK'!BK16,'DETAIL SALES'!$AB$10:$AB$7501,"No",'DETAIL SALES'!$C$10:$C$7501,"26") -> 0 | DM16: =COUNTIFS('DETAIL SALES'!$Q$10:$Q$7501,'FILL RATE MANDATORY STOCK'!BK16,'DETAIL SALES'!$AB$10:$AB$7501,"Full",'DETAIL SALES'!$C$10:$C$7501,"27") -> 0 | DN16: =COUNTIFS('DETAIL SALES'!$Q$10:$Q$7501,'FILL RATE MANDATORY STOCK'!BK16,'DETAIL SALES'!$AB$10:$AB$7501,"No",'DETAIL SALES'!$C$10:$C$7501,"27") -> 0 | DO16: =COUNTIFS('DETAIL SALES'!$Q$10:$Q$7501,'FILL RATE MANDATORY STOCK'!BK16,'DETAIL SALES'!$AB$10:$AB$7501,"Full",'DETAIL SALES'!$C$10:$C$7501,"28") -> 0 | DP16: =COUNTIFS('DETAIL SALES'!$Q$10:$Q$7501,'FILL RATE MANDATORY STOCK'!BK16,'DETAIL SALES'!$AB$10:$AB$7501,"No",'DETAIL SALES'!$C$10:$C$7501,"28") -> 0 | DQ16: =COUNTIFS('DETAIL SALES'!$Q$10:$Q$7501,'FILL RATE MANDATORY STOCK'!BK16,'DETAIL SALES'!$AB$10:$AB$7501,"Full",'DETAIL SALES'!$C$10:$C$7501,"29") -> 0 | DR16: =COUNTIFS('DETAIL SALES'!$Q$10:$Q$7501,'FILL RATE MANDATORY STOCK'!BK16,'DETAIL SALES'!$AB$10:$AB$7501,"No",'DETAIL SALES'!$C$10:$C$7501,"29") -> 0 | DS16: =COUNTIFS('DETAIL SALES'!$Q$10:$Q$7501,'FILL RATE MANDATORY STOCK'!BK16,'DETAIL SALES'!$AB$10:$AB$7501,"Full",'DETAIL SALES'!$C$10:$C$7501,"30") -> 0 | DT16: =COUNTIFS('DETAIL SALES'!$Q$10:$Q$7501,'FILL RATE MANDATORY STOCK'!BK16,'DETAIL SALES'!$AB$10:$AB$7501,"No",'DETAIL SALES'!$C$10:$C$7501,"30") -> 0 | DU16: =COUNTIFS('DETAIL SALES'!$Q$10:$Q$7501,'FILL RATE MANDATORY STOCK'!\,'DETAIL SALES'!$AB$10:$AB$7501,"Full",'DETAIL SALES'!$C$10:$C$7501,"31") -> 0 | DV16: =COUNTIFS('DETAIL SALES'!$Q$10:$Q$7501,'FILL RATE MANDATORY STOCK'!BK16,'DETAIL SALES'!$AB$10:$AB$7501,"No",'DETAIL SALES'!$C$10:$C$7501,"31") -> 0 | DW16: =BM16+BO16+BQ16+BS16+BU16+BW16+BY16+CA16+CC16+CE16+CG16+CI16+CK16+CM16+CO16+CQ16+CS16+CU16+CW16+CY16+DA16+DC16+DE16+DG16+DI16+DK16+DM16+DO16+DQ16+DS16+DU16 -> 0 | DX16: =BN16+BP16+BR16+BT16+BV16+BX16+BZ16+CB16+CD16+CF16+CH16+CJ16+CL16+CN16+CP16+CR16+CT16+CV16+CX16+CZ16+DB16+DD16+DF16+DH16+DJ16+DL16+DN16+DP16+DR16+DT16+DV16 -> 0 | DY16: =DW16+DX16 -> 0 | DZ16: =DW16/DY16 -> #DIV/0!
A17: 8 | C17: =DAY(B17) -> 0 | D17: =MONTH(B17) -> 1 | E17: =YEAR(B17) -> 1900 | Y17: =X17*U17 -> 0 | Z17: =Y17*1.1 -> 0 | AB17: =IF(S17="","",IF(S17-U17=0,"Full","No")) | AC17: =IF(AND(S17>U17,V17=0),"Lost",IF(AND(S17>U17,V17<(S17-U17)),"Lost","")) | AD17: =IF(AND(S17>U17,V17=0),S17-U17,IF(AND(S17>U17,V17<(S17-U17)),S17-(U17+V17),"")) | AJ17: 6 | AK17: Agriculture | AL17: Pertanian, Perkebunan, Perhutanan, | AN17: PT. AUTOMOBIL BORNEO PERDANA | BE17: =MAX(BE11:BE16)+1 -> 6 | BF17: Dessicant | BG17: RANGER | BH17: 44831LBA30 | BI17: =VLOOKUP(BH17,#REF!,8,FALSE) -> #REF! | BJ17: 60000 | BK17: 1 | BL17: 0 | BM17: =COUNTIFS('DETAIL SALES'!$Q$10:$Q$7501,'FILL RATE MANDATORY STOCK'!BK17,'DETAIL SALES'!$AB$10:$AB$7501,"Full",'DETAIL SALES'!$C$10:$C$7501,"1") -> 0 | BN17: =COUNTIFS('DETAIL SALES'!$Q$10:$Q$7501,'FILL RATE MANDATORY STOCK'!BK17,'DETAIL SALES'!$AB$10:$AB$7501,"No",'DETAIL SALES'!$C$10:$C$7501,"1") -> 0 | BO17: =COUNTIFS('DETAIL SALES'!$Q$10:$Q$7501,'FILL RATE MANDATORY STOCK'!BK17,'DETAIL SALES'!$AB$10:$AB$7501,"Full",'DETAIL SALES'!$C$10:$C$7501,"2") -> 0 | BP17: =COUNTIFS('DETAIL SALES'!$Q$10:$Q$7501,'FILL RATE MANDATORY STOCK'!BK17,'DETAIL SALES'!$AB$10:$AB$7501,"No",'DETAIL SALES'!$C$10:$C$7501,"2") -> 0 | BQ17: =COUNTIFS('DETAIL SALES'!$Q$10:$Q$7501,'FILL RATE MANDATORY STOCK'!BK17,'DETAIL SALES'!$AB$10:$AB$7501,"Full",'DETAIL SALES'!$C$10:$C$7501,"3") -> 0 | BR17: =COUNTIFS('DETAIL SALES'!$Q$10:$Q$7501,'FILL RATE MANDATORY STOCK'!BK17,'DETAIL SALES'!$AB$10:$AB$7501,"No",'DETAIL SALES'!$C$10:$C$7501,"3") -> 0 | BS17: =COUNTIFS('DETAIL SALES'!$Q$10:$Q$7501,'FILL RATE MANDATORY STOCK'!BK17,'DETAIL SALES'!$AB$10:$AB$7501,"Full",'DETAIL SALES'!$C$10:$C$7501,"4") -> 0 | BT17: =COUNTIFS('DETAIL SALES'!$Q$10:$Q$7501,'FILL RATE MANDATORY STOCK'!BK17,'DETAIL SALES'!$AB$10:$AB$7501,"No",'DETAIL SALES'!$C$10:$C$7501,"4") -> 0 | BU17: =COUNTIFS('DETAIL SALES'!$Q$10:$Q$7501,'FILL RATE MANDATORY STOCK'!BK17,'DETAIL SALES'!$AB$10:$AB$7501,"Full",'DETAIL SALES'!$C$10:$C$7501,"5") -> 0 | BV17: =COUNTIFS('DETAIL SALES'!$Q$10:$Q$7501,'FILL RATE MANDATORY STOCK'!BK17,'DETAIL SALES'!$AB$10:$AB$7501,"No",'DETAIL SALES'!$C$10:$C$7501,"5") -> 0 | BW17: =COUNTIFS('DETAIL SALES'!$Q$10:$Q$7501,'FILL RATE MANDATORY STOCK'!BK17,'DETAIL SALES'!$AB$10:$AB$7501,"Full",'DETAIL SALES'!$C$10:$C$7501,"6") -> 0 | BX17: =COUNTIFS('DETAIL SALES'!$Q$10:$Q$7501,'FILL RATE MANDATORY STOCK'!BK17,'DETAIL SALES'!$AB$10:$AB$7501,"No",'DETAIL SALES'!$C$10:$C$7501,"6") -> 0 | BY17: =COUNTIFS('DETAIL SALES'!$Q$10:$Q$7501,'FILL RATE MANDATORY STOCK'!BK17,'DETAIL SALES'!$AB$10:$AB$7501,"Full",'DETAIL SALES'!$C$10:$C$7501,"7") -> 0 | BZ17: =COUNTIFS('DETAIL SALES'!$Q$10:$Q$7501,'FILL RATE MANDATORY STOCK'!BK17,'DETAIL SALES'!$AB$10:$AB$7501,"No",'DETAIL SALES'!$C$10:$C$7501,"7") -> 0 | CA17: =COUNTIFS('DETAIL SALES'!$Q$10:$Q$7501,'FILL RATE MANDATORY STOCK'!BK17,'DETAIL SALES'!$AB$10:$AB$7501,"Full",'DETAIL SALES'!$C$10:$C$7501,"8") -> 0 | CB17: =COUNTIFS('DETAIL SALES'!$Q$10:$Q$7501,'FILL RATE MANDATORY STOCK'!BK17,'DETAIL SALES'!$AB$10:$AB$7501,"No",'DETAIL SALES'!$C$10:$C$7501,"8") -> 0 | CC17: =COUNTIFS('DETAIL SALES'!$Q$10:$Q$7501,'FILL RATE MANDATORY STOCK'!BK17,'DETAIL SALES'!$AB$10:$AB$7501,"Full",'DETAIL SALES'!$C$10:$C$7501,"9") -> 0 | CD17: =COUNTIFS('DETAIL SALES'!$Q$10:$Q$7501,'FILL RATE MANDATORY STOCK'!BK17,'DETAIL SALES'!$AB$10:$AB$7501,"No",'DETAIL SALES'!$C$10:$C$7501,"9") -> 0 | CE17: =COUNTIFS('DETAIL SALES'!$Q$10:$Q$7501,'FILL RATE MANDATORY STOCK'!BK17,'DETAIL SALES'!$AB$10:$AB$7501,"Full",'DETAIL SALES'!$C$10:$C$7501,"10") -> 0 | CF17: =COUNTIFS('DETAIL SALES'!$Q$10:$Q$7501,'FILL RATE MANDATORY STOCK'!BK17,'DETAIL SALES'!$AB$10:$AB$7501,"No",'DETAIL SALES'!$C$10:$C$7501,"10") -> 0 | CG17: =COUNTIFS('DETAIL SALES'!$Q$10:$Q$7501,'FILL RATE MANDATORY STOCK'!BK17,'DETAIL SALES'!$AB$10:$AB$7501,"Full",'DETAIL SALES'!$C$10:$C$7501,"11") -> 0 | CH17: =COUNTIFS('DETAIL SALES'!$Q$10:$Q$7501,'FILL RATE MANDATORY STOCK'!BK17,'DETAIL SALES'!$AB$10:$AB$7501,"No",'DETAIL SALES'!$C$10:$C$7501,"11") -> 0 | CI17: =COUNTIFS('DETAIL SALES'!$Q$10:$Q$7501,'FILL RATE MANDATORY STOCK'!BK17,'DETAIL SALES'!$AB$10:$AB$7501,"Full",'DETAIL SALES'!$C$10:$C$7501,"12") -> 0 | CJ17: =COUNTIFS('DETAIL SALES'!$Q$10:$Q$7501,'FILL RATE MANDATORY STOCK'!BK17,'DETAIL SALES'!$AB$10:$AB$7501,"No",'DETAIL SALES'!$C$10:$C$7501,"12") -> 0 | CK17: =COUNTIFS('DETAIL SALES'!$Q$10:$Q$7501,'FILL RATE MANDATORY STOCK'!BK17,'DETAIL SALES'!$AB$10:$AB$7501,"Full",'DETAIL SALES'!$C$10:$C$7501,"13") -> 0 | CL17: =COUNTIFS('DETAIL SALES'!$Q$10:$Q$7501,'FILL RATE MANDATORY STOCK'!BK17,'DETAIL SALES'!$AB$10:$AB$7501,"No",'DETAIL SALES'!$C$10:$C$7501,"13") -> 0 | CM17: =COUNTIFS('DETAIL SALES'!$Q$10:$Q$7501,'FILL RATE MANDATORY STOCK'!BK17,'DETAIL SALES'!$AB$10:$AB$7501,"Full",'DETAIL SALES'!$C$10:$C$7501,"14") -> 0 | CN17: =COUNTIFS('DETAIL SALES'!$Q$10:$Q$7501,'FILL RATE MANDATORY STOCK'!BK17,'DETAIL SALES'!$AB$10:$AB$7501,"No",'DETAIL SALES'!$C$10:$C$7501,"14") -> 0 | CO17: =COUNTIFS('DETAIL SALES'!$Q$10:$Q$7501,'FILL RATE MANDATORY STOCK'!BK17,'DETAIL SALES'!$AB$10:$AB$7501,"Full",'DETAIL SALES'!$C$10:$C$7501,"15") -> 0 | CP17: =COUNTIFS('DETAIL SALES'!$Q$10:$Q$7501,'FILL RATE MANDATORY STOCK'!BK17,'DETAIL SALES'!$AB$10:$AB$7501,"No",'DETAIL SALES'!$C$10:$C$7501,"15") -> 0 | CQ17: =COUNTIFS('DETAIL SALES'!$Q$10:$Q$7501,'FILL RATE MANDATORY STOCK'!BK17,'DETAIL SALES'!$AB$10:$AB$7501,"Full",'DETAIL SALES'!$C$10:$C$7501,"16") -> 0 | CR17: =COUNTIFS('DETAIL SALES'!$Q$10:$Q$7501,'FILL RATE MANDATORY STOCK'!BK17,'DETAIL SALES'!$AB$10:$AB$7501,"No",'DETAIL SALES'!$C$10:$C$7501,"16") -> 0 | CS17: =COUNTIFS('DETAIL SALES'!$Q$10:$Q$7501,'FILL RATE MANDATORY STOCK'!BK17,'DETAIL SALES'!$AB$10:$AB$7501,"Full",'DETAIL SALES'!$C$10:$C$7501,"17") -> 0 | CT17: =COUNTIFS('DETAIL SALES'!$Q$10:$Q$7501,'FILL RATE MANDATORY STOCK'!BK17,'DETAIL SALES'!$AB$10:$AB$7501,"No",'DETAIL SALES'!$C$10:$C$7501,"17") -> 0 | CU17: =COUNTIFS('DETAIL SALES'!$Q$10:$Q$7501,'FILL RATE MANDATORY STOCK'!BK17,'DETAIL SALES'!$AB$10:$AB$7501,"Full",'DETAIL SALES'!$C$10:$C$7501,"18") -> 0 | CV17: =COUNTIFS('DETAIL SALES'!$Q$10:$Q$7501,'FILL RATE MANDATORY STOCK'!BK17,'DETAIL SALES'!$AB$10:$AB$7501,"No",'DETAIL SALES'!$C$10:$C$7501,"18") -> 0 | CW17: =COUNTIFS('DETAIL SALES'!$Q$10:$Q$7501,'FILL RATE MANDATORY STOCK'!BK17,'DETAIL SALES'!$AB$10:$AB$7501,"Full",'DETAIL SALES'!$C$10:$C$7501,"19") -> 0 | CX17: =COUNTIFS('DETAIL SALES'!$Q$10:$Q$7501,'FILL RATE MANDATORY STOCK'!BK17,'DETAIL SALES'!$AB$10:$AB$7501,"No",'DETAIL SALES'!$C$10:$C$7501,"19") -> 0 | CY17: =COUNTIFS('DETAIL SALES'!$Q$10:$Q$7501,'FILL RATE MANDATORY STOCK'!BK17,'DETAIL SALES'!$AB$10:$AB$7501,"Full",'DETAIL SALES'!$C$10:$C$7501,"20") -> 0 | CZ17: =COUNTIFS('DETAIL SALES'!$Q$10:$Q$7501,'FILL RATE MANDATORY STOCK'!BK17,'DETAIL SALES'!$AB$10:$AB$7501,"No",'DETAIL SALES'!$C$10:$C$7501,"20") -> 0 | DA17: =COUNTIFS('DETAIL SALES'!$Q$10:$Q$7501,'FILL RATE MANDATORY STOCK'!BK17,'DETAIL SALES'!$AB$10:$AB$7501,"Full",'DETAIL SALES'!$C$10:$C$7501,"21") -> 0 | DB17: =COUNTIFS('DETAIL SALES'!$Q$10:$Q$7501,'FILL RATE MANDATORY STOCK'!BK17,'DETAIL SALES'!$AB$10:$AB$7501,"No",'DETAIL SALES'!$C$10:$C$7501,"21") -> 0 | DC17: =COUNTIFS('DETAIL SALES'!$Q$10:$Q$7501,'FILL RATE MANDATORY STOCK'!BK17,'DETAIL SALES'!$AB$10:$AB$7501,"Full",'DETAIL SALES'!$C$10:$C$7501,"22") -> 0 | DD17: =COUNTIFS('DETAIL SALES'!$Q$10:$Q$7501,'FILL RATE MANDATORY STOCK'!BK17,'DETAIL SALES'!$AB$10:$AB$7501,"No",'DETAIL SALES'!$C$10:$C$7501,"22") -> 0 | DE17: =COUNTIFS('DETAIL SALES'!$Q$10:$Q$7501,'FILL RATE MANDATORY STOCK'!BK17,'DETAIL SALES'!$AB$10:$AB$7501,"Full",'DETAIL SALES'!$C$10:$C$7501,"23") -> 0 | DF17: =COUNTIFS('DETAIL SALES'!$Q$10:$Q$7501,'FILL RATE MANDATORY STOCK'!BK17,'DETAIL SALES'!$AB$10:$AB$7501,"No",'DETAIL SALES'!$C$10:$C$7501,"23") -> 0 | DG17: =COUNTIFS('DETAIL SALES'!$Q$10:$Q$7501,'FILL RATE MANDATORY STOCK'!BK17,'DETAIL SALES'!$AB$10:$AB$7501,"Full",'DETAIL SALES'!$C$10:$C$7501,"24") -> 0 | DH17: =COUNTIFS('DETAIL SALES'!$Q$10:$Q$7501,'FILL RATE MANDATORY STOCK'!BK17,'DETAIL SALES'!$AB$10:$AB$7501,"No",'DETAIL SALES'!$C$10:$C$7501,"24") -> 0 | DI17: =COUNTIFS('DETAIL SALES'!$Q$10:$Q$7501,'FILL RATE MANDATORY STOCK'!BK17,'DETAIL SALES'!$AB$10:$AB$7501,"Full",'DETAIL SALES'!$C$10:$C$7501,"25") -> 0 | DJ17: =COUNTIFS('DETAIL SALES'!$Q$10:$Q$7501,'FILL RATE MANDATORY STOCK'!BK17,'DETAIL SALES'!$AB$10:$AB$7501,"No",'DETAIL SALES'!$C$10:$C$7501,"25") -> 0 | DK17: =COUNTIFS('DETAIL SALES'!$Q$10:$Q$7501,'FILL RATE MANDATORY STOCK'!BK17,'DETAIL SALES'!$AB$10:$AB$7501,"Full",'DETAIL SALES'!$C$10:$C$7501,"26") -> 0 | DL17: =COUNTIFS('DETAIL SALES'!$Q$10:$Q$7501,'FILL RATE MANDATORY STOCK'!BK17,'DETAIL SALES'!$AB$10:$AB$7501,"No",'DETAIL SALES'!$C$10:$C$7501,"26") -> 0 | DM17: =COUNTIFS('DETAIL SALES'!$Q$10:$Q$7501,'FILL RATE MANDATORY STOCK'!BK17,'DETAIL SALES'!$AB$10:$AB$7501,"Full",'DETAIL SALES'!$C$10:$C$7501,"27") -> 0 | DN17: =COUNTIFS('DETAIL SALES'!$Q$10:$Q$7501,'FILL RATE MANDATORY STOCK'!BK17,'DETAIL SALES'!$AB$10:$AB$7501,"No",'DETAIL SALES'!$C$10:$C$7501,"27") -> 0 | DO17: =COUNTIFS('DETAIL SALES'!$Q$10:$Q$7501,'FILL RATE MANDATORY STOCK'!BK17,'DETAIL SALES'!$AB$10:$AB$7501,"Full",'DETAIL SALES'!$C$10:$C$7501,"28") -> 0 | DP17: =COUNTIFS('DETAIL SALES'!$Q$10:$Q$7501,'FILL RATE MANDATORY STOCK'!BK17,'DETAIL SALES'!$AB$10:$AB$7501,"No",'DETAIL SALES'!$C$10:$C$7501,"28") -> 0 | DQ17: =COUNTIFS('DETAIL SALES'!$Q$10:$Q$7501,'FILL RATE MANDATORY STOCK'!BK17,'DETAIL SALES'!$AB$10:$AB$7501,"Full",'DETAIL SALES'!$C$10:$C$7501,"29") -> 0 | DR17: =COUNTIFS('DETAIL SALES'!$Q$10:$Q$7501,'FILL RATE MANDATORY STOCK'!BK17,'DETAIL SALES'!$AB$10:$AB$7501,"No",'DETAIL SALES'!$C$10:$C$7501,"29") -> 0 | DS17: =COUNTIFS('DETAIL SALES'!$Q$10:$Q$7501,'FILL RATE MANDATORY STOCK'!BK17,'DETAIL SALES'!$AB$10:$AB$7501,"Full",'DETAIL SALES'!$C$10:$C$7501,"30") -> 0 | DT17: =COUNTIFS('DETAIL SALES'!$Q$10:$Q$7501,'FILL RATE MANDATORY STOCK'!BK17,'DETAIL SALES'!$AB$10:$AB$7501,"No",'DETAIL SALES'!$C$10:$C$7501,"30") -> 0 | DU17: =COUNTIFS('DETAIL SALES'!$Q$10:$Q$7501,'FILL RATE MANDATORY STOCK'!\,'DETAIL SALES'!$AB$10:$AB$7501,"Full",'DETAIL SALES'!$C$10:$C$7501,"31") -> 0 | DV17: =COUNTIFS('DETAIL SALES'!$Q$10:$Q$7501,'FILL RATE MANDATORY STOCK'!BK17,'DETAIL SALES'!$AB$10:$AB$7501,"No",'DETAIL SALES'!$C$10:$C$7501,"31") -> 0 | DW17: =BM17+BO17+BQ17+BS17+BU17+BW17+BY17+CA17+CC17+CE17+CG17+CI17+CK17+CM17+CO17+CQ17+CS17+CU17+CW17+CY17+DA17+DC17+DE17+DG17+DI17+DK17+DM17+DO17+DQ17+DS17+DU17 -> 0 | DX17: =BN17+BP17+BR17+BT17+BV17+BX17+BZ17+CB17+CD17+CF17+CH17+CJ17+CL17+CN17+CP17+CR17+CT17+CV17+CX17+CZ17+DB17+DD17+DF17+DH17+DJ17+DL17+DN17+DP17+DR17+DT17+DV17 -> 0 | DY17: =DW17+DX17 -> 0 | DZ17: =DW17/DY17 -> #DIV/0!
A18: 9 | C18: =DAY(B18) -> 0 | D18: =MONTH(B18) -> 1 | E18: =YEAR(B18) -> 1900 | Y18: =X18*U18 -> 0 | Z18: =Y18*1.1 -> 0 | AB18: =IF(S18="","",IF(S18-U18=0,"Full","No")) | AC18: =IF(AND(S18>U18,V18=0),"Lost",IF(AND(S18>U18,V18<(S18-U18)),"Lost","")) | AD18: =IF(AND(S18>U18,V18=0),S18-U18,IF(AND(S18>U18,V18<(S18-U18)),S18-(U18+V18),"")) | AJ18: 7 | AK18: Mining | AL18: Batubara, nikel | AN18: PT. BYPASSINDO JAYA INDAH | AQ18: END USER - BISNIS CUSTOMER | BE18: =MAX(BE12:BE17)+1 -> 7 | BF18: Transmission Oil GL-5 80W90 | BG18: ALL MODEL | BH18: S041024414 | BI18: =VLOOKUP(BH18,#REF!,8,FALSE) -> #REF! | BJ18: 1.000 & 60.000 | BK18: 13 | BL18: 0 | BM18: =COUNTIFS('DETAIL SALES'!$Q$10:$Q$7501,'FILL RATE MANDATORY STOCK'!BK18,'DETAIL SALES'!$AB$10:$AB$7501,"Full",'DETAIL SALES'!$C$10:$C$7501,"1") -> 0 | BN18: =COUNTIFS('DETAIL SALES'!$Q$10:$Q$7501,'FILL RATE MANDATORY STOCK'!BK18,'DETAIL SALES'!$AB$10:$AB$7501,"No",'DETAIL SALES'!$C$10:$C$7501,"1") -> 0 | BO18: =COUNTIFS('DETAIL SALES'!$Q$10:$Q$7501,'FILL RATE MANDATORY STOCK'!BK18,'DETAIL SALES'!$AB$10:$AB$7501,"Full",'DETAIL SALES'!$C$10:$C$7501,"2") -> 0 | BP18: =COUNTIFS('DETAIL SALES'!$Q$10:$Q$7501,'FILL RATE MANDATORY STOCK'!BK18,'DETAIL SALES'!$AB$10:$AB$7501,"No",'DETAIL SALES'!$C$10:$C$7501,"2") -> 0 | BQ18: =COUNTIFS('DETAIL SALES'!$Q$10:$Q$7501,'FILL RATE MANDATORY STOCK'!BK18,'DETAIL SALES'!$AB$10:$AB$7501,"Full",'DETAIL SALES'!$C$10:$C$7501,"3") -> 0 | BR18: =COUNTIFS('DETAIL SALES'!$Q$10:$Q$7501,'FILL RATE MANDATORY STOCK'!BK18,'DETAIL SALES'!$AB$10:$AB$7501,"No",'DETAIL SALES'!$C$10:$C$7501,"3") -> 0 | BS18: =COUNTIFS('DETAIL SALES'!$Q$10:$Q$7501,'FILL RATE MANDATORY STOCK'!BK18,'DETAIL SALES'!$AB$10:$AB$7501,"Full",'DETAIL SALES'!$C$10:$C$7501,"4") -> 0 | BT18: =COUNTIFS('DETAIL SALES'!$Q$10:$Q$7501,'FILL RATE MANDATORY STOCK'!BK18,'DETAIL SALES'!$AB$10:$AB$7501,"No",'DETAIL SALES'!$C$10:$C$7501,"4") -> 0 | BU18: =COUNTIFS('DETAIL SALES'!$Q$10:$Q$7501,'FILL RATE MANDATORY STOCK'!BK18,'DETAIL SALES'!$AB$10:$AB$7501,"Full",'DETAIL SALES'!$C$10:$C$7501,"5") -> 0 | BV18: =COUNTIFS('DETAIL SALES'!$Q$10:$Q$7501,'FILL RATE MANDATORY STOCK'!BK18,'DETAIL SALES'!$AB$10:$AB$7501,"No",'DETAIL SALES'!$C$10:$C$7501,"5") -> 0 | BW18: =COUNTIFS('DETAIL SALES'!$Q$10:$Q$7501,'FILL RATE MANDATORY STOCK'!BK18,'DETAIL SALES'!$AB$10:$AB$7501,"Full",'DETAIL SALES'!$C$10:$C$7501,"6") -> 0 | BX18: =COUNTIFS('DETAIL SALES'!$Q$10:$Q$7501,'FILL RATE MANDATORY STOCK'!BK18,'DETAIL SALES'!$AB$10:$AB$7501,"No",'DETAIL SALES'!$C$10:$C$7501,"6") -> 0 | BY18: =COUNTIFS('DETAIL SALES'!$Q$10:$Q$7501,'FILL RATE MANDATORY STOCK'!BK18,'DETAIL SALES'!$AB$10:$AB$7501,"Full",'DETAIL SALES'!$C$10:$C$7501,"7") -> 0 | BZ18: =COUNTIFS('DETAIL SALES'!$Q$10:$Q$7501,'FILL RATE MANDATORY STOCK'!BK18,'DETAIL SALES'!$AB$10:$AB$7501,"No",'DETAIL SALES'!$C$10:$C$7501,"7") -> 0 | CA18: =COUNTIFS('DETAIL SALES'!$Q$10:$Q$7501,'FILL RATE MANDATORY STOCK'!BK18,'DETAIL SALES'!$AB$10:$AB$7501,"Full",'DETAIL SALES'!$C$10:$C$7501,"8") -> 0 | CB18: =COUNTIFS('DETAIL SALES'!$Q$10:$Q$7501,'FILL RATE MANDATORY STOCK'!BK18,'DETAIL SALES'!$AB$10:$AB$7501,"No",'DETAIL SALES'!$C$10:$C$7501,"8") -> 0 | CC18: =COUNTIFS('DETAIL SALES'!$Q$10:$Q$7501,'FILL RATE MANDATORY STOCK'!BK18,'DETAIL SALES'!$AB$10:$AB$7501,"Full",'DETAIL SALES'!$C$10:$C$7501,"9") -> 0 | CD18: =COUNTIFS('DETAIL SALES'!$Q$10:$Q$7501,'FILL RATE MANDATORY STOCK'!BK18,'DETAIL SALES'!$AB$10:$AB$7501,"No",'DETAIL SALES'!$C$10:$C$7501,"9") -> 0 | CE18: =COUNTIFS('DETAIL SALES'!$Q$10:$Q$7501,'FILL RATE MANDATORY STOCK'!BK18,'DETAIL SALES'!$AB$10:$AB$7501,"Full",'DETAIL SALES'!$C$10:$C$7501,"10") -> 0 | CF18: =COUNTIFS('DETAIL SALES'!$Q$10:$Q$7501,'FILL RATE MANDATORY STOCK'!BK18,'DETAIL SALES'!$AB$10:$AB$7501,"No",'DETAIL SALES'!$C$10:$C$7501,"10") -> 0 | CG18: =COUNTIFS('DETAIL SALES'!$Q$10:$Q$7501,'FILL RATE MANDATORY STOCK'!BK18,'DETAIL SALES'!$AB$10:$AB$7501,"Full",'DETAIL SALES'!$C$10:$C$7501,"11") -> 0 | CH18: =COUNTIFS('DETAIL SALES'!$Q$10:$Q$7501,'FILL RATE MANDATORY STOCK'!BK18,'DETAIL SALES'!$AB$10:$AB$7501,"No",'DETAIL SALES'!$C$10:$C$7501,"11") -> 0 | CI18: =COUNTIFS('DETAIL SALES'!$Q$10:$Q$7501,'FILL RATE MANDATORY STOCK'!BK18,'DETAIL SALES'!$AB$10:$AB$7501,"Full",'DETAIL SALES'!$C$10:$C$7501,"12") -> 0 | CJ18: =COUNTIFS('DETAIL SALES'!$Q$10:$Q$7501,'FILL RATE MANDATORY STOCK'!BK18,'DETAIL SALES'!$AB$10:$AB$7501,"No",'DETAIL SALES'!$C$10:$C$7501,"12") -> 0 | CK18: =COUNTIFS('DETAIL SALES'!$Q$10:$Q$7501,'FILL RATE MANDATORY STOCK'!BK18,'DETAIL SALES'!$AB$10:$AB$7501,"Full",'DETAIL SALES'!$C$10:$C$7501,"13") -> 0 | CL18: =COUNTIFS('DETAIL SALES'!$Q$10:$Q$7501,'FILL RATE MANDATORY STOCK'!BK18,'DETAIL SALES'!$AB$10:$AB$7501,"No",'DETAIL SALES'!$C$10:$C$7501,"13") -> 0 | CM18: =COUNTIFS('DETAIL SALES'!$Q$10:$Q$7501,'FILL RATE MANDATORY STOCK'!BK18,'DETAIL SALES'!$AB$10:$AB$7501,"Full",'DETAIL SALES'!$C$10:$C$7501,"14") -> 0 | CN18: =COUNTIFS('DETAIL SALES'!$Q$10:$Q$7501,'FILL RATE MANDATORY STOCK'!BK18,'DETAIL SALES'!$AB$10:$AB$7501,"No",'DETAIL SALES'!$C$10:$C$7501,"14") -> 0 | CO18: =COUNTIFS('DETAIL SALES'!$Q$10:$Q$7501,'FILL RATE MANDATORY STOCK'!BK18,'DETAIL SALES'!$AB$10:$AB$7501,"Full",'DETAIL SALES'!$C$10:$C$7501,"15") -> 0 | CP18: =COUNTIFS('DETAIL SALES'!$Q$10:$Q$7501,'FILL RATE MANDATORY STOCK'!BK18,'DETAIL SALES'!$AB$10:$AB$7501,"No",'DETAIL SALES'!$C$10:$C$7501,"15") -> 0 | CQ18: =COUNTIFS('DETAIL SALES'!$Q$10:$Q$7501,'FILL RATE MANDATORY STOCK'!BK18,'DETAIL SALES'!$AB$10:$AB$7501,"Full",'DETAIL SALES'!$C$10:$C$7501,"16") -> 0 | CR18: =COUNTIFS('DETAIL SALES'!$Q$10:$Q$7501,'FILL RATE MANDATORY STOCK'!BK18,'DETAIL SALES'!$AB$10:$AB$7501,"No",'DETAIL SALES'!$C$10:$C$7501,"16") -> 0 | CS18: =COUNTIFS('DETAIL SALES'!$Q$10:$Q$7501,'FILL RATE MANDATORY STOCK'!BK18,'DETAIL SALES'!$AB$10:$AB$7501,"Full",'DETAIL SALES'!$C$10:$C$7501,"17") -> 0 | CT18: =COUNTIFS('DETAIL SALES'!$Q$10:$Q$7501,'FILL RATE MANDATORY STOCK'!BK18,'DETAIL SALES'!$AB$10:$AB$7501,"No",'DETAIL SALES'!$C$10:$C$7501,"17") -> 0 | CU18: =COUNTIFS('DETAIL SALES'!$Q$10:$Q$7501,'FILL RATE MANDATORY STOCK'!BK18,'DETAIL SALES'!$AB$10:$AB$7501,"Full",'DETAIL SALES'!$C$10:$C$7501,"18") -> 0 | CV18: =COUNTIFS('DETAIL SALES'!$Q$10:$Q$7501,'FILL RATE MANDATORY STOCK'!BK18,'DETAIL SALES'!$AB$10:$AB$7501,"No",'DETAIL SALES'!$C$10:$C$7501,"18") -> 0 | CW18: =COUNTIFS('DETAIL SALES'!$Q$10:$Q$7501,'FILL RATE MANDATORY STOCK'!BK18,'DETAIL SALES'!$AB$10:$AB$7501,"Full",'DETAIL SALES'!$C$10:$C$7501,"19") -> 0 | CX18: =COUNTIFS('DETAIL SALES'!$Q$10:$Q$7501,'FILL RATE MANDATORY STOCK'!BK18,'DETAIL SALES'!$AB$10:$AB$7501,"No",'DETAIL SALES'!$C$10:$C$7501,"19") -> 0 | CY18: =COUNTIFS('DETAIL SALES'!$Q$10:$Q$7501,'FILL RATE MANDATORY STOCK'!BK18,'DETAIL SALES'!$AB$10:$AB$7501,"Full",'DETAIL SALES'!$C$10:$C$7501,"20") -> 0 | CZ18: =COUNTIFS('DETAIL SALES'!$Q$10:$Q$7501,'FILL RATE MANDATORY STOCK'!BK18,'DETAIL SALES'!$AB$10:$AB$7501,"No",'DETAIL SALES'!$C$10:$C$7501,"20") -> 0 | DA18: =COUNTIFS('DETAIL SALES'!$Q$10:$Q$7501,'FILL RATE MANDATORY STOCK'!BK18,'DETAIL SALES'!$AB$10:$AB$7501,"Full",'DETAIL SALES'!$C$10:$C$7501,"21") -> 0 | DB18: =COUNTIFS('DETAIL SALES'!$Q$10:$Q$7501,'FILL RATE MANDATORY STOCK'!BK18,'DETAIL SALES'!$AB$10:$AB$7501,"No",'DETAIL SALES'!$C$10:$C$7501,"21") -> 0 | DC18: =COUNTIFS('DETAIL SALES'!$Q$10:$Q$7501,'FILL RATE MANDATORY STOCK'!BK18,'DETAIL SALES'!$AB$10:$AB$7501,"Full",'DETAIL SALES'!$C$10:$C$7501,"22") -> 0 | DD18: =COUNTIFS('DETAIL SALES'!$Q$10:$Q$7501,'FILL RATE MANDATORY STOCK'!BK18,'DETAIL SALES'!$AB$10:$AB$7501,"No",'DETAIL SALES'!$C$10:$C$7501,"22") -> 0 | DE18: =COUNTIFS('DETAIL SALES'!$Q$10:$Q$7501,'FILL RATE MANDATORY STOCK'!BK18,'DETAIL SALES'!$AB$10:$AB$7501,"Full",'DETAIL SALES'!$C$10:$C$7501,"23") -> 0 | DF18: =COUNTIFS('DETAIL SALES'!$Q$10:$Q$7501,'FILL RATE MANDATORY STOCK'!BK18,'DETAIL SALES'!$AB$10:$AB$7501,"No",'DETAIL SALES'!$C$10:$C$7501,"23") -> 0 | DG18: =COUNTIFS('DETAIL SALES'!$Q$10:$Q$7501,'FILL RATE MANDATORY STOCK'!BK18,'DETAIL SALES'!$AB$10:$AB$7501,"Full",'DETAIL SALES'!$C$10:$C$7501,"24") -> 0 | DH18: =COUNTIFS('DETAIL SALES'!$Q$10:$Q$7501,'FILL RATE MANDATORY STOCK'!BK18,'DETAIL SALES'!$AB$10:$AB$7501,"No",'DETAIL SALES'!$C$10:$C$7501,"24") -> 0 | DI18: =COUNTIFS('DETAIL SALES'!$Q$10:$Q$7501,'FILL RATE MANDATORY STOCK'!BK18,'DETAIL SALES'!$AB$10:$AB$7501,"Full",'DETAIL SALES'!$C$10:$C$7501,"25") -> 0 | DJ18: =COUNTIFS('DETAIL SALES'!$Q$10:$Q$7501,'FILL RATE MANDATORY STOCK'!BK18,'DETAIL SALES'!$AB$10:$AB$7501,"No",'DETAIL SALES'!$C$10:$C$7501,"25") -> 0 | DK18: =COUNTIFS('DETAIL SALES'!$Q$10:$Q$7501,'FILL RATE MANDATORY STOCK'!BK18,'DETAIL SALES'!$AB$10:$AB$7501,"Full",'DETAIL SALES'!$C$10:$C$7501,"26") -> 0 | DL18: =COUNTIFS('DETAIL SALES'!$Q$10:$Q$7501,'FILL RATE MANDATORY STOCK'!BK18,'DETAIL SALES'!$AB$10:$AB$7501,"No",'DETAIL SALES'!$C$10:$C$7501,"26") -> 0 | DM18: =COUNTIFS('DETAIL SALES'!$Q$10:$Q$7501,'FILL RATE MANDATORY STOCK'!BK18,'DETAIL SALES'!$AB$10:$AB$7501,"Full",'DETAIL SALES'!$C$10:$C$7501,"27") -> 0 | DN18: =COUNTIFS('DETAIL SALES'!$Q$10:$Q$7501,'FILL RATE MANDATORY STOCK'!BK18,'DETAIL SALES'!$AB$10:$AB$7501,"No",'DETAIL SALES'!$C$10:$C$7501,"27") -> 0 | DO18: =COUNTIFS('DETAIL SALES'!$Q$10:$Q$7501,'FILL RATE MANDATORY STOCK'!BK18,'DETAIL SALES'!$AB$10:$AB$7501,"Full",'DETAIL SALES'!$C$10:$C$7501,"28") -> 0 | DP18: =COUNTIFS('DETAIL SALES'!$Q$10:$Q$7501,'FILL RATE MANDATORY STOCK'!BK18,'DETAIL SALES'!$AB$10:$AB$7501,"No",'DETAIL SALES'!$C$10:$C$7501,"28") -> 0 | DQ18: =COUNTIFS('DETAIL SALES'!$Q$10:$Q$7501,'FILL RATE MANDATORY STOCK'!BK18,'DETAIL SALES'!$AB$10:$AB$7501,"Full",'DETAIL SALES'!$C$10:$C$7501,"29") -> 0 | DR18: =COUNTIFS('DETAIL SALES'!$Q$10:$Q$7501,'FILL RATE MANDATORY STOCK'!BK18,'DETAIL SALES'!$AB$10:$AB$7501,"No",'DETAIL SALES'!$C$10:$C$7501,"29") -> 0 | DS18: =COUNTIFS('DETAIL SALES'!$Q$10:$Q$7501,'FILL RATE MANDATORY STOCK'!BK18,'DETAIL SALES'!$AB$10:$AB$7501,"Full",'DETAIL SALES'!$C$10:$C$7501,"30") -> 0 | DT18: =COUNTIFS('DETAIL SALES'!$Q$10:$Q$7501,'FILL RATE MANDATORY STOCK'!BK18,'DETAIL SALES'!$AB$10:$AB$7501,"No",'DETAIL SALES'!$C$10:$C$7501,"30") -> 0 | DU18: =COUNTIFS('DETAIL SALES'!$Q$10:$Q$7501,'FILL RATE MANDATORY STOCK'!\,'DETAIL SALES'!$AB$10:$AB$7501,"Full",'DETAIL SALES'!$C$10:$C$7501,"31") -> 0 | DV18: =COUNTIFS('DETAIL SALES'!$Q$10:$Q$7501,'FILL RATE MANDATORY STOCK'!BK18,'DETAIL SALES'!$AB$10:$AB$7501,"No",'DETAIL SALES'!$C$10:$C$7501,"31") -> 0 | DW18: =BM18+BO18+BQ18+BS18+BU18+BW18+BY18+CA18+CC18+CE18+CG18+CI18+CK18+CM18+CO18+CQ18+CS18+CU18+CW18+CY18+DA18+DC18+DE18+DG18+DI18+DK18+DM18+DO18+DQ18+DS18+DU18 -> 0 | DX18: =BN18+BP18+BR18+BT18+BV18+BX18+BZ18+CB18+CD18+CF18+CH18+CJ18+CL18+CN18+CP18+CR18+CT18+CV18+CX18+CZ18+DB18+DD18+DF18+DH18+DJ18+DL18+DN18+DP18+DR18+DT18+DV18 -> 0 | DY18: =DW18+DX18 -> 0 | DZ18: =DW18/DY18 -> #DIV/0!
A19: 10 | C19: =DAY(B19) -> 0 | D19: =MONTH(B19) -> 1 | E19: =YEAR(B19) -> 1900 | Y19: =X19*U19 -> 0 | Z19: =Y19*1.1 -> 0 | AB19: =IF(S19="","",IF(S19-U19=0,"Full","No")) | AC19: =IF(AND(S19>U19,V19=0),"Lost",IF(AND(S19>U19,V19<(S19-U19)),"Lost","")) | AD19: =IF(AND(S19>U19,V19=0),S19-U19,IF(AND(S19>U19,V19<(S19-U19)),S19-(U19+V19),"")) | AJ19: 8 | AK19: Material Construction | AL19: Pasir, bata | AN19: PT. CAHAYA SURYA BALI INDAH | AQ19: BISNIS CUSTOMER | AR19: CAT.2 | AS19: CAT.3 | AT19: CAT.5 | AU19: OIL & ACC | AV19: TOTAL | AW19: % | AX19: CONTRACT | AY19: NON CONTRACT | AZ19: % CONTRACT | BE19: =MAX(BE16:BE18)+1 -> 8 | BF19: Oil Filter | BG19: FG/FL/FM/SG (J08E-363 MODEL) | BH19: 156072190L | BI19: =VLOOKUP(BH19,#REF!,8,FALSE) -> #REF! | BJ19: 20000 | BK19: 1 | BL19: 133.83333 | BM19: =COUNTIFS('DETAIL SALES'!$Q$10:$Q$7501,'FILL RATE MANDATORY STOCK'!BK19,'DETAIL SALES'!$AB$10:$AB$7501,"Full",'DETAIL SALES'!$C$10:$C$7501,"1") -> 0 | BN19: =COUNTIFS('DETAIL SALES'!$Q$10:$Q$7501,'FILL RATE MANDATORY STOCK'!BK19,'DETAIL SALES'!$AB$10:$AB$7501,"No",'DETAIL SALES'!$C$10:$C$7501,"1") -> 0 | BO19: =COUNTIFS('DETAIL SALES'!$Q$10:$Q$7501,'FILL RATE MANDATORY STOCK'!BK19,'DETAIL SALES'!$AB$10:$AB$7501,"Full",'DETAIL SALES'!$C$10:$C$7501,"2") -> 0 | BP19: =COUNTIFS('DETAIL SALES'!$Q$10:$Q$7501,'FILL RATE MANDATORY STOCK'!BK19,'DETAIL SALES'!$AB$10:$AB$7501,"No",'DETAIL SALES'!$C$10:$C$7501,"2") -> 0 | BQ19: =COUNTIFS('DETAIL SALES'!$Q$10:$Q$7501,'FILL RATE MANDATORY STOCK'!BK19,'DETAIL SALES'!$AB$10:$AB$7501,"Full",'DETAIL SALES'!$C$10:$C$7501,"3") -> 0 | BR19: =COUNTIFS('DETAIL SALES'!$Q$10:$Q$7501,'FILL RATE MANDATORY STOCK'!BK19,'DETAIL SALES'!$AB$10:$AB$7501,"No",'DETAIL SALES'!$C$10:$C$7501,"3") -> 0 | BS19: =COUNTIFS('DETAIL SALES'!$Q$10:$Q$7501,'FILL RATE MANDATORY STOCK'!BK19,'DETAIL SALES'!$AB$10:$AB$7501,"Full",'DETAIL SALES'!$C$10:$C$7501,"4") -> 0 | BT19: =COUNTIFS('DETAIL SALES'!$Q$10:$Q$7501,'FILL RATE MANDATORY STOCK'!BK19,'DETAIL SALES'!$AB$10:$AB$7501,"No",'DETAIL SALES'!$C$10:$C$7501,"4") -> 0 | BU19: =COUNTIFS('DETAIL SALES'!$Q$10:$Q$7501,'FILL RATE MANDATORY STOCK'!BK19,'DETAIL SALES'!$AB$10:$AB$7501,"Full",'DETAIL SALES'!$C$10:$C$7501,"5") -> 0 | BV19: =COUNTIFS('DETAIL SALES'!$Q$10:$Q$7501,'FILL RATE MANDATORY STOCK'!BK19,'DETAIL SALES'!$AB$10:$AB$7501,"No",'DETAIL SALES'!$C$10:$C$7501,"5") -> 0 | BW19: =COUNTIFS('DETAIL SALES'!$Q$10:$Q$7501,'FILL RATE MANDATORY STOCK'!BK19,'DETAIL SALES'!$AB$10:$AB$7501,"Full",'DETAIL SALES'!$C$10:$C$7501,"6") -> 0 | BX19: =COUNTIFS('DETAIL SALES'!$Q$10:$Q$7501,'FILL RATE MANDATORY STOCK'!BK19,'DETAIL SALES'!$AB$10:$AB$7501,"No",'DETAIL SALES'!$C$10:$C$7501,"6") -> 0 | BY19: =COUNTIFS('DETAIL SALES'!$Q$10:$Q$7501,'FILL RATE MANDATORY STOCK'!BK19,'DETAIL SALES'!$AB$10:$AB$7501,"Full",'DETAIL SALES'!$C$10:$C$7501,"7") -> 0 | BZ19: =COUNTIFS('DETAIL SALES'!$Q$10:$Q$7501,'FILL RATE MANDATORY STOCK'!BK19,'DETAIL SALES'!$AB$10:$AB$7501,"No",'DETAIL SALES'!$C$10:$C$7501,"7") -> 0 | CA19: =COUNTIFS('DETAIL SALES'!$Q$10:$Q$7501,'FILL RATE MANDATORY STOCK'!BK19,'DETAIL SALES'!$AB$10:$AB$7501,"Full",'DETAIL SALES'!$C$10:$C$7501,"8") -> 0 | CB19: =COUNTIFS('DETAIL SALES'!$Q$10:$Q$7501,'FILL RATE MANDATORY STOCK'!BK19,'DETAIL SALES'!$AB$10:$AB$7501,"No",'DETAIL SALES'!$C$10:$C$7501,"8") -> 0 | CC19: =COUNTIFS('DETAIL SALES'!$Q$10:$Q$7501,'FILL RATE MANDATORY STOCK'!BK19,'DETAIL SALES'!$AB$10:$AB$7501,"Full",'DETAIL SALES'!$C$10:$C$7501,"9") -> 0 | CD19: =COUNTIFS('DETAIL SALES'!$Q$10:$Q$7501,'FILL RATE MANDATORY STOCK'!BK19,'DETAIL SALES'!$AB$10:$AB$7501,"No",'DETAIL SALES'!$C$10:$C$7501,"9") -> 0 | CE19: =COUNTIFS('DETAIL SALES'!$Q$10:$Q$7501,'FILL RATE MANDATORY STOCK'!BK19,'DETAIL SALES'!$AB$10:$AB$7501,"Full",'DETAIL SALES'!$C$10:$C$7501,"10") -> 0 | CF19: =COUNTIFS('DETAIL SALES'!$Q$10:$Q$7501,'FILL RATE MANDATORY STOCK'!BK19,'DETAIL SALES'!$AB$10:$AB$7501,"No",'DETAIL SALES'!$C$10:$C$7501,"10") -> 0 | CG19: =COUNTIFS('DETAIL SALES'!$Q$10:$Q$7501,'FILL RATE MANDATORY STOCK'!BK19,'DETAIL SALES'!$AB$10:$AB$7501,"Full",'DETAIL SALES'!$C$10:$C$7501,"11") -> 0 | CH19: =COUNTIFS('DETAIL SALES'!$Q$10:$Q$7501,'FILL RATE MANDATORY STOCK'!BK19,'DETAIL SALES'!$AB$10:$AB$7501,"No",'DETAIL SALES'!$C$10:$C$7501,"11") -> 0 | CI19: =COUNTIFS('DETAIL SALES'!$Q$10:$Q$7501,'FILL RATE MANDATORY STOCK'!BK19,'DETAIL SALES'!$AB$10:$AB$7501,"Full",'DETAIL SALES'!$C$10:$C$7501,"12") -> 0 | CJ19: =COUNTIFS('DETAIL SALES'!$Q$10:$Q$7501,'FILL RATE MANDATORY STOCK'!BK19,'DETAIL SALES'!$AB$10:$AB$7501,"No",'DETAIL SALES'!$C$10:$C$7501,"12") -> 0 | CK19: =COUNTIFS('DETAIL SALES'!$Q$10:$Q$7501,'FILL RATE MANDATORY STOCK'!BK19,'DETAIL SALES'!$AB$10:$AB$7501,"Full",'DETAIL SALES'!$C$10:$C$7501,"13") -> 0 | CL19: =COUNTIFS('DETAIL SALES'!$Q$10:$Q$7501,'FILL RATE MANDATORY STOCK'!BK19,'DETAIL SALES'!$AB$10:$AB$7501,"No",'DETAIL SALES'!$C$10:$C$7501,"13") -> 0 | CM19: =COUNTIFS('DETAIL SALES'!$Q$10:$Q$7501,'FILL RATE MANDATORY STOCK'!BK19,'DETAIL SALES'!$AB$10:$AB$7501,"Full",'DETAIL SALES'!$C$10:$C$7501,"14") -> 0 | CN19: =COUNTIFS('DETAIL SALES'!$Q$10:$Q$7501,'FILL RATE MANDATORY STOCK'!BK19,'DETAIL SALES'!$AB$10:$AB$7501,"No",'DETAIL SALES'!$C$10:$C$7501,"14") -> 0 | CO19: =COUNTIFS('DETAIL SALES'!$Q$10:$Q$7501,'FILL RATE MANDATORY STOCK'!BK19,'DETAIL SALES'!$AB$10:$AB$7501,"Full",'DETAIL SALES'!$C$10:$C$7501,"15") -> 0 | CP19: =COUNTIFS('DETAIL SALES'!$Q$10:$Q$7501,'FILL RATE MANDATORY STOCK'!BK19,'DETAIL SALES'!$AB$10:$AB$7501,"No",'DETAIL SALES'!$C$10:$C$7501,"15") -> 0 | CQ19: =COUNTIFS('DETAIL SALES'!$Q$10:$Q$7501,'FILL RATE MANDATORY STOCK'!BK19,'DETAIL SALES'!$AB$10:$AB$7501,"Full",'DETAIL SALES'!$C$10:$C$7501,"16") -> 0 | CR19: =COUNTIFS('DETAIL SALES'!$Q$10:$Q$7501,'FILL RATE MANDATORY STOCK'!BK19,'DETAIL SALES'!$AB$10:$AB$7501,"No",'DETAIL SALES'!$C$10:$C$7501,"16") -> 0 | CS19: =COUNTIFS('DETAIL SALES'!$Q$10:$Q$7501,'FILL RATE MANDATORY STOCK'!BK19,'DETAIL SALES'!$AB$10:$AB$7501,"Full",'DETAIL SALES'!$C$10:$C$7501,"17") -> 0 | CT19: =COUNTIFS('DETAIL SALES'!$Q$10:$Q$7501,'FILL RATE MANDATORY STOCK'!BK19,'DETAIL SALES'!$AB$10:$AB$7501,"No",'DETAIL SALES'!$C$10:$C$7501,"17") -> 0 | CU19: =COUNTIFS('DETAIL SALES'!$Q$10:$Q$7501,'FILL RATE MANDATORY STOCK'!BK19,'DETAIL SALES'!$AB$10:$AB$7501,"Full",'DETAIL SALES'!$C$10:$C$7501,"18") -> 0 | CV19: =COUNTIFS('DETAIL SALES'!$Q$10:$Q$7501,'FILL RATE MANDATORY STOCK'!BK19,'DETAIL SALES'!$AB$10:$AB$7501,"No",'DETAIL SALES'!$C$10:$C$7501,"18") -> 0 | CW19: =COUNTIFS('DETAIL SALES'!$Q$10:$Q$7501,'FILL RATE MANDATORY STOCK'!BK19,'DETAIL SALES'!$AB$10:$AB$7501,"Full",'DETAIL SALES'!$C$10:$C$7501,"19") -> 0 | CX19: =COUNTIFS('DETAIL SALES'!$Q$10:$Q$7501,'FILL RATE MANDATORY STOCK'!BK19,'DETAIL SALES'!$AB$10:$AB$7501,"No",'DETAIL SALES'!$C$10:$C$7501,"19") -> 0 | CY19: =COUNTIFS('DETAIL SALES'!$Q$10:$Q$7501,'FILL RATE MANDATORY STOCK'!BK19,'DETAIL SALES'!$AB$10:$AB$7501,"Full",'DETAIL SALES'!$C$10:$C$7501,"20") -> 0 | CZ19: =COUNTIFS('DETAIL SALES'!$Q$10:$Q$7501,'FILL RATE MANDATORY STOCK'!BK19,'DETAIL SALES'!$AB$10:$AB$7501,"No",'DETAIL SALES'!$C$10:$C$7501,"20") -> 0 | DA19: =COUNTIFS('DETAIL SALES'!$Q$10:$Q$7501,'FILL RATE MANDATORY STOCK'!BK19,'DETAIL SALES'!$AB$10:$AB$7501,"Full",'DETAIL SALES'!$C$10:$C$7501,"21") -> 0 | DB19: =COUNTIFS('DETAIL SALES'!$Q$10:$Q$7501,'FILL RATE MANDATORY STOCK'!BK19,'DETAIL SALES'!$AB$10:$AB$7501,"No",'DETAIL SALES'!$C$10:$C$7501,"21") -> 0 | DC19: =COUNTIFS('DETAIL SALES'!$Q$10:$Q$7501,'FILL RATE MANDATORY STOCK'!BK19,'DETAIL SALES'!$AB$10:$AB$7501,"Full",'DETAIL SALES'!$C$10:$C$7501,"22") -> 0 | DD19: =COUNTIFS('DETAIL SALES'!$Q$10:$Q$7501,'FILL RATE MANDATORY STOCK'!BK19,'DETAIL SALES'!$AB$10:$AB$7501,"No",'DETAIL SALES'!$C$10:$C$7501,"22") -> 0 | DE19: =COUNTIFS('DETAIL SALES'!$Q$10:$Q$7501,'FILL RATE MANDATORY STOCK'!BK19,'DETAIL SALES'!$AB$10:$AB$7501,"Full",'DETAIL SALES'!$C$10:$C$7501,"23") -> 0 | DF19: =COUNTIFS('DETAIL SALES'!$Q$10:$Q$7501,'FILL RATE MANDATORY STOCK'!BK19,'DETAIL SALES'!$AB$10:$AB$7501,"No",'DETAIL SALES'!$C$10:$C$7501,"23") -> 0 | DG19: =COUNTIFS('DETAIL SALES'!$Q$10:$Q$7501,'FILL RATE MANDATORY STOCK'!BK19,'DETAIL SALES'!$AB$10:$AB$7501,"Full",'DETAIL SALES'!$C$10:$C$7501,"24") -> 0 | DH19: =COUNTIFS('DETAIL SALES'!$Q$10:$Q$7501,'FILL RATE MANDATORY STOCK'!BK19,'DETAIL SALES'!$AB$10:$AB$7501,"No",'DETAIL SALES'!$C$10:$C$7501,"24") -> 0 | DI19: =COUNTIFS('DETAIL SALES'!$Q$10:$Q$7501,'FILL RATE MANDATORY STOCK'!BK19,'DETAIL SALES'!$AB$10:$AB$7501,"Full",'DETAIL SALES'!$C$10:$C$7501,"25") -> 0 | DJ19: =COUNTIFS('DETAIL SALES'!$Q$10:$Q$7501,'FILL RATE MANDATORY STOCK'!BK19,'DETAIL SALES'!$AB$10:$AB$7501,"No",'DETAIL SALES'!$C$10:$C$7501,"25") -> 0 | DK19: =COUNTIFS('DETAIL SALES'!$Q$10:$Q$7501,'FILL RATE MANDATORY STOCK'!BK19,'DETAIL SALES'!$AB$10:$AB$7501,"Full",'DETAIL SALES'!$C$10:$C$7501,"26") -> 0 | DL19: =COUNTIFS('DETAIL SALES'!$Q$10:$Q$7501,'FILL RATE MANDATORY STOCK'!BK19,'DETAIL SALES'!$AB$10:$AB$7501,"No",'DETAIL SALES'!$C$10:$C$7501,"26") -> 0 | DM19: =COUNTIFS('DETAIL SALES'!$Q$10:$Q$7501,'FILL RATE MANDATORY STOCK'!BK19,'DETAIL SALES'!$AB$10:$AB$7501,"Full",'DETAIL SALES'!$C$10:$C$7501,"27") -> 0 | DN19: =COUNTIFS('DETAIL SALES'!$Q$10:$Q$7501,'FILL RATE MANDATORY STOCK'!BK19,'DETAIL SALES'!$AB$10:$AB$7501,"No",'DETAIL SALES'!$C$10:$C$7501,"27") -> 0 | DO19: =COUNTIFS('DETAIL SALES'!$Q$10:$Q$7501,'FILL RATE MANDATORY STOCK'!BK19,'DETAIL SALES'!$AB$10:$AB$7501,"Full",'DETAIL SALES'!$C$10:$C$7501,"28") -> 0 | DP19: =COUNTIFS('DETAIL SALES'!$Q$10:$Q$7501,'FILL RATE MANDATORY STOCK'!BK19,'DETAIL SALES'!$AB$10:$AB$7501,"No",'DETAIL SALES'!$C$10:$C$7501,"28") -> 0 | DQ19: =COUNTIFS('DETAIL SALES'!$Q$10:$Q$7501,'FILL RATE MANDATORY STOCK'!BK19,'DETAIL SALES'!$AB$10:$AB$7501,"Full",'DETAIL SALES'!$C$10:$C$7501,"29") -> 0 | DR19: =COUNTIFS('DETAIL SALES'!$Q$10:$Q$7501,'FILL RATE MANDATORY STOCK'!BK19,'DETAIL SALES'!$AB$10:$AB$7501,"No",'DETAIL SALES'!$C$10:$C$7501,"29") -> 0 | DS19: =COUNTIFS('DETAIL SALES'!$Q$10:$Q$7501,'FILL RATE MANDATORY STOCK'!BK19,'DETAIL SALES'!$AB$10:$AB$7501,"Full",'DETAIL SALES'!$C$10:$C$7501,"30") -> 0 | DT19: =COUNTIFS('DETAIL SALES'!$Q$10:$Q$7501,'FILL RATE MANDATORY STOCK'!BK19,'DETAIL SALES'!$AB$10:$AB$7501,"No",'DETAIL SALES'!$C$10:$C$7501,"30") -> 0 | DU19: =COUNTIFS('DETAIL SALES'!$Q$10:$Q$7501,'FILL RATE MANDATORY STOCK'!\,'DETAIL SALES'!$AB$10:$AB$7501,"Full",'DETAIL SALES'!$C$10:$C$7501,"31") -> 0 | DV19: =COUNTIFS('DETAIL SALES'!$Q$10:$Q$7501,'FILL RATE MANDATORY STOCK'!BK19,'DETAIL SALES'!$AB$10:$AB$7501,"No",'DETAIL SALES'!$C$10:$C$7501,"31") -> 0 | DW19: =BM19+BO19+BQ19+BS19+BU19+BW19+BY19+CA19+CC19+CE19+CG19+CI19+CK19+CM19+CO19+CQ19+CS19+CU19+CW19+CY19+DA19+DC19+DE19+DG19+DI19+DK19+DM19+DO19+DQ19+DS19+DU19 -> 0 | DX19: =BN19+BP19+BR19+BT19+BV19+BX19+BZ19+CB19+CD19+CF19+CH19+CJ19+CL19+CN19+CP19+CR19+CT19+CV19+CX19+CZ19+DB19+DD19+DF19+DH19+DJ19+DL19+DN19+DP19+DR19+DT19+DV19 -> 0 | DY19: =DW19+DX19 -> 0 | DZ19: =DW19/DY19 -> #DIV/0!
A20: 11 | C20: =DAY(B20) -> 0 | D20: =MONTH(B20) -> 1 | E20: =YEAR(B20) -> 1900 | Y20: =X20*U20 -> 0 | Z20: =Y20*1.1 -> 0 | AB20: =IF(S20="","",IF(S20-U20=0,"Full","No")) | AC20: =IF(AND(S20>U20,V20=0),"Lost",IF(AND(S20>U20,V20<(S20-U20)),"Lost","")) | AD20: =IF(AND(S20>U20,V20=0),S20-U20,IF(AND(S20>U20,V20<(S20-U20)),S20-(U20+V20),"")) | AJ20: 9 | AK20: Travel & Tourism | AL20: Jasa Travel | AN20: PT. CATUR KOKOH MOBIL NASIONAL | AQ20: Food Industry | AW20: =AV20/$AV$40 -> #DIV/0! | AZ20: =AY20/(AX20+AY20) -> #DIV/0! | BE20: =MAX(BE17:BE19)+1 -> 9 | BF20: Oil Filter (main) | BG20: FM2P (P11C-363 MODEL) | BH20: 156071531L | BI20: =VLOOKUP(BH20,#REF!,8,FALSE) -> #REF! | BJ20: 20000 | BK20: 1 | BL20: 0.83333333 | BM20: =COUNTIFS('DETAIL SALES'!$Q$10:$Q$7501,'FILL RATE MANDATORY STOCK'!BK20,'DETAIL SALES'!$AB$10:$AB$7501,"Full",'DETAIL SALES'!$C$10:$C$7501,"1") -> 0 | BN20: =COUNTIFS('DETAIL SALES'!$Q$10:$Q$7501,'FILL RATE MANDATORY STOCK'!BK20,'DETAIL SALES'!$AB$10:$AB$7501,"No",'DETAIL SALES'!$C$10:$C$7501,"1") -> 0 | BO20: =COUNTIFS('DETAIL SALES'!$Q$10:$Q$7501,'FILL RATE MANDATORY STOCK'!BK20,'DETAIL SALES'!$AB$10:$AB$7501,"Full",'DETAIL SALES'!$C$10:$C$7501,"2") -> 0 | BP20: =COUNTIFS('DETAIL SALES'!$Q$10:$Q$7501,'FILL RATE MANDATORY STOCK'!BK20,'DETAIL SALES'!$AB$10:$AB$7501,"No",'DETAIL SALES'!$C$10:$C$7501,"2") -> 0 | BQ20: =COUNTIFS('DETAIL SALES'!$Q$10:$Q$7501,'FILL RATE MANDATORY STOCK'!BK20,'DETAIL SALES'!$AB$10:$AB$7501,"Full",'DETAIL SALES'!$C$10:$C$7501,"3") -> 0 | BR20: =COUNTIFS('DETAIL SALES'!$Q$10:$Q$7501,'FILL RATE MANDATORY STOCK'!BK20,'DETAIL SALES'!$AB$10:$AB$7501,"No",'DETAIL SALES'!$C$10:$C$7501,"3") -> 0 | BS20: =COUNTIFS('DETAIL SALES'!$Q$10:$Q$7501,'FILL RATE MANDATORY STOCK'!BK20,'DETAIL SALES'!$AB$10:$AB$7501,"Full",'DETAIL SALES'!$C$10:$C$7501,"4") -> 0 | BT20: =COUNTIFS('DETAIL SALES'!$Q$10:$Q$7501,'FILL RATE MANDATORY STOCK'!BK20,'DETAIL SALES'!$AB$10:$AB$7501,"No",'DETAIL SALES'!$C$10:$C$7501,"4") -> 0 | BU20: =COUNTIFS('DETAIL SALES'!$Q$10:$Q$7501,'FILL RATE MANDATORY STOCK'!BK20,'DETAIL SALES'!$AB$10:$AB$7501,"Full",'DETAIL SALES'!$C$10:$C$7501,"5") -> 0 | BV20: =COUNTIFS('DETAIL SALES'!$Q$10:$Q$7501,'FILL RATE MANDATORY STOCK'!BK20,'DETAIL SALES'!$AB$10:$AB$7501,"No",'DETAIL SALES'!$C$10:$C$7501,"5") -> 0 | BW20: =COUNTIFS('DETAIL SALES'!$Q$10:$Q$7501,'FILL RATE MANDATORY STOCK'!BK20,'DETAIL SALES'!$AB$10:$AB$7501,"Full",'DETAIL SALES'!$C$10:$C$7501,"6") -> 0 | BX20: =COUNTIFS('DETAIL SALES'!$Q$10:$Q$7501,'FILL RATE MANDATORY STOCK'!BK20,'DETAIL SALES'!$AB$10:$AB$7501,"No",'DETAIL SALES'!$C$10:$C$7501,"6") -> 0 | BY20: =COUNTIFS('DETAIL SALES'!$Q$10:$Q$7501,'FILL RATE MANDATORY STOCK'!BK20,'DETAIL SALES'!$AB$10:$AB$7501,"Full",'DETAIL SALES'!$C$10:$C$7501,"7") -> 0 | BZ20: =COUNTIFS('DETAIL SALES'!$Q$10:$Q$7501,'FILL RATE MANDATORY STOCK'!BK20,'DETAIL SALES'!$AB$10:$AB$7501,"No",'DETAIL SALES'!$C$10:$C$7501,"7") -> 0 | CA20: =COUNTIFS('DETAIL SALES'!$Q$10:$Q$7501,'FILL RATE MANDATORY STOCK'!BK20,'DETAIL SALES'!$AB$10:$AB$7501,"Full",'DETAIL SALES'!$C$10:$C$7501,"8") -> 0 | CB20: =COUNTIFS('DETAIL SALES'!$Q$10:$Q$7501,'FILL RATE MANDATORY STOCK'!BK20,'DETAIL SALES'!$AB$10:$AB$7501,"No",'DETAIL SALES'!$C$10:$C$7501,"8") -> 0 | CC20: =COUNTIFS('DETAIL SALES'!$Q$10:$Q$7501,'FILL RATE MANDATORY STOCK'!BK20,'DETAIL SALES'!$AB$10:$AB$7501,"Full",'DETAIL SALES'!$C$10:$C$7501,"9") -> 0 | CD20: =COUNTIFS('DETAIL SALES'!$Q$10:$Q$7501,'FILL RATE MANDATORY STOCK'!BK20,'DETAIL SALES'!$AB$10:$AB$7501,"No",'DETAIL SALES'!$C$10:$C$7501,"9") -> 0 | CE20: =COUNTIFS('DETAIL SALES'!$Q$10:$Q$7501,'FILL RATE MANDATORY STOCK'!BK20,'DETAIL SALES'!$AB$10:$AB$7501,"Full",'DETAIL SALES'!$C$10:$C$7501,"10") -> 0 | CF20: =COUNTIFS('DETAIL SALES'!$Q$10:$Q$7501,'FILL RATE MANDATORY STOCK'!BK20,'DETAIL SALES'!$AB$10:$AB$7501,"No",'DETAIL SALES'!$C$10:$C$7501,"10") -> 0 | CG20: =COUNTIFS('DETAIL SALES'!$Q$10:$Q$7501,'FILL RATE MANDATORY STOCK'!BK20,'DETAIL SALES'!$AB$10:$AB$7501,"Full",'DETAIL SALES'!$C$10:$C$7501,"11") -> 0 | CH20: =COUNTIFS('DETAIL SALES'!$Q$10:$Q$7501,'FILL RATE MANDATORY STOCK'!BK20,'DETAIL SALES'!$AB$10:$AB$7501,"No",'DETAIL SALES'!$C$10:$C$7501,"11") -> 0 | CI20: =COUNTIFS('DETAIL SALES'!$Q$10:$Q$7501,'FILL RATE MANDATORY STOCK'!BK20,'DETAIL SALES'!$AB$10:$AB$7501,"Full",'DETAIL SALES'!$C$10:$C$7501,"12") -> 0 | CJ20: =COUNTIFS('DETAIL SALES'!$Q$10:$Q$7501,'FILL RATE MANDATORY STOCK'!BK20,'DETAIL SALES'!$AB$10:$AB$7501,"No",'DETAIL SALES'!$C$10:$C$7501,"12") -> 0 | CK20: =COUNTIFS('DETAIL SALES'!$Q$10:$Q$7501,'FILL RATE MANDATORY STOCK'!BK20,'DETAIL SALES'!$AB$10:$AB$7501,"Full",'DETAIL SALES'!$C$10:$C$7501,"13") -> 0 | CL20: =COUNTIFS('DETAIL SALES'!$Q$10:$Q$7501,'FILL RATE MANDATORY STOCK'!BK20,'DETAIL SALES'!$AB$10:$AB$7501,"No",'DETAIL SALES'!$C$10:$C$7501,"13") -> 0 | CM20: =COUNTIFS('DETAIL SALES'!$Q$10:$Q$7501,'FILL RATE MANDATORY STOCK'!BK20,'DETAIL SALES'!$AB$10:$AB$7501,"Full",'DETAIL SALES'!$C$10:$C$7501,"14") -> 0 | CN20: =COUNTIFS('DETAIL SALES'!$Q$10:$Q$7501,'FILL RATE MANDATORY STOCK'!BK20,'DETAIL SALES'!$AB$10:$AB$7501,"No",'DETAIL SALES'!$C$10:$C$7501,"14") -> 0 | CO20: =COUNTIFS('DETAIL SALES'!$Q$10:$Q$7501,'FILL RATE MANDATORY STOCK'!BK20,'DETAIL SALES'!$AB$10:$AB$7501,"Full",'DETAIL SALES'!$C$10:$C$7501,"15") -> 0 | CP20: =COUNTIFS('DETAIL SALES'!$Q$10:$Q$7501,'FILL RATE MANDATORY STOCK'!BK20,'DETAIL SALES'!$AB$10:$AB$7501,"No",'DETAIL SALES'!$C$10:$C$7501,"15") -> 0 | CQ20: =COUNTIFS('DETAIL SALES'!$Q$10:$Q$7501,'FILL RATE MANDATORY STOCK'!BK20,'DETAIL SALES'!$AB$10:$AB$7501,"Full",'DETAIL SALES'!$C$10:$C$7501,"16") -> 0 | CR20: =COUNTIFS('DETAIL SALES'!$Q$10:$Q$7501,'FILL RATE MANDATORY STOCK'!BK20,'DETAIL SALES'!$AB$10:$AB$7501,"No",'DETAIL SALES'!$C$10:$C$7501,"16") -> 0 | CS20: =COUNTIFS('DETAIL SALES'!$Q$10:$Q$7501,'FILL RATE MANDATORY STOCK'!BK20,'DETAIL SALES'!$AB$10:$AB$7501,"Full",'DETAIL SALES'!$C$10:$C$7501,"17") -> 0 | CT20: =COUNTIFS('DETAIL SALES'!$Q$10:$Q$7501,'FILL RATE MANDATORY STOCK'!BK20,'DETAIL SALES'!$AB$10:$AB$7501,"No",'DETAIL SALES'!$C$10:$C$7501,"17") -> 0 | CU20: =COUNTIFS('DETAIL SALES'!$Q$10:$Q$7501,'FILL RATE MANDATORY STOCK'!BK20,'DETAIL SALES'!$AB$10:$AB$7501,"Full",'DETAIL SALES'!$C$10:$C$7501,"18") -> 0 | CV20: =COUNTIFS('DETAIL SALES'!$Q$10:$Q$7501,'FILL RATE MANDATORY STOCK'!BK20,'DETAIL SALES'!$AB$10:$AB$7501,"No",'DETAIL SALES'!$C$10:$C$7501,"18") -> 0 | CW20: =COUNTIFS('DETAIL SALES'!$Q$10:$Q$7501,'FILL RATE MANDATORY STOCK'!BK20,'DETAIL SALES'!$AB$10:$AB$7501,"Full",'DETAIL SALES'!$C$10:$C$7501,"19") -> 0 | CX20: =COUNTIFS('DETAIL SALES'!$Q$10:$Q$7501,'FILL RATE MANDATORY STOCK'!BK20,'DETAIL SALES'!$AB$10:$AB$7501,"No",'DETAIL SALES'!$C$10:$C$7501,"19") -> 0 | CY20: =COUNTIFS('DETAIL SALES'!$Q$10:$Q$7501,'FILL RATE MANDATORY STOCK'!BK20,'DETAIL SALES'!$AB$10:$AB$7501,"Full",'DETAIL SALES'!$C$10:$C$7501,"20") -> 0 | CZ20: =COUNTIFS('DETAIL SALES'!$Q$10:$Q$7501,'FILL RATE MANDATORY STOCK'!BK20,'DETAIL SALES'!$AB$10:$AB$7501,"No",'DETAIL SALES'!$C$10:$C$7501,"20") -> 0 | DA20: =COUNTIFS('DETAIL SALES'!$Q$10:$Q$7501,'FILL RATE MANDATORY STOCK'!BK20,'DETAIL SALES'!$AB$10:$AB$7501,"Full",'DETAIL SALES'!$C$10:$C$7501,"21") -> 0 | DB20: =COUNTIFS('DETAIL SALES'!$Q$10:$Q$7501,'FILL RATE MANDATORY STOCK'!BK20,'DETAIL SALES'!$AB$10:$AB$7501,"No",'DETAIL SALES'!$C$10:$C$7501,"21") -> 0 | DC20: =COUNTIFS('DETAIL SALES'!$Q$10:$Q$7501,'FILL RATE MANDATORY STOCK'!BK20,'DETAIL SALES'!$AB$10:$AB$7501,"Full",'DETAIL SALES'!$C$10:$C$7501,"22") -> 0 | DD20: =COUNTIFS('DETAIL SALES'!$Q$10:$Q$7501,'FILL RATE MANDATORY STOCK'!BK20,'DETAIL SALES'!$AB$10:$AB$7501,"No",'DETAIL SALES'!$C$10:$C$7501,"22") -> 0 | DE20: =COUNTIFS('DETAIL SALES'!$Q$10:$Q$7501,'FILL RATE MANDATORY STOCK'!BK20,'DETAIL SALES'!$AB$10:$AB$7501,"Full",'DETAIL SALES'!$C$10:$C$7501,"23") -> 0 | DF20: =COUNTIFS('DETAIL SALES'!$Q$10:$Q$7501,'FILL RATE MANDATORY STOCK'!BK20,'DETAIL SALES'!$AB$10:$AB$7501,"No",'DETAIL SALES'!$C$10:$C$7501,"23") -> 0 | DG20: =COUNTIFS('DETAIL SALES'!$Q$10:$Q$7501,'FILL RATE MANDATORY STOCK'!BK20,'DETAIL SALES'!$AB$10:$AB$7501,"Full",'DETAIL SALES'!$C$10:$C$7501,"24") -> 0 | DH20: =COUNTIFS('DETAIL SALES'!$Q$10:$Q$7501,'FILL RATE MANDATORY STOCK'!BK20,'DETAIL SALES'!$AB$10:$AB$7501,"No",'DETAIL SALES'!$C$10:$C$7501,"24") -> 0 | DI20: =COUNTIFS('DETAIL SALES'!$Q$10:$Q$7501,'FILL RATE MANDATORY STOCK'!BK20,'DETAIL SALES'!$AB$10:$AB$7501,"Full",'DETAIL SALES'!$C$10:$C$7501,"25") -> 0 | DJ20: =COUNTIFS('DETAIL SALES'!$Q$10:$Q$7501,'FILL RATE MANDATORY STOCK'!BK20,'DETAIL SALES'!$AB$10:$AB$7501,"No",'DETAIL SALES'!$C$10:$C$7501,"25") -> 0 | DK20: =COUNTIFS('DETAIL SALES'!$Q$10:$Q$7501,'FILL RATE MANDATORY STOCK'!BK20,'DETAIL SALES'!$AB$10:$AB$7501,"Full",'DETAIL SALES'!$C$10:$C$7501,"26") -> 0 | DL20: =COUNTIFS('DETAIL SALES'!$Q$10:$Q$7501,'FILL RATE MANDATORY STOCK'!BK20,'DETAIL SALES'!$AB$10:$AB$7501,"No",'DETAIL SALES'!$C$10:$C$7501,"26") -> 0 | DM20: =COUNTIFS('DETAIL SALES'!$Q$10:$Q$7501,'FILL RATE MANDATORY STOCK'!BK20,'DETAIL SALES'!$AB$10:$AB$7501,"Full",'DETAIL SALES'!$C$10:$C$7501,"27") -> 0 | DN20: =COUNTIFS('DETAIL SALES'!$Q$10:$Q$7501,'FILL RATE MANDATORY STOCK'!BK20,'DETAIL SALES'!$AB$10:$AB$7501,"No",'DETAIL SALES'!$C$10:$C$7501,"27") -> 0 | DO20: =COUNTIFS('DETAIL SALES'!$Q$10:$Q$7501,'FILL RATE MANDATORY STOCK'!BK20,'DETAIL SALES'!$AB$10:$AB$7501,"Full",'DETAIL SALES'!$C$10:$C$7501,"28") -> 0 | DP20: =COUNTIFS('DETAIL SALES'!$Q$10:$Q$7501,'FILL RATE MANDATORY STOCK'!BK20,'DETAIL SALES'!$AB$10:$AB$7501,"No",'DETAIL SALES'!$C$10:$C$7501,"28") -> 0 | DQ20: =COUNTIFS('DETAIL SALES'!$Q$10:$Q$7501,'FILL RATE MANDATORY STOCK'!BK20,'DETAIL SALES'!$AB$10:$AB$7501,"Full",'DETAIL SALES'!$C$10:$C$7501,"29") -> 0 | DR20: =COUNTIFS('DETAIL SALES'!$Q$10:$Q$7501,'FILL RATE MANDATORY STOCK'!BK20,'DETAIL SALES'!$AB$10:$AB$7501,"No",'DETAIL SALES'!$C$10:$C$7501,"29") -> 0 | DS20: =COUNTIFS('DETAIL SALES'!$Q$10:$Q$7501,'FILL RATE MANDATORY STOCK'!BK20,'DETAIL SALES'!$AB$10:$AB$7501,"Full",'DETAIL SALES'!$C$10:$C$7501,"30") -> 0 | DT20: =COUNTIFS('DETAIL SALES'!$Q$10:$Q$7501,'FILL RATE MANDATORY STOCK'!BK20,'DETAIL SALES'!$AB$10:$AB$7501,"No",'DETAIL SALES'!$C$10:$C$7501,"30") -> 0 | DU20: =COUNTIFS('DETAIL SALES'!$Q$10:$Q$7501,'FILL RATE MANDATORY STOCK'!\,'DETAIL SALES'!$AB$10:$AB$7501,"Full",'DETAIL SALES'!$C$10:$C$7501,"31") -> 0 | DV20: =COUNTIFS('DETAIL SALES'!$Q$10:$Q$7501,'FILL RATE MANDATORY STOCK'!BK20,'DETAIL SALES'!$AB$10:$AB$7501,"No",'DETAIL SALES'!$C$10:$C$7501,"31") -> 0 | DW20: =BM20+BO20+BQ20+BS20+BU20+BW20+BY20+CA20+CC20+CE20+CG20+CI20+CK20+CM20+CO20+CQ20+CS20+CU20+CW20+CY20+DA20+DC20+DE20+DG20+DI20+DK20+DM20+DO20+DQ20+DS20+DU20 -> 0 | DX20: =BN20+BP20+BR20+BT20+BV20+BX20+BZ20+CB20+CD20+CF20+CH20+CJ20+CL20+CN20+CP20+CR20+CT20+CV20+CX20+CZ20+DB20+DD20+DF20+DH20+DJ20+DL20+DN20+DP20+DR20+DT20+DV20 -> 0 | DY20: =DW20+DX20 -> 0 | DZ20: =DW20/DY20 -> #DIV/0!
A21: 12 | C21: =DAY(B21) -> 0 | D21: =MONTH(B21) -> 1 | E21: =YEAR(B21) -> 1900 | Y21: =X21*U21 -> 0 | Z21: =Y21*1.1 -> 0 | AB21: =IF(S21="","",IF(S21-U21=0,"Full","No")) | AC21: =IF(AND(S21>U21,V21=0),"Lost",IF(AND(S21>U21,V21<(S21-U21)),"Lost","")) | AD21: =IF(AND(S21>U21,V21=0),S21-U21,IF(AND(S21>U21,V21<(S21-U21)),S21-(U21+V21),"")) | AJ21: 10 | AK21: Logging | AL21: Kayu | AN21: PT. CEMACO MAKMUR CORPORATAMA | AQ21: Consumer Goods | AW21: =AV21/$AV$40 -> #DIV/0! | AZ21: =AY21/(AX21+AY21) -> #DIV/0! | BE21: =MAX(BE18:BE20)+1 -> 10 | BF21: Oil Filter (bypass) | BG21: FM2P (P11C-363 MODEL) | BH21: 156071560L | BI21: =VLOOKUP(BH21,#REF!,8,FALSE) -> #REF! | BJ21: 20000 | BK21: 1 | BL21: 1.1666667 | BM21: =COUNTIFS('DETAIL SALES'!$Q$10:$Q$7501,'FILL RATE MANDATORY STOCK'!BK21,'DETAIL SALES'!$AB$10:$AB$7501,"Full",'DETAIL SALES'!$C$10:$C$7501,"1") -> 0 | BN21: =COUNTIFS('DETAIL SALES'!$Q$10:$Q$7501,'FILL RATE MANDATORY STOCK'!BK21,'DETAIL SALES'!$AB$10:$AB$7501,"No",'DETAIL SALES'!$C$10:$C$7501,"1") -> 0 | BO21: =COUNTIFS('DETAIL SALES'!$Q$10:$Q$7501,'FILL RATE MANDATORY STOCK'!BK21,'DETAIL SALES'!$AB$10:$AB$7501,"Full",'DETAIL SALES'!$C$10:$C$7501,"2") -> 0 | BP21: =COUNTIFS('DETAIL SALES'!$Q$10:$Q$7501,'FILL RATE MANDATORY STOCK'!BK21,'DETAIL SALES'!$AB$10:$AB$7501,"No",'DETAIL SALES'!$C$10:$C$7501,"2") -> 0 | BQ21: =COUNTIFS('DETAIL SALES'!$Q$10:$Q$7501,'FILL RATE MANDATORY STOCK'!BK21,'DETAIL SALES'!$AB$10:$AB$7501,"Full",'DETAIL SALES'!$C$10:$C$7501,"3") -> 0 | BR21: =COUNTIFS('DETAIL SALES'!$Q$10:$Q$7501,'FILL RATE MANDATORY STOCK'!BK21,'DETAIL SALES'!$AB$10:$AB$7501,"No",'DETAIL SALES'!$C$10:$C$7501,"3") -> 0 | BS21: =COUNTIFS('DETAIL SALES'!$Q$10:$Q$7501,'FILL RATE MANDATORY STOCK'!BK21,'DETAIL SALES'!$AB$10:$AB$7501,"Full",'DETAIL SALES'!$C$10:$C$7501,"4") -> 0 | BT21: =COUNTIFS('DETAIL SALES'!$Q$10:$Q$7501,'FILL RATE MANDATORY STOCK'!BK21,'DETAIL SALES'!$AB$10:$AB$7501,"No",'DETAIL SALES'!$C$10:$C$7501,"4") -> 0 | BU21: =COUNTIFS('DETAIL SALES'!$Q$10:$Q$7501,'FILL RATE MANDATORY STOCK'!BK21,'DETAIL SALES'!$AB$10:$AB$7501,"Full",'DETAIL SALES'!$C$10:$C$7501,"5") -> 0 | BV21: =COUNTIFS('DETAIL SALES'!$Q$10:$Q$7501,'FILL RATE MANDATORY STOCK'!BK21,'DETAIL SALES'!$AB$10:$AB$7501,"No",'DETAIL SALES'!$C$10:$C$7501,"5") -> 0 | BW21: =COUNTIFS('DETAIL SALES'!$Q$10:$Q$7501,'FILL RATE MANDATORY STOCK'!BK21,'DETAIL SALES'!$AB$10:$AB$7501,"Full",'DETAIL SALES'!$C$10:$C$7501,"6") -> 0 | BX21: =COUNTIFS('DETAIL SALES'!$Q$10:$Q$7501,'FILL RATE MANDATORY STOCK'!BK21,'DETAIL SALES'!$AB$10:$AB$7501,"No",'DETAIL SALES'!$C$10:$C$7501,"6") -> 0 | BY21: =COUNTIFS('DETAIL SALES'!$Q$10:$Q$7501,'FILL RATE MANDATORY STOCK'!BK21,'DETAIL SALES'!$AB$10:$AB$7501,"Full",'DETAIL SALES'!$C$10:$C$7501,"7") -> 0 | BZ21: =COUNTIFS('DETAIL SALES'!$Q$10:$Q$7501,'FILL RATE MANDATORY STOCK'!BK21,'DETAIL SALES'!$AB$10:$AB$7501,"No",'DETAIL SALES'!$C$10:$C$7501,"7") -> 0 | CA21: =COUNTIFS('DETAIL SALES'!$Q$10:$Q$7501,'FILL RATE MANDATORY STOCK'!BK21,'DETAIL SALES'!$AB$10:$AB$7501,"Full",'DETAIL SALES'!$C$10:$C$7501,"8") -> 0 | CB21: =COUNTIFS('DETAIL SALES'!$Q$10:$Q$7501,'FILL RATE MANDATORY STOCK'!BK21,'DETAIL SALES'!$AB$10:$AB$7501,"No",'DETAIL SALES'!$C$10:$C$7501,"8") -> 0 | CC21: =COUNTIFS('DETAIL SALES'!$Q$10:$Q$7501,'FILL RATE MANDATORY STOCK'!BK21,'DETAIL SALES'!$AB$10:$AB$7501,"Full",'DETAIL SALES'!$C$10:$C$7501,"9") -> 0 | CD21: =COUNTIFS('DETAIL SALES'!$Q$10:$Q$7501,'FILL RATE MANDATORY STOCK'!BK21,'DETAIL SALES'!$AB$10:$AB$7501,"No",'DETAIL SALES'!$C$10:$C$7501,"9") -> 0 | CE21: =COUNTIFS('DETAIL SALES'!$Q$10:$Q$7501,'FILL RATE MANDATORY STOCK'!BK21,'DETAIL SALES'!$AB$10:$AB$7501,"Full",'DETAIL SALES'!$C$10:$C$7501,"10") -> 0 | CF21: =COUNTIFS('DETAIL SALES'!$Q$10:$Q$7501,'FILL RATE MANDATORY STOCK'!BK21,'DETAIL SALES'!$AB$10:$AB$7501,"No",'DETAIL SALES'!$C$10:$C$7501,"10") -> 0 | CG21: =COUNTIFS('DETAIL SALES'!$Q$10:$Q$7501,'FILL RATE MANDATORY STOCK'!BK21,'DETAIL SALES'!$AB$10:$AB$7501,"Full",'DETAIL SALES'!$C$10:$C$7501,"11") -> 0 | CH21: =COUNTIFS('DETAIL SALES'!$Q$10:$Q$7501,'FILL RATE MANDATORY STOCK'!BK21,'DETAIL SALES'!$AB$10:$AB$7501,"No",'DETAIL SALES'!$C$10:$C$7501,"11") -> 0 | CI21: =COUNTIFS('DETAIL SALES'!$Q$10:$Q$7501,'FILL RATE MANDATORY STOCK'!BK21,'DETAIL SALES'!$AB$10:$AB$7501,"Full",'DETAIL SALES'!$C$10:$C$7501,"12") -> 0 | CJ21: =COUNTIFS('DETAIL SALES'!$Q$10:$Q$7501,'FILL RATE MANDATORY STOCK'!BK21,'DETAIL SALES'!$AB$10:$AB$7501,"No",'DETAIL SALES'!$C$10:$C$7501,"12") -> 0 | CK21: =COUNTIFS('DETAIL SALES'!$Q$10:$Q$7501,'FILL RATE MANDATORY STOCK'!BK21,'DETAIL SALES'!$AB$10:$AB$7501,"Full",'DETAIL SALES'!$C$10:$C$7501,"13") -> 0 | CL21: =COUNTIFS('DETAIL SALES'!$Q$10:$Q$7501,'FILL RATE MANDATORY STOCK'!BK21,'DETAIL SALES'!$AB$10:$AB$7501,"No",'DETAIL SALES'!$C$10:$C$7501,"13") -> 0 | CM21: =COUNTIFS('DETAIL SALES'!$Q$10:$Q$7501,'FILL RATE MANDATORY STOCK'!BK21,'DETAIL SALES'!$AB$10:$AB$7501,"Full",'DETAIL SALES'!$C$10:$C$7501,"14") -> 0 | CN21: =COUNTIFS('DETAIL SALES'!$Q$10:$Q$7501,'FILL RATE MANDATORY STOCK'!BK21,'DETAIL SALES'!$AB$10:$AB$7501,"No",'DETAIL SALES'!$C$10:$C$7501,"14") -> 0 | CO21: =COUNTIFS('DETAIL SALES'!$Q$10:$Q$7501,'FILL RATE MANDATORY STOCK'!BK21,'DETAIL SALES'!$AB$10:$AB$7501,"Full",'DETAIL SALES'!$C$10:$C$7501,"15") -> 0 | CP21: =COUNTIFS('DETAIL SALES'!$Q$10:$Q$7501,'FILL RATE MANDATORY STOCK'!BK21,'DETAIL SALES'!$AB$10:$AB$7501,"No",'DETAIL SALES'!$C$10:$C$7501,"15") -> 0 | CQ21: =COUNTIFS('DETAIL SALES'!$Q$10:$Q$7501,'FILL RATE MANDATORY STOCK'!BK21,'DETAIL SALES'!$AB$10:$AB$7501,"Full",'DETAIL SALES'!$C$10:$C$7501,"16") -> 0 | CR21: =COUNTIFS('DETAIL SALES'!$Q$10:$Q$7501,'FILL RATE MANDATORY STOCK'!BK21,'DETAIL SALES'!$AB$10:$AB$7501,"No",'DETAIL SALES'!$C$10:$C$7501,"16") -> 0 | CS21: =COUNTIFS('DETAIL SALES'!$Q$10:$Q$7501,'FILL RATE MANDATORY STOCK'!BK21,'DETAIL SALES'!$AB$10:$AB$7501,"Full",'DETAIL SALES'!$C$10:$C$7501,"17") -> 0 | CT21: =COUNTIFS('DETAIL SALES'!$Q$10:$Q$7501,'FILL RATE MANDATORY STOCK'!BK21,'DETAIL SALES'!$AB$10:$AB$7501,"No",'DETAIL SALES'!$C$10:$C$7501,"17") -> 0 | CU21: =COUNTIFS('DETAIL SALES'!$Q$10:$Q$7501,'FILL RATE MANDATORY STOCK'!BK21,'DETAIL SALES'!$AB$10:$AB$7501,"Full",'DETAIL SALES'!$C$10:$C$7501,"18") -> 0 | CV21: =COUNTIFS('DETAIL SALES'!$Q$10:$Q$7501,'FILL RATE MANDATORY STOCK'!BK21,'DETAIL SALES'!$AB$10:$AB$7501,"No",'DETAIL SALES'!$C$10:$C$7501,"18") -> 0 | CW21: =COUNTIFS('DETAIL SALES'!$Q$10:$Q$7501,'FILL RATE MANDATORY STOCK'!BK21,'DETAIL SALES'!$AB$10:$AB$7501,"Full",'DETAIL SALES'!$C$10:$C$7501,"19") -> 0 | CX21: =COUNTIFS('DETAIL SALES'!$Q$10:$Q$7501,'FILL RATE MANDATORY STOCK'!BK21,'DETAIL SALES'!$AB$10:$AB$7501,"No",'DETAIL SALES'!$C$10:$C$7501,"19") -> 0 | CY21: =COUNTIFS('DETAIL SALES'!$Q$10:$Q$7501,'FILL RATE MANDATORY STOCK'!BK21,'DETAIL SALES'!$AB$10:$AB$7501,"Full",'DETAIL SALES'!$C$10:$C$7501,"20") -> 0 | CZ21: =COUNTIFS('DETAIL SALES'!$Q$10:$Q$7501,'FILL RATE MANDATORY STOCK'!BK21,'DETAIL SALES'!$AB$10:$AB$7501,"No",'DETAIL SALES'!$C$10:$C$7501,"20") -> 0 | DA21: =COUNTIFS('DETAIL SALES'!$Q$10:$Q$7501,'FILL RATE MANDATORY STOCK'!BK21,'DETAIL SALES'!$AB$10:$AB$7501,"Full",'DETAIL SALES'!$C$10:$C$7501,"21") -> 0 | DB21: =COUNTIFS('DETAIL SALES'!$Q$10:$Q$7501,'FILL RATE MANDATORY STOCK'!BK21,'DETAIL SALES'!$AB$10:$AB$7501,"No",'DETAIL SALES'!$C$10:$C$7501,"21") -> 0 | DC21: =COUNTIFS('DETAIL SALES'!$Q$10:$Q$7501,'FILL RATE MANDATORY STOCK'!BK21,'DETAIL SALES'!$AB$10:$AB$7501,"Full",'DETAIL SALES'!$C$10:$C$7501,"22") -> 0 | DD21: =COUNTIFS('DETAIL SALES'!$Q$10:$Q$7501,'FILL RATE MANDATORY STOCK'!BK21,'DETAIL SALES'!$AB$10:$AB$7501,"No",'DETAIL SALES'!$C$10:$C$7501,"22") -> 0 | DE21: =COUNTIFS('DETAIL SALES'!$Q$10:$Q$7501,'FILL RATE MANDATORY STOCK'!BK21,'DETAIL SALES'!$AB$10:$AB$7501,"Full",'DETAIL SALES'!$C$10:$C$7501,"23") -> 0 | DF21: =COUNTIFS('DETAIL SALES'!$Q$10:$Q$7501,'FILL RATE MANDATORY STOCK'!BK21,'DETAIL SALES'!$AB$10:$AB$7501,"No",'DETAIL SALES'!$C$10:$C$7501,"23") -> 0 | DG21: =COUNTIFS('DETAIL SALES'!$Q$10:$Q$7501,'FILL RATE MANDATORY STOCK'!BK21,'DETAIL SALES'!$AB$10:$AB$7501,"Full",'DETAIL SALES'!$C$10:$C$7501,"24") -> 0 | DH21: =COUNTIFS('DETAIL SALES'!$Q$10:$Q$7501,'FILL RATE MANDATORY STOCK'!BK21,'DETAIL SALES'!$AB$10:$AB$7501,"No",'DETAIL SALES'!$C$10:$C$7501,"24") -> 0 | DI21: =COUNTIFS('DETAIL SALES'!$Q$10:$Q$7501,'FILL RATE MANDATORY STOCK'!BK21,'DETAIL SALES'!$AB$10:$AB$7501,"Full",'DETAIL SALES'!$C$10:$C$7501,"25") -> 0 | DJ21: =COUNTIFS('DETAIL SALES'!$Q$10:$Q$7501,'FILL RATE MANDATORY STOCK'!BK21,'DETAIL SALES'!$AB$10:$AB$7501,"No",'DETAIL SALES'!$C$10:$C$7501,"25") -> 0 | DK21: =COUNTIFS('DETAIL SALES'!$Q$10:$Q$7501,'FILL RATE MANDATORY STOCK'!BK21,'DETAIL SALES'!$AB$10:$AB$7501,"Full",'DETAIL SALES'!$C$10:$C$7501,"26") -> 0 | DL21: =COUNTIFS('DETAIL SALES'!$Q$10:$Q$7501,'FILL RATE MANDATORY STOCK'!BK21,'DETAIL SALES'!$AB$10:$AB$7501,"No",'DETAIL SALES'!$C$10:$C$7501,"26") -> 0 | DM21: =COUNTIFS('DETAIL SALES'!$Q$10:$Q$7501,'FILL RATE MANDATORY STOCK'!BK21,'DETAIL SALES'!$AB$10:$AB$7501,"Full",'DETAIL SALES'!$C$10:$C$7501,"27") -> 0 | DN21: =COUNTIFS('DETAIL SALES'!$Q$10:$Q$7501,'FILL RATE MANDATORY STOCK'!BK21,'DETAIL SALES'!$AB$10:$AB$7501,"No",'DETAIL SALES'!$C$10:$C$7501,"27") -> 0 | DO21: =COUNTIFS('DETAIL SALES'!$Q$10:$Q$7501,'FILL RATE MANDATORY STOCK'!BK21,'DETAIL SALES'!$AB$10:$AB$7501,"Full",'DETAIL SALES'!$C$10:$C$7501,"28") -> 0 | DP21: =COUNTIFS('DETAIL SALES'!$Q$10:$Q$7501,'FILL RATE MANDATORY STOCK'!BK21,'DETAIL SALES'!$AB$10:$AB$7501,"No",'DETAIL SALES'!$C$10:$C$7501,"28") -> 0 | DQ21: =COUNTIFS('DETAIL SALES'!$Q$10:$Q$7501,'FILL RATE MANDATORY STOCK'!BK21,'DETAIL SALES'!$AB$10:$AB$7501,"Full",'DETAIL SALES'!$C$10:$C$7501,"29") -> 0 | DR21: =COUNTIFS('DETAIL SALES'!$Q$10:$Q$7501,'FILL RATE MANDATORY STOCK'!BK21,'DETAIL SALES'!$AB$10:$AB$7501,"No",'DETAIL SALES'!$C$10:$C$7501,"29") -> 0 | DS21: =COUNTIFS('DETAIL SALES'!$Q$10:$Q$7501,'FILL RATE MANDATORY STOCK'!BK21,'DETAIL SALES'!$AB$10:$AB$7501,"Full",'DETAIL SALES'!$C$10:$C$7501,"30") -> 0 | DT21: =COUNTIFS('DETAIL SALES'!$Q$10:$Q$7501,'FILL RATE MANDATORY STOCK'!BK21,'DETAIL SALES'!$AB$10:$AB$7501,"No",'DETAIL SALES'!$C$10:$C$7501,"30") -> 0 | DU21: =COUNTIFS('DETAIL SALES'!$Q$10:$Q$7501,'FILL RATE MANDATORY STOCK'!\,'DETAIL SALES'!$AB$10:$AB$7501,"Full",'DETAIL SALES'!$C$10:$C$7501,"31") -> 0 | DV21: =COUNTIFS('DETAIL SALES'!$Q$10:$Q$7501,'FILL RATE MANDATORY STOCK'!BK21,'DETAIL SALES'!$AB$10:$AB$7501,"No",'DETAIL SALES'!$C$10:$C$7501,"31") -> 0 | DW21: =BM21+BO21+BQ21+BS21+BU21+BW21+BY21+CA21+CC21+CE21+CG21+CI21+CK21+CM21+CO21+CQ21+CS21+CU21+CW21+CY21+DA21+DC21+DE21+DG21+DI21+DK21+DM21+DO21+DQ21+DS21+DU21 -> 0 | DX21: =BN21+BP21+BR21+BT21+BV21+BX21+BZ21+CB21+CD21+CF21+CH21+CJ21+CL21+CN21+CP21+CR21+CT21+CV21+CX21+CZ21+DB21+DD21+DF21+DH21+DJ21+DL21+DN21+DP21+DR21+DT21+DV21 -> 0 | DY21: =DW21+DX21 -> 0 | DZ21: =DW21/DY21 -> #DIV/0!
A22: 13 | C22: =DAY(B22) -> 0 | D22: =MONTH(B22) -> 1 | E22: =YEAR(B22) -> 1900 | Y22: =X22*U22 -> 0 | Z22: =Y22*1.1 -> 0 | AB22: =IF(S22="","",IF(S22-U22=0,"Full","No")) | AC22: =IF(AND(S22>U22,V22=0),"Lost",IF(AND(S22>U22,V22<(S22-U22)),"Lost","")) | AD22: =IF(AND(S22>U22,V22=0),S22-U22,IF(AND(S22>U22,V22<(S22-U22)),S22-(U22+V22),"")) | AJ22: 11 | AK22: Oil & Gas | AL22: Pertamina | AN22: PT. CITRA ASRI BUANA | AQ22: Government | AW22: =AV22/$AV$40 -> #DIV/0! | AZ22: =AY22/(AX22+AY22) -> #DIV/0! | BE22: =MAX(BE19:BE21)+1 -> 11 | BF22: Oil Filter T/M | BG22: FM2P (363 MODEL) & 230 ALL MODEL | BH22: 32915LVA10 | BI22: =VLOOKUP(BH22,#REF!,8,FALSE) -> #REF! | BJ22: 20000 | BK22: 1 | BL22: 2.5 | BM22: =COUNTIFS('DETAIL SALES'!$Q$10:$Q$7501,'FILL RATE MANDATORY STOCK'!BK22,'DETAIL SALES'!$AB$10:$AB$7501,"Full",'DETAIL SALES'!$C$10:$C$7501,"1") -> 0 | BN22: =COUNTIFS('DETAIL SALES'!$Q$10:$Q$7501,'FILL RATE MANDATORY STOCK'!BK22,'DETAIL SALES'!$AB$10:$AB$7501,"No",'DETAIL SALES'!$C$10:$C$7501,"1") -> 0 | BO22: =COUNTIFS('DETAIL SALES'!$Q$10:$Q$7501,'FILL RATE MANDATORY STOCK'!BK22,'DETAIL SALES'!$AB$10:$AB$7501,"Full",'DETAIL SALES'!$C$10:$C$7501,"2") -> 0 | BP22: =COUNTIFS('DETAIL SALES'!$Q$10:$Q$7501,'FILL RATE MANDATORY STOCK'!BK22,'DETAIL SALES'!$AB$10:$AB$7501,"No",'DETAIL SALES'!$C$10:$C$7501,"2") -> 0 | BQ22: =COUNTIFS('DETAIL SALES'!$Q$10:$Q$7501,'FILL RATE MANDATORY STOCK'!BK22,'DETAIL SALES'!$AB$10:$AB$7501,"Full",'DETAIL SALES'!$C$10:$C$7501,"3") -> 0 | BR22: =COUNTIFS('DETAIL SALES'!$Q$10:$Q$7501,'FILL RATE MANDATORY STOCK'!BK22,'DETAIL SALES'!$AB$10:$AB$7501,"No",'DETAIL SALES'!$C$10:$C$7501,"3") -> 0 | BS22: =COUNTIFS('DETAIL SALES'!$Q$10:$Q$7501,'FILL RATE MANDATORY STOCK'!BK22,'DETAIL SALES'!$AB$10:$AB$7501,"Full",'DETAIL SALES'!$C$10:$C$7501,"4") -> 0 | BT22: =COUNTIFS('DETAIL SALES'!$Q$10:$Q$7501,'FILL RATE MANDATORY STOCK'!BK22,'DETAIL SALES'!$AB$10:$AB$7501,"No",'DETAIL SALES'!$C$10:$C$7501,"4") -> 0 | BU22: =COUNTIFS('DETAIL SALES'!$Q$10:$Q$7501,'FILL RATE MANDATORY STOCK'!BK22,'DETAIL SALES'!$AB$10:$AB$7501,"Full",'DETAIL SALES'!$C$10:$C$7501,"5") -> 0 | BV22: =COUNTIFS('DETAIL SALES'!$Q$10:$Q$7501,'FILL RATE MANDATORY STOCK'!BK22,'DETAIL SALES'!$AB$10:$AB$7501,"No",'DETAIL SALES'!$C$10:$C$7501,"5") -> 0 | BW22: =COUNTIFS('DETAIL SALES'!$Q$10:$Q$7501,'FILL RATE MANDATORY STOCK'!BK22,'DETAIL SALES'!$AB$10:$AB$7501,"Full",'DETAIL SALES'!$C$10:$C$7501,"6") -> 0 | BX22: =COUNTIFS('DETAIL SALES'!$Q$10:$Q$7501,'FILL RATE MANDATORY STOCK'!BK22,'DETAIL SALES'!$AB$10:$AB$7501,"No",'DETAIL SALES'!$C$10:$C$7501,"6") -> 0 | BY22: =COUNTIFS('DETAIL SALES'!$Q$10:$Q$7501,'FILL RATE MANDATORY STOCK'!BK22,'DETAIL SALES'!$AB$10:$AB$7501,"Full",'DETAIL SALES'!$C$10:$C$7501,"7") -> 0 | BZ22: =COUNTIFS('DETAIL SALES'!$Q$10:$Q$7501,'FILL RATE MANDATORY STOCK'!BK22,'DETAIL SALES'!$AB$10:$AB$7501,"No",'DETAIL SALES'!$C$10:$C$7501,"7") -> 0 | CA22: =COUNTIFS('DETAIL SALES'!$Q$10:$Q$7501,'FILL RATE MANDATORY STOCK'!BK22,'DETAIL SALES'!$AB$10:$AB$7501,"Full",'DETAIL SALES'!$C$10:$C$7501,"8") -> 0 | CB22: =COUNTIFS('DETAIL SALES'!$Q$10:$Q$7501,'FILL RATE MANDATORY STOCK'!BK22,'DETAIL SALES'!$AB$10:$AB$7501,"No",'DETAIL SALES'!$C$10:$C$7501,"8") -> 0 | CC22: =COUNTIFS('DETAIL SALES'!$Q$10:$Q$7501,'FILL RATE MANDATORY STOCK'!BK22,'DETAIL SALES'!$AB$10:$AB$7501,"Full",'DETAIL SALES'!$C$10:$C$7501,"9") -> 0 | CD22: =COUNTIFS('DETAIL SALES'!$Q$10:$Q$7501,'FILL RATE MANDATORY STOCK'!BK22,'DETAIL SALES'!$AB$10:$AB$7501,"No",'DETAIL SALES'!$C$10:$C$7501,"9") -> 0 | CE22: =COUNTIFS('DETAIL SALES'!$Q$10:$Q$7501,'FILL RATE MANDATORY STOCK'!BK22,'DETAIL SALES'!$AB$10:$AB$7501,"Full",'DETAIL SALES'!$C$10:$C$7501,"10") -> 0 | CF22: =COUNTIFS('DETAIL SALES'!$Q$10:$Q$7501,'FILL RATE MANDATORY STOCK'!BK22,'DETAIL SALES'!$AB$10:$AB$7501,"No",'DETAIL SALES'!$C$10:$C$7501,"10") -> 0 | CG22: =COUNTIFS('DETAIL SALES'!$Q$10:$Q$7501,'FILL RATE MANDATORY STOCK'!BK22,'DETAIL SALES'!$AB$10:$AB$7501,"Full",'DETAIL SALES'!$C$10:$C$7501,"11") -> 0 | CH22: =COUNTIFS('DETAIL SALES'!$Q$10:$Q$7501,'FILL RATE MANDATORY STOCK'!BK22,'DETAIL SALES'!$AB$10:$AB$7501,"No",'DETAIL SALES'!$C$10:$C$7501,"11") -> 0 | CI22: =COUNTIFS('DETAIL SALES'!$Q$10:$Q$7501,'FILL RATE MANDATORY STOCK'!BK22,'DETAIL SALES'!$AB$10:$AB$7501,"Full",'DETAIL SALES'!$C$10:$C$7501,"12") -> 0 | CJ22: =COUNTIFS('DETAIL SALES'!$Q$10:$Q$7501,'FILL RATE MANDATORY STOCK'!BK22,'DETAIL SALES'!$AB$10:$AB$7501,"No",'DETAIL SALES'!$C$10:$C$7501,"12") -> 0 | CK22: =COUNTIFS('DETAIL SALES'!$Q$10:$Q$7501,'FILL RATE MANDATORY STOCK'!BK22,'DETAIL SALES'!$AB$10:$AB$7501,"Full",'DETAIL SALES'!$C$10:$C$7501,"13") -> 0 | CL22: =COUNTIFS('DETAIL SALES'!$Q$10:$Q$7501,'FILL RATE MANDATORY STOCK'!BK22,'DETAIL SALES'!$AB$10:$AB$7501,"No",'DETAIL SALES'!$C$10:$C$7501,"13") -> 0 | CM22: =COUNTIFS('DETAIL SALES'!$Q$10:$Q$7501,'FILL RATE MANDATORY STOCK'!BK22,'DETAIL SALES'!$AB$10:$AB$7501,"Full",'DETAIL SALES'!$C$10:$C$7501,"14") -> 0 | CN22: =COUNTIFS('DETAIL SALES'!$Q$10:$Q$7501,'FILL RATE MANDATORY STOCK'!BK22,'DETAIL SALES'!$AB$10:$AB$7501,"No",'DETAIL SALES'!$C$10:$C$7501,"14") -> 0 | CO22: =COUNTIFS('DETAIL SALES'!$Q$10:$Q$7501,'FILL RATE MANDATORY STOCK'!BK22,'DETAIL SALES'!$AB$10:$AB$7501,"Full",'DETAIL SALES'!$C$10:$C$7501,"15") -> 0 | CP22: =COUNTIFS('DETAIL SALES'!$Q$10:$Q$7501,'FILL RATE MANDATORY STOCK'!BK22,'DETAIL SALES'!$AB$10:$AB$7501,"No",'DETAIL SALES'!$C$10:$C$7501,"15") -> 0 | CQ22: =COUNTIFS('DETAIL SALES'!$Q$10:$Q$7501,'FILL RATE MANDATORY STOCK'!BK22,'DETAIL SALES'!$AB$10:$AB$7501,"Full",'DETAIL SALES'!$C$10:$C$7501,"16") -> 0 | CR22: =COUNTIFS('DETAIL SALES'!$Q$10:$Q$7501,'FILL RATE MANDATORY STOCK'!BK22,'DETAIL SALES'!$AB$10:$AB$7501,"No",'DETAIL SALES'!$C$10:$C$7501,"16") -> 0 | CS22: =COUNTIFS('DETAIL SALES'!$Q$10:$Q$7501,'FILL RATE MANDATORY STOCK'!BK22,'DETAIL SALES'!$AB$10:$AB$7501,"Full",'DETAIL SALES'!$C$10:$C$7501,"17") -> 0 | CT22: =COUNTIFS('DETAIL SALES'!$Q$10:$Q$7501,'FILL RATE MANDATORY STOCK'!BK22,'DETAIL SALES'!$AB$10:$AB$7501,"No",'DETAIL SALES'!$C$10:$C$7501,"17") -> 0 | CU22: =COUNTIFS('DETAIL SALES'!$Q$10:$Q$7501,'FILL RATE MANDATORY STOCK'!BK22,'DETAIL SALES'!$AB$10:$AB$7501,"Full",'DETAIL SALES'!$C$10:$C$7501,"18") -> 0 | CV22: =COUNTIFS('DETAIL SALES'!$Q$10:$Q$7501,'FILL RATE MANDATORY STOCK'!BK22,'DETAIL SALES'!$AB$10:$AB$7501,"No",'DETAIL SALES'!$C$10:$C$7501,"18") -> 0 | CW22: =COUNTIFS('DETAIL SALES'!$Q$10:$Q$7501,'FILL RATE MANDATORY STOCK'!BK22,'DETAIL SALES'!$AB$10:$AB$7501,"Full",'DETAIL SALES'!$C$10:$C$7501,"19") -> 0 | CX22: =COUNTIFS('DETAIL SALES'!$Q$10:$Q$7501,'FILL RATE MANDATORY STOCK'!BK22,'DETAIL SALES'!$AB$10:$AB$7501,"No",'DETAIL SALES'!$C$10:$C$7501,"19") -> 0 | CY22: =COUNTIFS('DETAIL SALES'!$Q$10:$Q$7501,'FILL RATE MANDATORY STOCK'!BK22,'DETAIL SALES'!$AB$10:$AB$7501,"Full",'DETAIL SALES'!$C$10:$C$7501,"20") -> 0 | CZ22: =COUNTIFS('DETAIL SALES'!$Q$10:$Q$7501,'FILL RATE MANDATORY STOCK'!BK22,'DETAIL SALES'!$AB$10:$AB$7501,"No",'DETAIL SALES'!$C$10:$C$7501,"20") -> 0 | DA22: =COUNTIFS('DETAIL SALES'!$Q$10:$Q$7501,'FILL RATE MANDATORY STOCK'!BK22,'DETAIL SALES'!$AB$10:$AB$7501,"Full",'DETAIL SALES'!$C$10:$C$7501,"21") -> 0 | DB22: =COUNTIFS('DETAIL SALES'!$Q$10:$Q$7501,'FILL RATE MANDATORY STOCK'!BK22,'DETAIL SALES'!$AB$10:$AB$7501,"No",'DETAIL SALES'!$C$10:$C$7501,"21") -> 0 | DC22: =COUNTIFS('DETAIL SALES'!$Q$10:$Q$7501,'FILL RATE MANDATORY STOCK'!BK22,'DETAIL SALES'!$AB$10:$AB$7501,"Full",'DETAIL SALES'!$C$10:$C$7501,"22") -> 0 | DD22: =COUNTIFS('DETAIL SALES'!$Q$10:$Q$7501,'FILL RATE MANDATORY STOCK'!BK22,'DETAIL SALES'!$AB$10:$AB$7501,"No",'DETAIL SALES'!$C$10:$C$7501,"22") -> 0 | DE22: =COUNTIFS('DETAIL SALES'!$Q$10:$Q$7501,'FILL RATE MANDATORY STOCK'!BK22,'DETAIL SALES'!$AB$10:$AB$7501,"Full",'DETAIL SALES'!$C$10:$C$7501,"23") -> 0 | DF22: =COUNTIFS('DETAIL SALES'!$Q$10:$Q$7501,'FILL RATE MANDATORY STOCK'!BK22,'DETAIL SALES'!$AB$10:$AB$7501,"No",'DETAIL SALES'!$C$10:$C$7501,"23") -> 0 | DG22: =COUNTIFS('DETAIL SALES'!$Q$10:$Q$7501,'FILL RATE MANDATORY STOCK'!BK22,'DETAIL SALES'!$AB$10:$AB$7501,"Full",'DETAIL SALES'!$C$10:$C$7501,"24") -> 0 | DH22: =COUNTIFS('DETAIL SALES'!$Q$10:$Q$7501,'FILL RATE MANDATORY STOCK'!BK22,'DETAIL SALES'!$AB$10:$AB$7501,"No",'DETAIL SALES'!$C$10:$C$7501,"24") -> 0 | DI22: =COUNTIFS('DETAIL SALES'!$Q$10:$Q$7501,'FILL RATE MANDATORY STOCK'!BK22,'DETAIL SALES'!$AB$10:$AB$7501,"Full",'DETAIL SALES'!$C$10:$C$7501,"25") -> 0 | DJ22: =COUNTIFS('DETAIL SALES'!$Q$10:$Q$7501,'FILL RATE MANDATORY STOCK'!BK22,'DETAIL SALES'!$AB$10:$AB$7501,"No",'DETAIL SALES'!$C$10:$C$7501,"25") -> 0 | DK22: =COUNTIFS('DETAIL SALES'!$Q$10:$Q$7501,'FILL RATE MANDATORY STOCK'!BK22,'DETAIL SALES'!$AB$10:$AB$7501,"Full",'DETAIL SALES'!$C$10:$C$7501,"26") -> 0 | DL22: =COUNTIFS('DETAIL SALES'!$Q$10:$Q$7501,'FILL RATE MANDATORY STOCK'!BK22,'DETAIL SALES'!$AB$10:$AB$7501,"No",'DETAIL SALES'!$C$10:$C$7501,"26") -> 0 | DM22: =COUNTIFS('DETAIL SALES'!$Q$10:$Q$7501,'FILL RATE MANDATORY STOCK'!BK22,'DETAIL SALES'!$AB$10:$AB$7501,"Full",'DETAIL SALES'!$C$10:$C$7501,"27") -> 0 | DN22: =COUNTIFS('DETAIL SALES'!$Q$10:$Q$7501,'FILL RATE MANDATORY STOCK'!BK22,'DETAIL SALES'!$AB$10:$AB$7501,"No",'DETAIL SALES'!$C$10:$C$7501,"27") -> 0 | DO22: =COUNTIFS('DETAIL SALES'!$Q$10:$Q$7501,'FILL RATE MANDATORY STOCK'!BK22,'DETAIL SALES'!$AB$10:$AB$7501,"Full",'DETAIL SALES'!$C$10:$C$7501,"28") -> 0 | DP22: =COUNTIFS('DETAIL SALES'!$Q$10:$Q$7501,'FILL RATE MANDATORY STOCK'!BK22,'DETAIL SALES'!$AB$10:$AB$7501,"No",'DETAIL SALES'!$C$10:$C$7501,"28") -> 0 | DQ22: =COUNTIFS('DETAIL SALES'!$Q$10:$Q$7501,'FILL RATE MANDATORY STOCK'!BK22,'DETAIL SALES'!$AB$10:$AB$7501,"Full",'DETAIL SALES'!$C$10:$C$7501,"29") -> 0 | DR22: =COUNTIFS('DETAIL SALES'!$Q$10:$Q$7501,'FILL RATE MANDATORY STOCK'!BK22,'DETAIL SALES'!$AB$10:$AB$7501,"No",'DETAIL SALES'!$C$10:$C$7501,"29") -> 0 | DS22: =COUNTIFS('DETAIL SALES'!$Q$10:$Q$7501,'FILL RATE MANDATORY STOCK'!BK22,'DETAIL SALES'!$AB$10:$AB$7501,"Full",'DETAIL SALES'!$C$10:$C$7501,"30") -> 0 | DT22: =COUNTIFS('DETAIL SALES'!$Q$10:$Q$7501,'FILL RATE MANDATORY STOCK'!BK22,'DETAIL SALES'!$AB$10:$AB$7501,"No",'DETAIL SALES'!$C$10:$C$7501,"30") -> 0 | DU22: =COUNTIFS('DETAIL SALES'!$Q$10:$Q$7501,'FILL RATE MANDATORY STOCK'!\,'DETAIL SALES'!$AB$10:$AB$7501,"Full",'DETAIL SALES'!$C$10:$C$7501,"31") -> 0 | DV22: =COUNTIFS('DETAIL SALES'!$Q$10:$Q$7501,'FILL RATE MANDATORY STOCK'!BK22,'DETAIL SALES'!$AB$10:$AB$7501,"No",'DETAIL SALES'!$C$10:$C$7501,"31") -> 0 | DW22: =BM22+BO22+BQ22+BS22+BU22+BW22+BY22+CA22+CC22+CE22+CG22+CI22+CK22+CM22+CO22+CQ22+CS22+CU22+CW22+CY22+DA22+DC22+DE22+DG22+DI22+DK22+DM22+DO22+DQ22+DS22+DU22 -> 0 | DX22: =BN22+BP22+BR22+BT22+BV22+BX22+BZ22+CB22+CD22+CF22+CH22+CJ22+CL22+CN22+CP22+CR22+CT22+CV22+CX22+CZ22+DB22+DD22+DF22+DH22+DJ22+DL22+DN22+DP22+DR22+DT22+DV22 -> 0 | DY22: =DW22+DX22 -> 0 | DZ22: =DW22/DY22 -> #DIV/0!
A23: 14 | C23: =DAY(B23) -> 0 | D23: =MONTH(B23) -> 1 | E23: =YEAR(B23) -> 1900 | Y23: =X23*U23 -> 0 | Z23: =Y23*1.1 -> 0 | AB23: =IF(S23="","",IF(S23-U23=0,"Full","No")) | AC23: =IF(AND(S23>U23,V23=0),"Lost",IF(AND(S23>U23,V23<(S23-U23)),"Lost","")) | AD23: =IF(AND(S23>U23,V23=0),S23-U23,IF(AND(S23>U23,V23<(S23-U23)),S23-(U23+V23),"")) | AJ23: 12 | AK23: Chemical | AL23: Petrochem | AN23: PT. CITRA LESTARI MOBILINDO | AQ23: General Cargo | AW23: =AV23/$AV$40 -> #DIV/0! | AZ23: =AY23/(AX23+AY23) -> #DIV/0! | BE23: =MAX(BE20:BE22)+1 -> 12 | BF23: Oil Filter | BG23: RK8J / FC9J | BH23: 156071731L | BI23: =VLOOKUP(BH23,#REF!,8,FALSE) -> #REF! | BJ23: 20000 | BK23: 1 | BL23: 407.5 | BM23: =COUNTIFS('DETAIL SALES'!$Q$10:$Q$7501,'FILL RATE MANDATORY STOCK'!BK23,'DETAIL SALES'!$AB$10:$AB$7501,"Full",'DETAIL SALES'!$C$10:$C$7501,"1") -> 0 | BN23: =COUNTIFS('DETAIL SALES'!$Q$10:$Q$7501,'FILL RATE MANDATORY STOCK'!BK23,'DETAIL SALES'!$AB$10:$AB$7501,"No",'DETAIL SALES'!$C$10:$C$7501,"1") -> 0 | BO23: =COUNTIFS('DETAIL SALES'!$Q$10:$Q$7501,'FILL RATE MANDATORY STOCK'!BK23,'DETAIL SALES'!$AB$10:$AB$7501,"Full",'DETAIL SALES'!$C$10:$C$7501,"2") -> 0 | BP23: =COUNTIFS('DETAIL SALES'!$Q$10:$Q$7501,'FILL RATE MANDATORY STOCK'!BK23,'DETAIL SALES'!$AB$10:$AB$7501,"No",'DETAIL SALES'!$C$10:$C$7501,"2") -> 0 | BQ23: =COUNTIFS('DETAIL SALES'!$Q$10:$Q$7501,'FILL RATE MANDATORY STOCK'!BK23,'DETAIL SALES'!$AB$10:$AB$7501,"Full",'DETAIL SALES'!$C$10:$C$7501,"3") -> 0 | BR23: =COUNTIFS('DETAIL SALES'!$Q$10:$Q$7501,'FILL RATE MANDATORY STOCK'!BK23,'DETAIL SALES'!$AB$10:$AB$7501,"No",'DETAIL SALES'!$C$10:$C$7501,"3") -> 0 | BS23: =COUNTIFS('DETAIL SALES'!$Q$10:$Q$7501,'FILL RATE MANDATORY STOCK'!BK23,'DETAIL SALES'!$AB$10:$AB$7501,"Full",'DETAIL SALES'!$C$10:$C$7501,"4") -> 0 | BT23: =COUNTIFS('DETAIL SALES'!$Q$10:$Q$7501,'FILL RATE MANDATORY STOCK'!BK23,'DETAIL SALES'!$AB$10:$AB$7501,"No",'DETAIL SALES'!$C$10:$C$7501,"4") -> 0 | BU23: =COUNTIFS('DETAIL SALES'!$Q$10:$Q$7501,'FILL RATE MANDATORY STOCK'!BK23,'DETAIL SALES'!$AB$10:$AB$7501,"Full",'DETAIL SALES'!$C$10:$C$7501,"5") -> 0 | BV23: =COUNTIFS('DETAIL SALES'!$Q$10:$Q$7501,'FILL RATE MANDATORY STOCK'!BK23,'DETAIL SALES'!$AB$10:$AB$7501,"No",'DETAIL SALES'!$C$10:$C$7501,"5") -> 0 | BW23: =COUNTIFS('DETAIL SALES'!$Q$10:$Q$7501,'FILL RATE MANDATORY STOCK'!BK23,'DETAIL SALES'!$AB$10:$AB$7501,"Full",'DETAIL SALES'!$C$10:$C$7501,"6") -> 0 | BX23: =COUNTIFS('DETAIL SALES'!$Q$10:$Q$7501,'FILL RATE MANDATORY STOCK'!BK23,'DETAIL SALES'!$AB$10:$AB$7501,"No",'DETAIL SALES'!$C$10:$C$7501,"6") -> 0 | BY23: =COUNTIFS('DETAIL SALES'!$Q$10:$Q$7501,'FILL RATE MANDATORY STOCK'!BK23,'DETAIL SALES'!$AB$10:$AB$7501,"Full",'DETAIL SALES'!$C$10:$C$7501,"7") -> 0 | BZ23: =COUNTIFS('DETAIL SALES'!$Q$10:$Q$7501,'FILL RATE MANDATORY STOCK'!BK23,'DETAIL SALES'!$AB$10:$AB$7501,"No",'DETAIL SALES'!$C$10:$C$7501,"7") -> 0 | CA23: =COUNTIFS('DETAIL SALES'!$Q$10:$Q$7501,'FILL RATE MANDATORY STOCK'!BK23,'DETAIL SALES'!$AB$10:$AB$7501,"Full",'DETAIL SALES'!$C$10:$C$7501,"8") -> 0 | CB23: =COUNTIFS('DETAIL SALES'!$Q$10:$Q$7501,'FILL RATE MANDATORY STOCK'!BK23,'DETAIL SALES'!$AB$10:$AB$7501,"No",'DETAIL SALES'!$C$10:$C$7501,"8") -> 0 | CC23: =COUNTIFS('DETAIL SALES'!$Q$10:$Q$7501,'FILL RATE MANDATORY STOCK'!BK23,'DETAIL SALES'!$AB$10:$AB$7501,"Full",'DETAIL SALES'!$C$10:$C$7501,"9") -> 0 | CD23: =COUNTIFS('DETAIL SALES'!$Q$10:$Q$7501,'FILL RATE MANDATORY STOCK'!BK23,'DETAIL SALES'!$AB$10:$AB$7501,"No",'DETAIL SALES'!$C$10:$C$7501,"9") -> 0 | CE23: =COUNTIFS('DETAIL SALES'!$Q$10:$Q$7501,'FILL RATE MANDATORY STOCK'!BK23,'DETAIL SALES'!$AB$10:$AB$7501,"Full",'DETAIL SALES'!$C$10:$C$7501,"10") -> 0 | CF23: =COUNTIFS('DETAIL SALES'!$Q$10:$Q$7501,'FILL RATE MANDATORY STOCK'!BK23,'DETAIL SALES'!$AB$10:$AB$7501,"No",'DETAIL SALES'!$C$10:$C$7501,"10") -> 0 | CG23: =COUNTIFS('DETAIL SALES'!$Q$10:$Q$7501,'FILL RATE MANDATORY STOCK'!BK23,'DETAIL SALES'!$AB$10:$AB$7501,"Full",'DETAIL SALES'!$C$10:$C$7501,"11") -> 0 | CH23: =COUNTIFS('DETAIL SALES'!$Q$10:$Q$7501,'FILL RATE MANDATORY STOCK'!BK23,'DETAIL SALES'!$AB$10:$AB$7501,"No",'DETAIL SALES'!$C$10:$C$7501,"11") -> 0 | CI23: =COUNTIFS('DETAIL SALES'!$Q$10:$Q$7501,'FILL RATE MANDATORY STOCK'!BK23,'DETAIL SALES'!$AB$10:$AB$7501,"Full",'DETAIL SALES'!$C$10:$C$7501,"12") -> 0 | CJ23: =COUNTIFS('DETAIL SALES'!$Q$10:$Q$7501,'FILL RATE MANDATORY STOCK'!BK23,'DETAIL SALES'!$AB$10:$AB$7501,"No",'DETAIL SALES'!$C$10:$C$7501,"12") -> 0 | CK23: =COUNTIFS('DETAIL SALES'!$Q$10:$Q$7501,'FILL RATE MANDATORY STOCK'!BK23,'DETAIL SALES'!$AB$10:$AB$7501,"Full",'DETAIL SALES'!$C$10:$C$7501,"13") -> 0 | CL23: =COUNTIFS('DETAIL SALES'!$Q$10:$Q$7501,'FILL RATE MANDATORY STOCK'!BK23,'DETAIL SALES'!$AB$10:$AB$7501,"No",'DETAIL SALES'!$C$10:$C$7501,"13") -> 0 | CM23: =COUNTIFS('DETAIL SALES'!$Q$10:$Q$7501,'FILL RATE MANDATORY STOCK'!BK23,'DETAIL SALES'!$AB$10:$AB$7501,"Full",'DETAIL SALES'!$C$10:$C$7501,"14") -> 0 | CN23: =COUNTIFS('DETAIL SALES'!$Q$10:$Q$7501,'FILL RATE MANDATORY STOCK'!BK23,'DETAIL SALES'!$AB$10:$AB$7501,"No",'DETAIL SALES'!$C$10:$C$7501,"14") -> 0 | CO23: =COUNTIFS('DETAIL SALES'!$Q$10:$Q$7501,'FILL RATE MANDATORY STOCK'!BK23,'DETAIL SALES'!$AB$10:$AB$7501,"Full",'DETAIL SALES'!$C$10:$C$7501,"15") -> 0 | CP23: =COUNTIFS('DETAIL SALES'!$Q$10:$Q$7501,'FILL RATE MANDATORY STOCK'!BK23,'DETAIL SALES'!$AB$10:$AB$7501,"No",'DETAIL SALES'!$C$10:$C$7501,"15") -> 0 | CQ23: =COUNTIFS('DETAIL SALES'!$Q$10:$Q$7501,'FILL RATE MANDATORY STOCK'!BK23,'DETAIL SALES'!$AB$10:$AB$7501,"Full",'DETAIL SALES'!$C$10:$C$7501,"16") -> 0 | CR23: =COUNTIFS('DETAIL SALES'!$Q$10:$Q$7501,'FILL RATE MANDATORY STOCK'!BK23,'DETAIL SALES'!$AB$10:$AB$7501,"No",'DETAIL SALES'!$C$10:$C$7501,"16") -> 0 | CS23: =COUNTIFS('DETAIL SALES'!$Q$10:$Q$7501,'FILL RATE MANDATORY STOCK'!BK23,'DETAIL SALES'!$AB$10:$AB$7501,"Full",'DETAIL SALES'!$C$10:$C$7501,"17") -> 0 | CT23: =COUNTIFS('DETAIL SALES'!$Q$10:$Q$7501,'FILL RATE MANDATORY STOCK'!BK23,'DETAIL SALES'!$AB$10:$AB$7501,"No",'DETAIL SALES'!$C$10:$C$7501,"17") -> 0 | CU23: =COUNTIFS('DETAIL SALES'!$Q$10:$Q$7501,'FILL RATE MANDATORY STOCK'!BK23,'DETAIL SALES'!$AB$10:$AB$7501,"Full",'DETAIL SALES'!$C$10:$C$7501,"18") -> 0 | CV23: =COUNTIFS('DETAIL SALES'!$Q$10:$Q$7501,'FILL RATE MANDATORY STOCK'!BK23,'DETAIL SALES'!$AB$10:$AB$7501,"No",'DETAIL SALES'!$C$10:$C$7501,"18") -> 0 | CW23: =COUNTIFS('DETAIL SALES'!$Q$10:$Q$7501,'FILL RATE MANDATORY STOCK'!BK23,'DETAIL SALES'!$AB$10:$AB$7501,"Full",'DETAIL SALES'!$C$10:$C$7501,"19") -> 0 | CX23: =COUNTIFS('DETAIL SALES'!$Q$10:$Q$7501,'FILL RATE MANDATORY STOCK'!BK23,'DETAIL SALES'!$AB$10:$AB$7501,"No",'DETAIL SALES'!$C$10:$C$7501,"19") -> 0 | CY23: =COUNTIFS('DETAIL SALES'!$Q$10:$Q$7501,'FILL RATE MANDATORY STOCK'!BK23,'DETAIL SALES'!$AB$10:$AB$7501,"Full",'DETAIL SALES'!$C$10:$C$7501,"20") -> 0 | CZ23: =COUNTIFS('DETAIL SALES'!$Q$10:$Q$7501,'FILL RATE MANDATORY STOCK'!BK23,'DETAIL SALES'!$AB$10:$AB$7501,"No",'DETAIL SALES'!$C$10:$C$7501,"20") -> 0 | DA23: =COUNTIFS('DETAIL SALES'!$Q$10:$Q$7501,'FILL RATE MANDATORY STOCK'!BK23,'DETAIL SALES'!$AB$10:$AB$7501,"Full",'DETAIL SALES'!$C$10:$C$7501,"21") -> 0 | DB23: =COUNTIFS('DETAIL SALES'!$Q$10:$Q$7501,'FILL RATE MANDATORY STOCK'!BK23,'DETAIL SALES'!$AB$10:$AB$7501,"No",'DETAIL SALES'!$C$10:$C$7501,"21") -> 0 | DC23: =COUNTIFS('DETAIL SALES'!$Q$10:$Q$7501,'FILL RATE MANDATORY STOCK'!BK23,'DETAIL SALES'!$AB$10:$AB$7501,"Full",'DETAIL SALES'!$C$10:$C$7501,"22") -> 0 | DD23: =COUNTIFS('DETAIL SALES'!$Q$10:$Q$7501,'FILL RATE MANDATORY STOCK'!BK23,'DETAIL SALES'!$AB$10:$AB$7501,"No",'DETAIL SALES'!$C$10:$C$7501,"22") -> 0 | DE23: =COUNTIFS('DETAIL SALES'!$Q$10:$Q$7501,'FILL RATE MANDATORY STOCK'!BK23,'DETAIL SALES'!$AB$10:$AB$7501,"Full",'DETAIL SALES'!$C$10:$C$7501,"23") -> 0 | DF23: =COUNTIFS('DETAIL SALES'!$Q$10:$Q$7501,'FILL RATE MANDATORY STOCK'!BK23,'DETAIL SALES'!$AB$10:$AB$7501,"No",'DETAIL SALES'!$C$10:$C$7501,"23") -> 0 | DG23: =COUNTIFS('DETAIL SALES'!$Q$10:$Q$7501,'FILL RATE MANDATORY STOCK'!BK23,'DETAIL SALES'!$AB$10:$AB$7501,"Full",'DETAIL SALES'!$C$10:$C$7501,"24") -> 0 | DH23: =COUNTIFS('DETAIL SALES'!$Q$10:$Q$7501,'FILL RATE MANDATORY STOCK'!BK23,'DETAIL SALES'!$AB$10:$AB$7501,"No",'DETAIL SALES'!$C$10:$C$7501,"24") -> 0 | DI23: =COUNTIFS('DETAIL SALES'!$Q$10:$Q$7501,'FILL RATE MANDATORY STOCK'!BK23,'DETAIL SALES'!$AB$10:$AB$7501,"Full",'DETAIL SALES'!$C$10:$C$7501,"25") -> 0 | DJ23: =COUNTIFS('DETAIL SALES'!$Q$10:$Q$7501,'FILL RATE MANDATORY STOCK'!BK23,'DETAIL SALES'!$AB$10:$AB$7501,"No",'DETAIL SALES'!$C$10:$C$7501,"25") -> 0 | DK23: =COUNTIFS('DETAIL SALES'!$Q$10:$Q$7501,'FILL RATE MANDATORY STOCK'!BK23,'DETAIL SALES'!$AB$10:$AB$7501,"Full",'DETAIL SALES'!$C$10:$C$7501,"26") -> 0 | DL23: =COUNTIFS('DETAIL SALES'!$Q$10:$Q$7501,'FILL RATE MANDATORY STOCK'!BK23,'DETAIL SALES'!$AB$10:$AB$7501,"No",'DETAIL SALES'!$C$10:$C$7501,"26") -> 0 | DM23: =COUNTIFS('DETAIL SALES'!$Q$10:$Q$7501,'FILL RATE MANDATORY STOCK'!BK23,'DETAIL SALES'!$AB$10:$AB$7501,"Full",'DETAIL SALES'!$C$10:$C$7501,"27") -> 0 | DN23: =COUNTIFS('DETAIL SALES'!$Q$10:$Q$7501,'FILL RATE MANDATORY STOCK'!BK23,'DETAIL SALES'!$AB$10:$AB$7501,"No",'DETAIL SALES'!$C$10:$C$7501,"27") -> 0 | DO23: =COUNTIFS('DETAIL SALES'!$Q$10:$Q$7501,'FILL RATE MANDATORY STOCK'!BK23,'DETAIL SALES'!$AB$10:$AB$7501,"Full",'DETAIL SALES'!$C$10:$C$7501,"28") -> 0 | DP23: =COUNTIFS('DETAIL SALES'!$Q$10:$Q$7501,'FILL RATE MANDATORY STOCK'!BK23,'DETAIL SALES'!$AB$10:$AB$7501,"No",'DETAIL SALES'!$C$10:$C$7501,"28") -> 0 | DQ23: =COUNTIFS('DETAIL SALES'!$Q$10:$Q$7501,'FILL RATE MANDATORY STOCK'!BK23,'DETAIL SALES'!$AB$10:$AB$7501,"Full",'DETAIL SALES'!$C$10:$C$7501,"29") -> 0 | DR23: =COUNTIFS('DETAIL SALES'!$Q$10:$Q$7501,'FILL RATE MANDATORY STOCK'!BK23,'DETAIL SALES'!$AB$10:$AB$7501,"No",'DETAIL SALES'!$C$10:$C$7501,"29") -> 0 | DS23: =COUNTIFS('DETAIL SALES'!$Q$10:$Q$7501,'FILL RATE MANDATORY STOCK'!BK23,'DETAIL SALES'!$AB$10:$AB$7501,"Full",'DETAIL SALES'!$C$10:$C$7501,"30") -> 0 | DT23: =COUNTIFS('DETAIL SALES'!$Q$10:$Q$7501,'FILL RATE MANDATORY STOCK'!BK23,'DETAIL SALES'!$AB$10:$AB$7501,"No",'DETAIL SALES'!$C$10:$C$7501,"30") -> 0 | DU23: =COUNTIFS('DETAIL SALES'!$Q$10:$Q$7501,'FILL RATE MANDATORY STOCK'!\,'DETAIL SALES'!$AB$10:$AB$7501,"Full",'DETAIL SALES'!$C$10:$C$7501,"31") -> 0 | DV23: =COUNTIFS('DETAIL SALES'!$Q$10:$Q$7501,'FILL RATE MANDATORY STOCK'!BK23,'DETAIL SALES'!$AB$10:$AB$7501,"No",'DETAIL SALES'!$C$10:$C$7501,"31") -> 0 | DW23: =BM23+BO23+BQ23+BS23+BU23+BW23+BY23+CA23+CC23+CE23+CG23+CI23+CK23+CM23+CO23+CQ23+CS23+CU23+CW23+CY23+DA23+DC23+DE23+DG23+DI23+DK23+DM23+DO23+DQ23+DS23+DU23 -> 0 | DX23: =BN23+BP23+BR23+BT23+BV23+BX23+BZ23+CB23+CD23+CF23+CH23+CJ23+CL23+CN23+CP23+CR23+CT23+CV23+CX23+CZ23+DB23+DD23+DF23+DH23+DJ23+DL23+DN23+DP23+DR23+DT23+DV23 -> 0 | DY23: =DW23+DX23 -> 0 | DZ23: =DW23/DY23 -> #DIV/0!
A24: 15 | C24: =DAY(B24) -> 0 | D24: =MONTH(B24) -> 1 | E24: =YEAR(B24) -> 1900 | Y24: =X24*U24 -> 0 | Z24: =Y24*1.1 -> 0 | AB24: =IF(S24="","",IF(S24-U24=0,"Full","No")) | AC24: =IF(AND(S24>U24,V24=0),"Lost",IF(AND(S24>U24,V24<(S24-U24)),"Lost","")) | AD24: =IF(AND(S24>U24,V24=0),S24-U24,IF(AND(S24>U24,V24<(S24-U24)),S24-(U24+V24),"")) | AJ24: 13 | AK24: Mineral water | AL24: Aqua | AN24: PT. DAYAGUNA MOTOR INDONESIA | AQ24: Cement | AW24: =AV24/$AV$40 -> #DIV/0! | AZ24: =AY24/(AX24+AY24) -> #DIV/0! | BE24: =MAX(BE21:BE23)+1 -> 13 | BF24: Oil filter Differential | BG24: FM ALL MODEL | BH24: 156072060L | BI24: =VLOOKUP(BH24,#REF!,8,FALSE) -> #REF! | BJ24: 60000 | BK24: 1 | BL24: 3.5 | BM24: =COUNTIFS('DETAIL SALES'!$Q$10:$Q$7501,'FILL RATE MANDATORY STOCK'!BK24,'DETAIL SALES'!$AB$10:$AB$7501,"Full",'DETAIL SALES'!$C$10:$C$7501,"1") -> 0 | BN24: =COUNTIFS('DETAIL SALES'!$Q$10:$Q$7501,'FILL RATE MANDATORY STOCK'!BK24,'DETAIL SALES'!$AB$10:$AB$7501,"No",'DETAIL SALES'!$C$10:$C$7501,"1") -> 0 | BO24: =COUNTIFS('DETAIL SALES'!$Q$10:$Q$7501,'FILL RATE MANDATORY STOCK'!BK24,'DETAIL SALES'!$AB$10:$AB$7501,"Full",'DETAIL SALES'!$C$10:$C$7501,"2") -> 0 | BP24: =COUNTIFS('DETAIL SALES'!$Q$10:$Q$7501,'FILL RATE MANDATORY STOCK'!BK24,'DETAIL SALES'!$AB$10:$AB$7501,"No",'DETAIL SALES'!$C$10:$C$7501,"2") -> 0 | BQ24: =COUNTIFS('DETAIL SALES'!$Q$10:$Q$7501,'FILL RATE MANDATORY STOCK'!BK24,'DETAIL SALES'!$AB$10:$AB$7501,"Full",'DETAIL SALES'!$C$10:$C$7501,"3") -> 0 | BR24: =COUNTIFS('DETAIL SALES'!$Q$10:$Q$7501,'FILL RATE MANDATORY STOCK'!BK24,'DETAIL SALES'!$AB$10:$AB$7501,"No",'DETAIL SALES'!$C$10:$C$7501,"3") -> 0 | BS24: =COUNTIFS('DETAIL SALES'!$Q$10:$Q$7501,'FILL RATE MANDATORY STOCK'!BK24,'DETAIL SALES'!$AB$10:$AB$7501,"Full",'DETAIL SALES'!$C$10:$C$7501,"4") -> 0 | BT24: =COUNTIFS('DETAIL SALES'!$Q$10:$Q$7501,'FILL RATE MANDATORY STOCK'!BK24,'DETAIL SALES'!$AB$10:$AB$7501,"No",'DETAIL SALES'!$C$10:$C$7501,"4") -> 0 | BU24: =COUNTIFS('DETAIL SALES'!$Q$10:$Q$7501,'FILL RATE MANDATORY STOCK'!BK24,'DETAIL SALES'!$AB$10:$AB$7501,"Full",'DETAIL SALES'!$C$10:$C$7501,"5") -> 0 | BV24: =COUNTIFS('DETAIL SALES'!$Q$10:$Q$7501,'FILL RATE MANDATORY STOCK'!BK24,'DETAIL SALES'!$AB$10:$AB$7501,"No",'DETAIL SALES'!$C$10:$C$7501,"5") -> 0 | BW24: =COUNTIFS('DETAIL SALES'!$Q$10:$Q$7501,'FILL RATE MANDATORY STOCK'!BK24,'DETAIL SALES'!$AB$10:$AB$7501,"Full",'DETAIL SALES'!$C$10:$C$7501,"6") -> 0 | BX24: =COUNTIFS('DETAIL SALES'!$Q$10:$Q$7501,'FILL RATE MANDATORY STOCK'!BK24,'DETAIL SALES'!$AB$10:$AB$7501,"No",'DETAIL SALES'!$C$10:$C$7501,"6") -> 0 | BY24: =COUNTIFS('DETAIL SALES'!$Q$10:$Q$7501,'FILL RATE MANDATORY STOCK'!BK24,'DETAIL SALES'!$AB$10:$AB$7501,"Full",'DETAIL SALES'!$C$10:$C$7501,"7") -> 0 | BZ24: =COUNTIFS('DETAIL SALES'!$Q$10:$Q$7501,'FILL RATE MANDATORY STOCK'!BK24,'DETAIL SALES'!$AB$10:$AB$7501,"No",'DETAIL SALES'!$C$10:$C$7501,"7") -> 0 | CA24: =COUNTIFS('DETAIL SALES'!$Q$10:$Q$7501,'FILL RATE MANDATORY STOCK'!BK24,'DETAIL SALES'!$AB$10:$AB$7501,"Full",'DETAIL SALES'!$C$10:$C$7501,"8") -> 0 | CB24: =COUNTIFS('DETAIL SALES'!$Q$10:$Q$7501,'FILL RATE MANDATORY STOCK'!BK24,'DETAIL SALES'!$AB$10:$AB$7501,"No",'DETAIL SALES'!$C$10:$C$7501,"8") -> 0 | CC24: =COUNTIFS('DETAIL SALES'!$Q$10:$Q$7501,'FILL RATE MANDATORY STOCK'!BK24,'DETAIL SALES'!$AB$10:$AB$7501,"Full",'DETAIL SALES'!$C$10:$C$7501,"9") -> 0 | CD24: =COUNTIFS('DETAIL SALES'!$Q$10:$Q$7501,'FILL RATE MANDATORY STOCK'!BK24,'DETAIL SALES'!$AB$10:$AB$7501,"No",'DETAIL SALES'!$C$10:$C$7501,"9") -> 0 | CE24: =COUNTIFS('DETAIL SALES'!$Q$10:$Q$7501,'FILL RATE MANDATORY STOCK'!BK24,'DETAIL SALES'!$AB$10:$AB$7501,"Full",'DETAIL SALES'!$C$10:$C$7501,"10") -> 0 | CF24: =COUNTIFS('DETAIL SALES'!$Q$10:$Q$7501,'FILL RATE MANDATORY STOCK'!BK24,'DETAIL SALES'!$AB$10:$AB$7501,"No",'DETAIL SALES'!$C$10:$C$7501,"10") -> 0 | CG24: =COUNTIFS('DETAIL SALES'!$Q$10:$Q$7501,'FILL RATE MANDATORY STOCK'!BK24,'DETAIL SALES'!$AB$10:$AB$7501,"Full",'DETAIL SALES'!$C$10:$C$7501,"11") -> 0 | CH24: =COUNTIFS('DETAIL SALES'!$Q$10:$Q$7501,'FILL RATE MANDATORY STOCK'!BK24,'DETAIL SALES'!$AB$10:$AB$7501,"No",'DETAIL SALES'!$C$10:$C$7501,"11") -> 0 | CI24: =COUNTIFS('DETAIL SALES'!$Q$10:$Q$7501,'FILL RATE MANDATORY STOCK'!BK24,'DETAIL SALES'!$AB$10:$AB$7501,"Full",'DETAIL SALES'!$C$10:$C$7501,"12") -> 0 | CJ24: =COUNTIFS('DETAIL SALES'!$Q$10:$Q$7501,'FILL RATE MANDATORY STOCK'!BK24,'DETAIL SALES'!$AB$10:$AB$7501,"No",'DETAIL SALES'!$C$10:$C$7501,"12") -> 0 | CK24: =COUNTIFS('DETAIL SALES'!$Q$10:$Q$7501,'FILL RATE MANDATORY STOCK'!BK24,'DETAIL SALES'!$AB$10:$AB$7501,"Full",'DETAIL SALES'!$C$10:$C$7501,"13") -> 0 | CL24: =COUNTIFS('DETAIL SALES'!$Q$10:$Q$7501,'FILL RATE MANDATORY STOCK'!BK24,'DETAIL SALES'!$AB$10:$AB$7501,"No",'DETAIL SALES'!$C$10:$C$7501,"13") -> 0 | CM24: =COUNTIFS('DETAIL SALES'!$Q$10:$Q$7501,'FILL RATE MANDATORY STOCK'!BK24,'DETAIL SALES'!$AB$10:$AB$7501,"Full",'DETAIL SALES'!$C$10:$C$7501,"14") -> 0 | CN24: =COUNTIFS('DETAIL SALES'!$Q$10:$Q$7501,'FILL RATE MANDATORY STOCK'!BK24,'DETAIL SALES'!$AB$10:$AB$7501,"No",'DETAIL SALES'!$C$10:$C$7501,"14") -> 0 | CO24: =COUNTIFS('DETAIL SALES'!$Q$10:$Q$7501,'FILL RATE MANDATORY STOCK'!BK24,'DETAIL SALES'!$AB$10:$AB$7501,"Full",'DETAIL SALES'!$C$10:$C$7501,"15") -> 0 | CP24: =COUNTIFS('DETAIL SALES'!$Q$10:$Q$7501,'FILL RATE MANDATORY STOCK'!BK24,'DETAIL SALES'!$AB$10:$AB$7501,"No",'DETAIL SALES'!$C$10:$C$7501,"15") -> 0 | CQ24: =COUNTIFS('DETAIL SALES'!$Q$10:$Q$7501,'FILL RATE MANDATORY STOCK'!BK24,'DETAIL SALES'!$AB$10:$AB$7501,"Full",'DETAIL SALES'!$C$10:$C$7501,"16") -> 0 | CR24: =COUNTIFS('DETAIL SALES'!$Q$10:$Q$7501,'FILL RATE MANDATORY STOCK'!BK24,'DETAIL SALES'!$AB$10:$AB$7501,"No",'DETAIL SALES'!$C$10:$C$7501,"16") -> 0 | CS24: =COUNTIFS('DETAIL SALES'!$Q$10:$Q$7501,'FILL RATE MANDATORY STOCK'!BK24,'DETAIL SALES'!$AB$10:$AB$7501,"Full",'DETAIL SALES'!$C$10:$C$7501,"17") -> 0 | CT24: =COUNTIFS('DETAIL SALES'!$Q$10:$Q$7501,'FILL RATE MANDATORY STOCK'!BK24,'DETAIL SALES'!$AB$10:$AB$7501,"No",'DETAIL SALES'!$C$10:$C$7501,"17") -> 0 | CU24: =COUNTIFS('DETAIL SALES'!$Q$10:$Q$7501,'FILL RATE MANDATORY STOCK'!BK24,'DETAIL SALES'!$AB$10:$AB$7501,"Full",'DETAIL SALES'!$C$10:$C$7501,"18") -> 0 | CV24: =COUNTIFS('DETAIL SALES'!$Q$10:$Q$7501,'FILL RATE MANDATORY STOCK'!BK24,'DETAIL SALES'!$AB$10:$AB$7501,"No",'DETAIL SALES'!$C$10:$C$7501,"18") -> 0 | CW24: =COUNTIFS('DETAIL SALES'!$Q$10:$Q$7501,'FILL RATE MANDATORY STOCK'!BK24,'DETAIL SALES'!$AB$10:$AB$7501,"Full",'DETAIL SALES'!$C$10:$C$7501,"19") -> 0 | CX24: =COUNTIFS('DETAIL SALES'!$Q$10:$Q$7501,'FILL RATE MANDATORY STOCK'!BK24,'DETAIL SALES'!$AB$10:$AB$7501,"No",'DETAIL SALES'!$C$10:$C$7501,"19") -> 0 | CY24: =COUNTIFS('DETAIL SALES'!$Q$10:$Q$7501,'FILL RATE MANDATORY STOCK'!BK24,'DETAIL SALES'!$AB$10:$AB$7501,"Full",'DETAIL SALES'!$C$10:$C$7501,"20") -> 0 | CZ24: =COUNTIFS('DETAIL SALES'!$Q$10:$Q$7501,'FILL RATE MANDATORY STOCK'!BK24,'DETAIL SALES'!$AB$10:$AB$7501,"No",'DETAIL SALES'!$C$10:$C$7501,"20") -> 0 | DA24: =COUNTIFS('DETAIL SALES'!$Q$10:$Q$7501,'FILL RATE MANDATORY STOCK'!BK24,'DETAIL SALES'!$AB$10:$AB$7501,"Full",'DETAIL SALES'!$C$10:$C$7501,"21") -> 0 | DB24: =COUNTIFS('DETAIL SALES'!$Q$10:$Q$7501,'FILL RATE MANDATORY STOCK'!BK24,'DETAIL SALES'!$AB$10:$AB$7501,"No",'DETAIL SALES'!$C$10:$C$7501,"21") -> 0 | DC24: =COUNTIFS('DETAIL SALES'!$Q$10:$Q$7501,'FILL RATE MANDATORY STOCK'!BK24,'DETAIL SALES'!$AB$10:$AB$7501,"Full",'DETAIL SALES'!$C$10:$C$7501,"22") -> 0 | DD24: =COUNTIFS('DETAIL SALES'!$Q$10:$Q$7501,'FILL RATE MANDATORY STOCK'!BK24,'DETAIL SALES'!$AB$10:$AB$7501,"No",'DETAIL SALES'!$C$10:$C$7501,"22") -> 0 | DE24: =COUNTIFS('DETAIL SALES'!$Q$10:$Q$7501,'FILL RATE MANDATORY STOCK'!BK24,'DETAIL SALES'!$AB$10:$AB$7501,"Full",'DETAIL SALES'!$C$10:$C$7501,"23") -> 0 | DF24: =COUNTIFS('DETAIL SALES'!$Q$10:$Q$7501,'FILL RATE MANDATORY STOCK'!BK24,'DETAIL SALES'!$AB$10:$AB$7501,"No",'DETAIL SALES'!$C$10:$C$7501,"23") -> 0 | DG24: =COUNTIFS('DETAIL SALES'!$Q$10:$Q$7501,'FILL RATE MANDATORY STOCK'!BK24,'DETAIL SALES'!$AB$10:$AB$7501,"Full",'DETAIL SALES'!$C$10:$C$7501,"24") -> 0 | DH24: =COUNTIFS('DETAIL SALES'!$Q$10:$Q$7501,'FILL RATE MANDATORY STOCK'!BK24,'DETAIL SALES'!$AB$10:$AB$7501,"No",'DETAIL SALES'!$C$10:$C$7501,"24") -> 0 | DI24: =COUNTIFS('DETAIL SALES'!$Q$10:$Q$7501,'FILL RATE MANDATORY STOCK'!BK24,'DETAIL SALES'!$AB$10:$AB$7501,"Full",'DETAIL SALES'!$C$10:$C$7501,"25") -> 0 | DJ24: =COUNTIFS('DETAIL SALES'!$Q$10:$Q$7501,'FILL RATE MANDATORY STOCK'!BK24,'DETAIL SALES'!$AB$10:$AB$7501,"No",'DETAIL SALES'!$C$10:$C$7501,"25") -> 0 | DK24: =COUNTIFS('DETAIL SALES'!$Q$10:$Q$7501,'FILL RATE MANDATORY STOCK'!BK24,'DETAIL SALES'!$AB$10:$AB$7501,"Full",'DETAIL SALES'!$C$10:$C$7501,"26") -> 0 | DL24: =COUNTIFS('DETAIL SALES'!$Q$10:$Q$7501,'FILL RATE MANDATORY STOCK'!BK24,'DETAIL SALES'!$AB$10:$AB$7501,"No",'DETAIL SALES'!$C$10:$C$7501,"26") -> 0 | DM24: =COUNTIFS('DETAIL SALES'!$Q$10:$Q$7501,'FILL RATE MANDATORY STOCK'!BK24,'DETAIL SALES'!$AB$10:$AB$7501,"Full",'DETAIL SALES'!$C$10:$C$7501,"27") -> 0 | DN24: =COUNTIFS('DETAIL SALES'!$Q$10:$Q$7501,'FILL RATE MANDATORY STOCK'!BK24,'DETAIL SALES'!$AB$10:$AB$7501,"No",'DETAIL SALES'!$C$10:$C$7501,"27") -> 0 | DO24: =COUNTIFS('DETAIL SALES'!$Q$10:$Q$7501,'FILL RATE MANDATORY STOCK'!BK24,'DETAIL SALES'!$AB$10:$AB$7501,"Full",'DETAIL SALES'!$C$10:$C$7501,"28") -> 0 | DP24: =COUNTIFS('DETAIL SALES'!$Q$10:$Q$7501,'FILL RATE MANDATORY STOCK'!BK24,'DETAIL SALES'!$AB$10:$AB$7501,"No",'DETAIL SALES'!$C$10:$C$7501,"28") -> 0 | DQ24: =COUNTIFS('DETAIL SALES'!$Q$10:$Q$7501,'FILL RATE MANDATORY STOCK'!BK24,'DETAIL SALES'!$AB$10:$AB$7501,"Full",'DETAIL SALES'!$C$10:$C$7501,"29") -> 0 | DR24: =COUNTIFS('DETAIL SALES'!$Q$10:$Q$7501,'FILL RATE MANDATORY STOCK'!BK24,'DETAIL SALES'!$AB$10:$AB$7501,"No",'DETAIL SALES'!$C$10:$C$7501,"29") -> 0 | DS24: =COUNTIFS('DETAIL SALES'!$Q$10:$Q$7501,'FILL RATE MANDATORY STOCK'!BK24,'DETAIL SALES'!$AB$10:$AB$7501,"Full",'DETAIL SALES'!$C$10:$C$7501,"30") -> 0 | DT24: =COUNTIFS('DETAIL SALES'!$Q$10:$Q$7501,'FILL RATE MANDATORY STOCK'!BK24,'DETAIL SALES'!$AB$10:$AB$7501,"No",'DETAIL SALES'!$C$10:$C$7501,"30") -> 0 | DU24: =COUNTIFS('DETAIL SALES'!$Q$10:$Q$7501,'FILL RATE MANDATORY STOCK'!\,'DETAIL SALES'!$AB$10:$AB$7501,"Full",'DETAIL SALES'!$C$10:$C$7501,"31") -> 0 | DV24: =COUNTIFS('DETAIL SALES'!$Q$10:$Q$7501,'FILL RATE MANDATORY STOCK'!BK24,'DETAIL SALES'!$AB$10:$AB$7501,"No",'DETAIL SALES'!$C$10:$C$7501,"31") -> 0 | DW24: =BM24+BO24+BQ24+BS24+BU24+BW24+BY24+CA24+CC24+CE24+CG24+CI24+CK24+CM24+CO24+CQ24+CS24+CU24+CW24+CY24+DA24+DC24+DE24+DG24+DI24+DK24+DM24+DO24+DQ24+DS24+DU24 -> 0 | DX24: =BN24+BP24+BR24+BT24+BV24+BX24+BZ24+CB24+CD24+CF24+CH24+CJ24+CL24+CN24+CP24+CR24+CT24+CV24+CX24+CZ24+DB24+DD24+DF24+DH24+DJ24+DL24+DN24+DP24+DR24+DT24+DV24 -> 0 | DY24: =DW24+DX24 -> 0 | DZ24: =DW24/DY24 -> #DIV/0!
A25: 16 | C25: =DAY(B25) -> 0 | D25: =MONTH(B25) -> 1 | E25: =YEAR(B25) -> 1900 | Y25: =X25*U25 -> 0 | Z25: =Y25*1.1 -> 0 | AB25: =IF(S25="","",IF(S25-U25=0,"Full","No")) | AC25: =IF(AND(S25>U25,V25=0),"Lost",IF(AND(S25>U25,V25<(S25-U25)),"Lost","")) | AD25: =IF(AND(S25>U25,V25=0),S25-U25,IF(AND(S25>U25,V25<(S25-U25)),S25-(U25+V25),"")) | AJ25: 14 | AK25: Contractor | AL25: General Kontraktor | AN25: PT. DUTA CEMERLANG MOTORS | AQ25: Agriculture | AW25: =AV25/$AV$40 -> #DIV/0! | AZ25: =AY25/(AX25+AY25) -> #DIV/0! | BE25: =MAX(BE22:BE24)+1 -> 14 | BF25: Oil Filter | BG25: 110SD/110LD/110HD/130MD/130HD/FB2WG | BH25: 15613LAA70 | BI25: =VLOOKUP(BH25,#REF!,8,FALSE) -> #REF! | BJ25: 10000 | BK25: 1 | BL25: 28.666667 | BM25: =COUNTIFS('DETAIL SALES'!$Q$10:$Q$7501,'FILL RATE MANDATORY STOCK'!BK25,'DETAIL SALES'!$AB$10:$AB$7501,"Full",'DETAIL SALES'!$C$10:$C$7501,"1") -> 0 | BN25: =COUNTIFS('DETAIL SALES'!$Q$10:$Q$7501,'FILL RATE MANDATORY STOCK'!BK25,'DETAIL SALES'!$AB$10:$AB$7501,"No",'DETAIL SALES'!$C$10:$C$7501,"1") -> 0 | BO25: =COUNTIFS('DETAIL SALES'!$Q$10:$Q$7501,'FILL RATE MANDATORY STOCK'!BK25,'DETAIL SALES'!$AB$10:$AB$7501,"Full",'DETAIL SALES'!$C$10:$C$7501,"2") -> 0 | BP25: =COUNTIFS('DETAIL SALES'!$Q$10:$Q$7501,'FILL RATE MANDATORY STOCK'!BK25,'DETAIL SALES'!$AB$10:$AB$7501,"No",'DETAIL SALES'!$C$10:$C$7501,"2") -> 0 | BQ25: =COUNTIFS('DETAIL SALES'!$Q$10:$Q$7501,'FILL RATE MANDATORY STOCK'!BK25,'DETAIL SALES'!$AB$10:$AB$7501,"Full",'DETAIL SALES'!$C$10:$C$7501,"3") -> 0 | BR25: =COUNTIFS('DETAIL SALES'!$Q$10:$Q$7501,'FILL RATE MANDATORY STOCK'!BK25,'DETAIL SALES'!$AB$10:$AB$7501,"No",'DETAIL SALES'!$C$10:$C$7501,"3") -> 0 | BS25: =COUNTIFS('DETAIL SALES'!$Q$10:$Q$7501,'FILL RATE MANDATORY STOCK'!BK25,'DETAIL SALES'!$AB$10:$AB$7501,"Full",'DETAIL SALES'!$C$10:$C$7501,"4") -> 0 | BT25: =COUNTIFS('DETAIL SALES'!$Q$10:$Q$7501,'FILL RATE MANDATORY STOCK'!BK25,'DETAIL SALES'!$AB$10:$AB$7501,"No",'DETAIL SALES'!$C$10:$C$7501,"4") -> 0 | BU25: =COUNTIFS('DETAIL SALES'!$Q$10:$Q$7501,'FILL RATE MANDATORY STOCK'!BK25,'DETAIL SALES'!$AB$10:$AB$7501,"Full",'DETAIL SALES'!$C$10:$C$7501,"5") -> 0 | BV25: =COUNTIFS('DETAIL SALES'!$Q$10:$Q$7501,'FILL RATE MANDATORY STOCK'!BK25,'DETAIL SALES'!$AB$10:$AB$7501,"No",'DETAIL SALES'!$C$10:$C$7501,"5") -> 0 | BW25: =COUNTIFS('DETAIL SALES'!$Q$10:$Q$7501,'FILL RATE MANDATORY STOCK'!BK25,'DETAIL SALES'!$AB$10:$AB$7501,"Full",'DETAIL SALES'!$C$10:$C$7501,"6") -> 0 | BX25: =COUNTIFS('DETAIL SALES'!$Q$10:$Q$7501,'FILL RATE MANDATORY STOCK'!BK25,'DETAIL SALES'!$AB$10:$AB$7501,"No",'DETAIL SALES'!$C$10:$C$7501,"6") -> 0 | BY25: =COUNTIFS('DETAIL SALES'!$Q$10:$Q$7501,'FILL RATE MANDATORY STOCK'!BK25,'DETAIL SALES'!$AB$10:$AB$7501,"Full",'DETAIL SALES'!$C$10:$C$7501,"7") -> 0 | BZ25: =COUNTIFS('DETAIL SALES'!$Q$10:$Q$7501,'FILL RATE MANDATORY STOCK'!BK25,'DETAIL SALES'!$AB$10:$AB$7501,"No",'DETAIL SALES'!$C$10:$C$7501,"7") -> 0 | CA25: =COUNTIFS('DETAIL SALES'!$Q$10:$Q$7501,'FILL RATE MANDATORY STOCK'!BK25,'DETAIL SALES'!$AB$10:$AB$7501,"Full",'DETAIL SALES'!$C$10:$C$7501,"8") -> 0 | CB25: =COUNTIFS('DETAIL SALES'!$Q$10:$Q$7501,'FILL RATE MANDATORY STOCK'!BK25,'DETAIL SALES'!$AB$10:$AB$7501,"No",'DETAIL SALES'!$C$10:$C$7501,"8") -> 0 | CC25: =COUNTIFS('DETAIL SALES'!$Q$10:$Q$7501,'FILL RATE MANDATORY STOCK'!BK25,'DETAIL SALES'!$AB$10:$AB$7501,"Full",'DETAIL SALES'!$C$10:$C$7501,"9") -> 0 | CD25: =COUNTIFS('DETAIL SALES'!$Q$10:$Q$7501,'FILL RATE MANDATORY STOCK'!BK25,'DETAIL SALES'!$AB$10:$AB$7501,"No",'DETAIL SALES'!$C$10:$C$7501,"9") -> 0 | CE25: =COUNTIFS('DETAIL SALES'!$Q$10:$Q$7501,'FILL RATE MANDATORY STOCK'!BK25,'DETAIL SALES'!$AB$10:$AB$7501,"Full",'DETAIL SALES'!$C$10:$C$7501,"10") -> 0 | CF25: =COUNTIFS('DETAIL SALES'!$Q$10:$Q$7501,'FILL RATE MANDATORY STOCK'!BK25,'DETAIL SALES'!$AB$10:$AB$7501,"No",'DETAIL SALES'!$C$10:$C$7501,"10") -> 0 | CG25: =COUNTIFS('DETAIL SALES'!$Q$10:$Q$7501,'FILL RATE MANDATORY STOCK'!BK25,'DETAIL SALES'!$AB$10:$AB$7501,"Full",'DETAIL SALES'!$C$10:$C$7501,"11") -> 0 | CH25: =COUNTIFS('DETAIL SALES'!$Q$10:$Q$7501,'FILL RATE MANDATORY STOCK'!BK25,'DETAIL SALES'!$AB$10:$AB$7501,"No",'DETAIL SALES'!$C$10:$C$7501,"11") -> 0 | CI25: =COUNTIFS('DETAIL SALES'!$Q$10:$Q$7501,'FILL RATE MANDATORY STOCK'!BK25,'DETAIL SALES'!$AB$10:$AB$7501,"Full",'DETAIL SALES'!$C$10:$C$7501,"12") -> 0 | CJ25: =COUNTIFS('DETAIL SALES'!$Q$10:$Q$7501,'FILL RATE MANDATORY STOCK'!BK25,'DETAIL SALES'!$AB$10:$AB$7501,"No",'DETAIL SALES'!$C$10:$C$7501,"12") -> 0 | CK25: =COUNTIFS('DETAIL SALES'!$Q$10:$Q$7501,'FILL RATE MANDATORY STOCK'!BK25,'DETAIL SALES'!$AB$10:$AB$7501,"Full",'DETAIL SALES'!$C$10:$C$7501,"13") -> 0 | CL25: =COUNTIFS('DETAIL SALES'!$Q$10:$Q$7501,'FILL RATE MANDATORY STOCK'!BK25,'DETAIL SALES'!$AB$10:$AB$7501,"No",'DETAIL SALES'!$C$10:$C$7501,"13") -> 0 | CM25: =COUNTIFS('DETAIL SALES'!$Q$10:$Q$7501,'FILL RATE MANDATORY STOCK'!BK25,'DETAIL SALES'!$AB$10:$AB$7501,"Full",'DETAIL SALES'!$C$10:$C$7501,"14") -> 0 | CN25: =COUNTIFS('DETAIL SALES'!$Q$10:$Q$7501,'FILL RATE MANDATORY STOCK'!BK25,'DETAIL SALES'!$AB$10:$AB$7501,"No",'DETAIL SALES'!$C$10:$C$7501,"14") -> 0 | CO25: =COUNTIFS('DETAIL SALES'!$Q$10:$Q$7501,'FILL RATE MANDATORY STOCK'!BK25,'DETAIL SALES'!$AB$10:$AB$7501,"Full",'DETAIL SALES'!$C$10:$C$7501,"15") -> 0 | CP25: =COUNTIFS('DETAIL SALES'!$Q$10:$Q$7501,'FILL RATE MANDATORY STOCK'!BK25,'DETAIL SALES'!$AB$10:$AB$7501,"No",'DETAIL SALES'!$C$10:$C$7501,"15") -> 0 | CQ25: =COUNTIFS('DETAIL SALES'!$Q$10:$Q$7501,'FILL RATE MANDATORY STOCK'!BK25,'DETAIL SALES'!$AB$10:$AB$7501,"Full",'DETAIL SALES'!$C$10:$C$7501,"16") -> 0 | CR25: =COUNTIFS('DETAIL SALES'!$Q$10:$Q$7501,'FILL RATE MANDATORY STOCK'!BK25,'DETAIL SALES'!$AB$10:$AB$7501,"No",'DETAIL SALES'!$C$10:$C$7501,"16") -> 0 | CS25: =COUNTIFS('DETAIL SALES'!$Q$10:$Q$7501,'FILL RATE MANDATORY STOCK'!BK25,'DETAIL SALES'!$AB$10:$AB$7501,"Full",'DETAIL SALES'!$C$10:$C$7501,"17") -> 0 | CT25: =COUNTIFS('DETAIL SALES'!$Q$10:$Q$7501,'FILL RATE MANDATORY STOCK'!BK25,'DETAIL SALES'!$AB$10:$AB$7501,"No",'DETAIL SALES'!$C$10:$C$7501,"17") -> 0 | CU25: =COUNTIFS('DETAIL SALES'!$Q$10:$Q$7501,'FILL RATE MANDATORY STOCK'!BK25,'DETAIL SALES'!$AB$10:$AB$7501,"Full",'DETAIL SALES'!$C$10:$C$7501,"18") -> 0 | CV25: =COUNTIFS('DETAIL SALES'!$Q$10:$Q$7501,'FILL RATE MANDATORY STOCK'!BK25,'DETAIL SALES'!$AB$10:$AB$7501,"No",'DETAIL SALES'!$C$10:$C$7501,"18") -> 0 | CW25: =COUNTIFS('DETAIL SALES'!$Q$10:$Q$7501,'FILL RATE MANDATORY STOCK'!BK25,'DETAIL SALES'!$AB$10:$AB$7501,"Full",'DETAIL SALES'!$C$10:$C$7501,"19") -> 0 | CX25: =COUNTIFS('DETAIL SALES'!$Q$10:$Q$7501,'FILL RATE MANDATORY STOCK'!BK25,'DETAIL SALES'!$AB$10:$AB$7501,"No",'DETAIL SALES'!$C$10:$C$7501,"19") -> 0 | CY25: =COUNTIFS('DETAIL SALES'!$Q$10:$Q$7501,'FILL RATE MANDATORY STOCK'!BK25,'DETAIL SALES'!$AB$10:$AB$7501,"Full",'DETAIL SALES'!$C$10:$C$7501,"20") -> 0 | CZ25: =COUNTIFS('DETAIL SALES'!$Q$10:$Q$7501,'FILL RATE MANDATORY STOCK'!BK25,'DETAIL SALES'!$AB$10:$AB$7501,"No",'DETAIL SALES'!$C$10:$C$7501,"20") -> 0 | DA25: =COUNTIFS('DETAIL SALES'!$Q$10:$Q$7501,'FILL RATE MANDATORY STOCK'!BK25,'DETAIL SALES'!$AB$10:$AB$7501,"Full",'DETAIL SALES'!$C$10:$C$7501,"21") -> 0 | DB25: =COUNTIFS('DETAIL SALES'!$Q$10:$Q$7501,'FILL RATE MANDATORY STOCK'!BK25,'DETAIL SALES'!$AB$10:$AB$7501,"No",'DETAIL SALES'!$C$10:$C$7501,"21") -> 0 | DC25: =COUNTIFS('DETAIL SALES'!$Q$10:$Q$7501,'FILL RATE MANDATORY STOCK'!BK25,'DETAIL SALES'!$AB$10:$AB$7501,"Full",'DETAIL SALES'!$C$10:$C$7501,"22") -> 0 | DD25: =COUNTIFS('DETAIL SALES'!$Q$10:$Q$7501,'FILL RATE MANDATORY STOCK'!BK25,'DETAIL SALES'!$AB$10:$AB$7501,"No",'DETAIL SALES'!$C$10:$C$7501,"22") -> 0 | DE25: =COUNTIFS('DETAIL SALES'!$Q$10:$Q$7501,'FILL RATE MANDATORY STOCK'!BK25,'DETAIL SALES'!$AB$10:$AB$7501,"Full",'DETAIL SALES'!$C$10:$C$7501,"23") -> 0 | DF25: =COUNTIFS('DETAIL SALES'!$Q$10:$Q$7501,'FILL RATE MANDATORY STOCK'!BK25,'DETAIL SALES'!$AB$10:$AB$7501,"No",'DETAIL SALES'!$C$10:$C$7501,"23") -> 0 | DG25: =COUNTIFS('DETAIL SALES'!$Q$10:$Q$7501,'FILL RATE MANDATORY STOCK'!BK25,'DETAIL SALES'!$AB$10:$AB$7501,"Full",'DETAIL SALES'!$C$10:$C$7501,"24") -> 0 | DH25: =COUNTIFS('DETAIL SALES'!$Q$10:$Q$7501,'FILL RATE MANDATORY STOCK'!BK25,'DETAIL SALES'!$AB$10:$AB$7501,"No",'DETAIL SALES'!$C$10:$C$7501,"24") -> 0 | DI25: =COUNTIFS('DETAIL SALES'!$Q$10:$Q$7501,'FILL RATE MANDATORY STOCK'!BK25,'DETAIL SALES'!$AB$10:$AB$7501,"Full",'DETAIL SALES'!$C$10:$C$7501,"25") -> 0 | DJ25: =COUNTIFS('DETAIL SALES'!$Q$10:$Q$7501,'FILL RATE MANDATORY STOCK'!BK25,'DETAIL SALES'!$AB$10:$AB$7501,"No",'DETAIL SALES'!$C$10:$C$7501,"25") -> 0 | DK25: =COUNTIFS('DETAIL SALES'!$Q$10:$Q$7501,'FILL RATE MANDATORY STOCK'!BK25,'DETAIL SALES'!$AB$10:$AB$7501,"Full",'DETAIL SALES'!$C$10:$C$7501,"26") -> 0 | DL25: =COUNTIFS('DETAIL SALES'!$Q$10:$Q$7501,'FILL RATE MANDATORY STOCK'!BK25,'DETAIL SALES'!$AB$10:$AB$7501,"No",'DETAIL SALES'!$C$10:$C$7501,"26") -> 0 | DM25: =COUNTIFS('DETAIL SALES'!$Q$10:$Q$7501,'FILL RATE MANDATORY STOCK'!BK25,'DETAIL SALES'!$AB$10:$AB$7501,"Full",'DETAIL SALES'!$C$10:$C$7501,"27") -> 0 | DN25: =COUNTIFS('DETAIL SALES'!$Q$10:$Q$7501,'FILL RATE MANDATORY STOCK'!BK25,'DETAIL SALES'!$AB$10:$AB$7501,"No",'DETAIL SALES'!$C$10:$C$7501,"27") -> 0 | DO25: =COUNTIFS('DETAIL SALES'!$Q$10:$Q$7501,'FILL RATE MANDATORY STOCK'!BK25,'DETAIL SALES'!$AB$10:$AB$7501,"Full",'DETAIL SALES'!$C$10:$C$7501,"28") -> 0 | DP25: =COUNTIFS('DETAIL SALES'!$Q$10:$Q$7501,'FILL RATE MANDATORY STOCK'!BK25,'DETAIL SALES'!$AB$10:$AB$7501,"No",'DETAIL SALES'!$C$10:$C$7501,"28") -> 0 | DQ25: =COUNTIFS('DETAIL SALES'!$Q$10:$Q$7501,'FILL RATE MANDATORY STOCK'!BK25,'DETAIL SALES'!$AB$10:$AB$7501,"Full",'DETAIL SALES'!$C$10:$C$7501,"29") -> 0 | DR25: =COUNTIFS('DETAIL SALES'!$Q$10:$Q$7501,'FILL RATE MANDATORY STOCK'!BK25,'DETAIL SALES'!$AB$10:$AB$7501,"No",'DETAIL SALES'!$C$10:$C$7501,"29") -> 0 | DS25: =COUNTIFS('DETAIL SALES'!$Q$10:$Q$7501,'FILL RATE MANDATORY STOCK'!BK25,'DETAIL SALES'!$AB$10:$AB$7501,"Full",'DETAIL SALES'!$C$10:$C$7501,"30") -> 0 | DT25: =COUNTIFS('DETAIL SALES'!$Q$10:$Q$7501,'FILL RATE MANDATORY STOCK'!BK25,'DETAIL SALES'!$AB$10:$AB$7501,"No",'DETAIL SALES'!$C$10:$C$7501,"30") -> 0 | DU25: =COUNTIFS('DETAIL SALES'!$Q$10:$Q$7501,'FILL RATE MANDATORY STOCK'!\,'DETAIL SALES'!$AB$10:$AB$7501,"Full",'DETAIL SALES'!$C$10:$C$7501,"31") -> 0 | DV25: =COUNTIFS('DETAIL SALES'!$Q$10:$Q$7501,'FILL RATE MANDATORY STOCK'!BK25,'DETAIL SALES'!$AB$10:$AB$7501,"No",'DETAIL SALES'!$C$10:$C$7501,"31") -> 0 | DW25: =BM25+BO25+BQ25+BS25+BU25+BW25+BY25+CA25+CC25+CE25+CG25+CI25+CK25+CM25+CO25+CQ25+CS25+CU25+CW25+CY25+DA25+DC25+DE25+DG25+DI25+DK25+DM25+DO25+DQ25+DS25+DU25 -> 0 | DX25: =BN25+BP25+BR25+BT25+BV25+BX25+BZ25+CB25+CD25+CF25+CH25+CJ25+CL25+CN25+CP25+CR25+CT25+CV25+CX25+CZ25+DB25+DD25+DF25+DH25+DJ25+DL25+DN25+DP25+DR25+DT25+DV25 -> 0 | DY25: =DW25+DX25 -> 0 | DZ25: =DW25/DY25 -> #DIV/0!
A26: 17 | C26: =DAY(B26) -> 0 | D26: =MONTH(B26) -> 1 | E26: =YEAR(B26) -> 1900 | Y26: =X26*U26 -> 0 | Z26: =Y26*1.1 -> 0 | AB26: =IF(S26="","",IF(S26-U26=0,"Full","No")) | AC26: =IF(AND(S26>U26,V26=0),"Lost",IF(AND(S26>U26,V26<(S26-U26)),"Lost","")) | AD26: =IF(AND(S26>U26,V26=0),S26-U26,IF(AND(S26>U26,V26<(S26-U26)),S26-(U26+V26),"")) | AJ26: 15 | AK26: Construction | AL26: WIKA | AN26: PT. GENTA LAMPUNG MAKMUR | AQ26: Mining | AW26: =AV26/$AV$40 -> #DIV/0! | AZ26: =AY26/(AX26+AY26) -> #DIV/0! | BE26: =MAX(BE23:BE25)+1 -> 15 | BF26: Oil Filter | BG26: FM2P 350PS (363&Y230) | BH26: S1560JCE30 | BI26: =VLOOKUP(BH26,#REF!,8,FALSE) -> #REF! | BJ26: 20000 | BK26: 1 | BL26: 0 | BM26: =COUNTIFS('DETAIL SALES'!$Q$10:$Q$7501,'FILL RATE MANDATORY STOCK'!BK26,'DETAIL SALES'!$AB$10:$AB$7501,"Full",'DETAIL SALES'!$C$10:$C$7501,"1") -> 0 | BN26: =COUNTIFS('DETAIL SALES'!$Q$10:$Q$7501,'FILL RATE MANDATORY STOCK'!BK26,'DETAIL SALES'!$AB$10:$AB$7501,"No",'DETAIL SALES'!$C$10:$C$7501,"1") -> 0 | BO26: =COUNTIFS('DETAIL SALES'!$Q$10:$Q$7501,'FILL RATE MANDATORY STOCK'!BK26,'DETAIL SALES'!$AB$10:$AB$7501,"Full",'DETAIL SALES'!$C$10:$C$7501,"2") -> 0 | BP26: =COUNTIFS('DETAIL SALES'!$Q$10:$Q$7501,'FILL RATE MANDATORY STOCK'!BK26,'DETAIL SALES'!$AB$10:$AB$7501,"No",'DETAIL SALES'!$C$10:$C$7501,"2") -> 0 | BQ26: =COUNTIFS('DETAIL SALES'!$Q$10:$Q$7501,'FILL RATE MANDATORY STOCK'!BK26,'DETAIL SALES'!$AB$10:$AB$7501,"Full",'DETAIL SALES'!$C$10:$C$7501,"3") -> 0 | BR26: =COUNTIFS('DETAIL SALES'!$Q$10:$Q$7501,'FILL RATE MANDATORY STOCK'!BK26,'DETAIL SALES'!$AB$10:$AB$7501,"No",'DETAIL SALES'!$C$10:$C$7501,"3") -> 0 | BS26: =COUNTIFS('DETAIL SALES'!$Q$10:$Q$7501,'FILL RATE MANDATORY STOCK'!BK26,'DETAIL SALES'!$AB$10:$AB$7501,"Full",'DETAIL SALES'!$C$10:$C$7501,"4") -> 0 | BT26: =COUNTIFS('DETAIL SALES'!$Q$10:$Q$7501,'FILL RATE MANDATORY STOCK'!BK26,'DETAIL SALES'!$AB$10:$AB$7501,"No",'DETAIL SALES'!$C$10:$C$7501,"4") -> 0 | BU26: =COUNTIFS('DETAIL SALES'!$Q$10:$Q$7501,'FILL RATE MANDATORY STOCK'!BK26,'DETAIL SALES'!$AB$10:$AB$7501,"Full",'DETAIL SALES'!$C$10:$C$7501,"5") -> 0 | BV26: =COUNTIFS('DETAIL SALES'!$Q$10:$Q$7501,'FILL RATE MANDATORY STOCK'!BK26,'DETAIL SALES'!$AB$10:$AB$7501,"No",'DETAIL SALES'!$C$10:$C$7501,"5") -> 0 | BW26: =COUNTIFS('DETAIL SALES'!$Q$10:$Q$7501,'FILL RATE MANDATORY STOCK'!BK26,'DETAIL SALES'!$AB$10:$AB$7501,"Full",'DETAIL SALES'!$C$10:$C$7501,"6") -> 0 | BX26: =COUNTIFS('DETAIL SALES'!$Q$10:$Q$7501,'FILL RATE MANDATORY STOCK'!BK26,'DETAIL SALES'!$AB$10:$AB$7501,"No",'DETAIL SALES'!$C$10:$C$7501,"6") -> 0 | BY26: =COUNTIFS('DETAIL SALES'!$Q$10:$Q$7501,'FILL RATE MANDATORY STOCK'!BK26,'DETAIL SALES'!$AB$10:$AB$7501,"Full",'DETAIL SALES'!$C$10:$C$7501,"7") -> 0 | BZ26: =COUNTIFS('DETAIL SALES'!$Q$10:$Q$7501,'FILL RATE MANDATORY STOCK'!BK26,'DETAIL SALES'!$AB$10:$AB$7501,"No",'DETAIL SALES'!$C$10:$C$7501,"7") -> 0 | CA26: =COUNTIFS('DETAIL SALES'!$Q$10:$Q$7501,'FILL RATE MANDATORY STOCK'!BK26,'DETAIL SALES'!$AB$10:$AB$7501,"Full",'DETAIL SALES'!$C$10:$C$7501,"8") -> 0 | CB26: =COUNTIFS('DETAIL SALES'!$Q$10:$Q$7501,'FILL RATE MANDATORY STOCK'!BK26,'DETAIL SALES'!$AB$10:$AB$7501,"No",'DETAIL SALES'!$C$10:$C$7501,"8") -> 0 | CC26: =COUNTIFS('DETAIL SALES'!$Q$10:$Q$7501,'FILL RATE MANDATORY STOCK'!BK26,'DETAIL SALES'!$AB$10:$AB$7501,"Full",'DETAIL SALES'!$C$10:$C$7501,"9") -> 0 | CD26: =COUNTIFS('DETAIL SALES'!$Q$10:$Q$7501,'FILL RATE MANDATORY STOCK'!BK26,'DETAIL SALES'!$AB$10:$AB$7501,"No",'DETAIL SALES'!$C$10:$C$7501,"9") -> 0 | CE26: =COUNTIFS('DETAIL SALES'!$Q$10:$Q$7501,'FILL RATE MANDATORY STOCK'!BK26,'DETAIL SALES'!$AB$10:$AB$7501,"Full",'DETAIL SALES'!$C$10:$C$7501,"10") -> 0 | CF26: =COUNTIFS('DETAIL SALES'!$Q$10:$Q$7501,'FILL RATE MANDATORY STOCK'!BK26,'DETAIL SALES'!$AB$10:$AB$7501,"No",'DETAIL SALES'!$C$10:$C$7501,"10") -> 0 | CG26: =COUNTIFS('DETAIL SALES'!$Q$10:$Q$7501,'FILL RATE MANDATORY STOCK'!BK26,'DETAIL SALES'!$AB$10:$AB$7501,"Full",'DETAIL SALES'!$C$10:$C$7501,"11") -> 0 | CH26: =COUNTIFS('DETAIL SALES'!$Q$10:$Q$7501,'FILL RATE MANDATORY STOCK'!BK26,'DETAIL SALES'!$AB$10:$AB$7501,"No",'DETAIL SALES'!$C$10:$C$7501,"11") -> 0 | CI26: =COUNTIFS('DETAIL SALES'!$Q$10:$Q$7501,'FILL RATE MANDATORY STOCK'!BK26,'DETAIL SALES'!$AB$10:$AB$7501,"Full",'DETAIL SALES'!$C$10:$C$7501,"12") -> 0 | CJ26: =COUNTIFS('DETAIL SALES'!$Q$10:$Q$7501,'FILL RATE MANDATORY STOCK'!BK26,'DETAIL SALES'!$AB$10:$AB$7501,"No",'DETAIL SALES'!$C$10:$C$7501,"12") -> 0 | CK26: =COUNTIFS('DETAIL SALES'!$Q$10:$Q$7501,'FILL RATE MANDATORY STOCK'!BK26,'DETAIL SALES'!$AB$10:$AB$7501,"Full",'DETAIL SALES'!$C$10:$C$7501,"13") -> 0 | CL26: =COUNTIFS('DETAIL SALES'!$Q$10:$Q$7501,'FILL RATE MANDATORY STOCK'!BK26,'DETAIL SALES'!$AB$10:$AB$7501,"No",'DETAIL SALES'!$C$10:$C$7501,"13") -> 0 | CM26: =COUNTIFS('DETAIL SALES'!$Q$10:$Q$7501,'FILL RATE MANDATORY STOCK'!BK26,'DETAIL SALES'!$AB$10:$AB$7501,"Full",'DETAIL SALES'!$C$10:$C$7501,"14") -> 0 | CN26: =COUNTIFS('DETAIL SALES'!$Q$10:$Q$7501,'FILL RATE MANDATORY STOCK'!BK26,'DETAIL SALES'!$AB$10:$AB$7501,"No",'DETAIL SALES'!$C$10:$C$7501,"14") -> 0 | CO26: =COUNTIFS('DETAIL SALES'!$Q$10:$Q$7501,'FILL RATE MANDATORY STOCK'!BK26,'DETAIL SALES'!$AB$10:$AB$7501,"Full",'DETAIL SALES'!$C$10:$C$7501,"15") -> 0 | CP26: =COUNTIFS('DETAIL SALES'!$Q$10:$Q$7501,'FILL RATE MANDATORY STOCK'!BK26,'DETAIL SALES'!$AB$10:$AB$7501,"No",'DETAIL SALES'!$C$10:$C$7501,"15") -> 0 | CQ26: =COUNTIFS('DETAIL SALES'!$Q$10:$Q$7501,'FILL RATE MANDATORY STOCK'!BK26,'DETAIL SALES'!$AB$10:$AB$7501,"Full",'DETAIL SALES'!$C$10:$C$7501,"16") -> 0 | CR26: =COUNTIFS('DETAIL SALES'!$Q$10:$Q$7501,'FILL RATE MANDATORY STOCK'!BK26,'DETAIL SALES'!$AB$10:$AB$7501,"No",'DETAIL SALES'!$C$10:$C$7501,"16") -> 0 | CS26: =COUNTIFS('DETAIL SALES'!$Q$10:$Q$7501,'FILL RATE MANDATORY STOCK'!BK26,'DETAIL SALES'!$AB$10:$AB$7501,"Full",'DETAIL SALES'!$C$10:$C$7501,"17") -> 0 | CT26: =COUNTIFS('DETAIL SALES'!$Q$10:$Q$7501,'FILL RATE MANDATORY STOCK'!BK26,'DETAIL SALES'!$AB$10:$AB$7501,"No",'DETAIL SALES'!$C$10:$C$7501,"17") -> 0 | CU26: =COUNTIFS('DETAIL SALES'!$Q$10:$Q$7501,'FILL RATE MANDATORY STOCK'!BK26,'DETAIL SALES'!$AB$10:$AB$7501,"Full",'DETAIL SALES'!$C$10:$C$7501,"18") -> 0 | CV26: =COUNTIFS('DETAIL SALES'!$Q$10:$Q$7501,'FILL RATE MANDATORY STOCK'!BK26,'DETAIL SALES'!$AB$10:$AB$7501,"No",'DETAIL SALES'!$C$10:$C$7501,"18") -> 0 | CW26: =COUNTIFS('DETAIL SALES'!$Q$10:$Q$7501,'FILL RATE MANDATORY STOCK'!BK26,'DETAIL SALES'!$AB$10:$AB$7501,"Full",'DETAIL SALES'!$C$10:$C$7501,"19") -> 0 | CX26: =COUNTIFS('DETAIL SALES'!$Q$10:$Q$7501,'FILL RATE MANDATORY STOCK'!BK26,'DETAIL SALES'!$AB$10:$AB$7501,"No",'DETAIL SALES'!$C$10:$C$7501,"19") -> 0 | CY26: =COUNTIFS('DETAIL SALES'!$Q$10:$Q$7501,'FILL RATE MANDATORY STOCK'!BK26,'DETAIL SALES'!$AB$10:$AB$7501,"Full",'DETAIL SALES'!$C$10:$C$7501,"20") -> 0 | CZ26: =COUNTIFS('DETAIL SALES'!$Q$10:$Q$7501,'FILL RATE MANDATORY STOCK'!BK26,'DETAIL SALES'!$AB$10:$AB$7501,"No",'DETAIL SALES'!$C$10:$C$7501,"20") -> 0 | DA26: =COUNTIFS('DETAIL SALES'!$Q$10:$Q$7501,'FILL RATE MANDATORY STOCK'!BK26,'DETAIL SALES'!$AB$10:$AB$7501,"Full",'DETAIL SALES'!$C$10:$C$7501,"21") -> 0 | DB26: =COUNTIFS('DETAIL SALES'!$Q$10:$Q$7501,'FILL RATE MANDATORY STOCK'!BK26,'DETAIL SALES'!$AB$10:$AB$7501,"No",'DETAIL SALES'!$C$10:$C$7501,"21") -> 0 | DC26: =COUNTIFS('DETAIL SALES'!$Q$10:$Q$7501,'FILL RATE MANDATORY STOCK'!BK26,'DETAIL SALES'!$AB$10:$AB$7501,"Full",'DETAIL SALES'!$C$10:$C$7501,"22") -> 0 | DD26: =COUNTIFS('DETAIL SALES'!$Q$10:$Q$7501,'FILL RATE MANDATORY STOCK'!BK26,'DETAIL SALES'!$AB$10:$AB$7501,"No",'DETAIL SALES'!$C$10:$C$7501,"22") -> 0 | DE26: =COUNTIFS('DETAIL SALES'!$Q$10:$Q$7501,'FILL RATE MANDATORY STOCK'!BK26,'DETAIL SALES'!$AB$10:$AB$7501,"Full",'DETAIL SALES'!$C$10:$C$7501,"23") -> 0 | DF26: =COUNTIFS('DETAIL SALES'!$Q$10:$Q$7501,'FILL RATE MANDATORY STOCK'!BK26,'DETAIL SALES'!$AB$10:$AB$7501,"No",'DETAIL SALES'!$C$10:$C$7501,"23") -> 0 | DG26: =COUNTIFS('DETAIL SALES'!$Q$10:$Q$7501,'FILL RATE MANDATORY STOCK'!BK26,'DETAIL SALES'!$AB$10:$AB$7501,"Full",'DETAIL SALES'!$C$10:$C$7501,"24") -> 0 | DH26: =COUNTIFS('DETAIL SALES'!$Q$10:$Q$7501,'FILL RATE MANDATORY STOCK'!BK26,'DETAIL SALES'!$AB$10:$AB$7501,"No",'DETAIL SALES'!$C$10:$C$7501,"24") -> 0 | DI26: =COUNTIFS('DETAIL SALES'!$Q$10:$Q$7501,'FILL RATE MANDATORY STOCK'!BK26,'DETAIL SALES'!$AB$10:$AB$7501,"Full",'DETAIL SALES'!$C$10:$C$7501,"25") -> 0 | DJ26: =COUNTIFS('DETAIL SALES'!$Q$10:$Q$7501,'FILL RATE MANDATORY STOCK'!BK26,'DETAIL SALES'!$AB$10:$AB$7501,"No",'DETAIL SALES'!$C$10:$C$7501,"25") -> 0 | DK26: =COUNTIFS('DETAIL SALES'!$Q$10:$Q$7501,'FILL RATE MANDATORY STOCK'!BK26,'DETAIL SALES'!$AB$10:$AB$7501,"Full",'DETAIL SALES'!$C$10:$C$7501,"26") -> 0 | DL26: =COUNTIFS('DETAIL SALES'!$Q$10:$Q$7501,'FILL RATE MANDATORY STOCK'!BK26,'DETAIL SALES'!$AB$10:$AB$7501,"No",'DETAIL SALES'!$C$10:$C$7501,"26") -> 0 | DM26: =COUNTIFS('DETAIL SALES'!$Q$10:$Q$7501,'FILL RATE MANDATORY STOCK'!BK26,'DETAIL SALES'!$AB$10:$AB$7501,"Full",'DETAIL SALES'!$C$10:$C$7501,"27") -> 0 | DN26: =COUNTIFS('DETAIL SALES'!$Q$10:$Q$7501,'FILL RATE MANDATORY STOCK'!BK26,'DETAIL SALES'!$AB$10:$AB$7501,"No",'DETAIL SALES'!$C$10:$C$7501,"27") -> 0 | DO26: =COUNTIFS('DETAIL SALES'!$Q$10:$Q$7501,'FILL RATE MANDATORY STOCK'!BK26,'DETAIL SALES'!$AB$10:$AB$7501,"Full",'DETAIL SALES'!$C$10:$C$7501,"28") -> 0 | DP26: =COUNTIFS('DETAIL SALES'!$Q$10:$Q$7501,'FILL RATE MANDATORY STOCK'!BK26,'DETAIL SALES'!$AB$10:$AB$7501,"No",'DETAIL SALES'!$C$10:$C$7501,"28") -> 0 | DQ26: =COUNTIFS('DETAIL SALES'!$Q$10:$Q$7501,'FILL RATE MANDATORY STOCK'!BK26,'DETAIL SALES'!$AB$10:$AB$7501,"Full",'DETAIL SALES'!$C$10:$C$7501,"29") -> 0 | DR26: =COUNTIFS('DETAIL SALES'!$Q$10:$Q$7501,'FILL RATE MANDATORY STOCK'!BK26,'DETAIL SALES'!$AB$10:$AB$7501,"No",'DETAIL SALES'!$C$10:$C$7501,"29") -> 0 | DS26: =COUNTIFS('DETAIL SALES'!$Q$10:$Q$7501,'FILL RATE MANDATORY STOCK'!BK26,'DETAIL SALES'!$AB$10:$AB$7501,"Full",'DETAIL SALES'!$C$10:$C$7501,"30") -> 0 | DT26: =COUNTIFS('DETAIL SALES'!$Q$10:$Q$7501,'FILL RATE MANDATORY STOCK'!BK26,'DETAIL SALES'!$AB$10:$AB$7501,"No",'DETAIL SALES'!$C$10:$C$7501,"30") -> 0 | DU26: =COUNTIFS('DETAIL SALES'!$Q$10:$Q$7501,'FILL RATE MANDATORY STOCK'!\,'DETAIL SALES'!$AB$10:$AB$7501,"Full",'DETAIL SALES'!$C$10:$C$7501,"31") -> 0 | DV26: =COUNTIFS('DETAIL SALES'!$Q$10:$Q$7501,'FILL RATE MANDATORY STOCK'!BK26,'DETAIL SALES'!$AB$10:$AB$7501,"No",'DETAIL SALES'!$C$10:$C$7501,"31") -> 0 | DW26: =BM26+BO26+BQ26+BS26+BU26+BW26+BY26+CA26+CC26+CE26+CG26+CI26+CK26+CM26+CO26+CQ26+CS26+CU26+CW26+CY26+DA26+DC26+DE26+DG26+DI26+DK26+DM26+DO26+DQ26+DS26+DU26 -> 0 | DX26: =BN26+BP26+BR26+BT26+BV26+BX26+BZ26+CB26+CD26+CF26+CH26+CJ26+CL26+CN26+CP26+CR26+CT26+CV26+CX26+CZ26+DB26+DD26+DF26+DH26+DJ26+DL26+DN26+DP26+DR26+DT26+DV26 -> 0 | DY26: =DW26+DX26 -> 0 | DZ26: =DW26/DY26 -> #DIV/0!
A27: 18 | C27: =DAY(B27) -> 0 | D27: =MONTH(B27) -> 1 | E27: =YEAR(B27) -> 1900 | Y27: =X27*U27 -> 0 | Z27: =Y27*1.1 -> 0 | AB27: =IF(S27="","",IF(S27-U27=0,"Full","No")) | AC27: =IF(AND(S27>U27,V27=0),"Lost",IF(AND(S27>U27,V27<(S27-U27)),"Lost","")) | AD27: =IF(AND(S27>U27,V27=0),S27-U27,IF(AND(S27>U27,V27<(S27-U27)),S27-(U27+V27),"")) | AJ27: 16 | AK27: Otomotif | AN27: PT. GITA RIAU MAKMUR | AQ27: Material Construction | AW27: =AV27/$AV$40 -> #DIV/0! | AZ27: =AY27/(AX27+AY27) -> #DIV/0! | BE27: =MAX(BE24:BE26)+1 -> 16 | BF27: Oil Filter | BG27: FM2P 350PS (363&Y230) | BH27: S1560JCE40 | BI27: =VLOOKUP(BH27,#REF!,8,FALSE) -> #REF! | BJ27: 20000 | BK27: 1 | BL27: 0 | BM27: =COUNTIFS('DETAIL SALES'!$Q$10:$Q$7501,'FILL RATE MANDATORY STOCK'!BK27,'DETAIL SALES'!$AB$10:$AB$7501,"Full",'DETAIL SALES'!$C$10:$C$7501,"1") -> 0 | BN27: =COUNTIFS('DETAIL SALES'!$Q$10:$Q$7501,'FILL RATE MANDATORY STOCK'!BK27,'DETAIL SALES'!$AB$10:$AB$7501,"No",'DETAIL SALES'!$C$10:$C$7501,"1") -> 0 | BO27: =COUNTIFS('DETAIL SALES'!$Q$10:$Q$7501,'FILL RATE MANDATORY STOCK'!BK27,'DETAIL SALES'!$AB$10:$AB$7501,"Full",'DETAIL SALES'!$C$10:$C$7501,"2") -> 0 | BP27: =COUNTIFS('DETAIL SALES'!$Q$10:$Q$7501,'FILL RATE MANDATORY STOCK'!BK27,'DETAIL SALES'!$AB$10:$AB$7501,"No",'DETAIL SALES'!$C$10:$C$7501,"2") -> 0 | BQ27: =COUNTIFS('DETAIL SALES'!$Q$10:$Q$7501,'FILL RATE MANDATORY STOCK'!BK27,'DETAIL SALES'!$AB$10:$AB$7501,"Full",'DETAIL SALES'!$C$10:$C$7501,"3") -> 0 | BR27: =COUNTIFS('DETAIL SALES'!$Q$10:$Q$7501,'FILL RATE MANDATORY STOCK'!BK27,'DETAIL SALES'!$AB$10:$AB$7501,"No",'DETAIL SALES'!$C$10:$C$7501,"3") -> 0 | BS27: =COUNTIFS('DETAIL SALES'!$Q$10:$Q$7501,'FILL RATE MANDATORY STOCK'!BK27,'DETAIL SALES'!$AB$10:$AB$7501,"Full",'DETAIL SALES'!$C$10:$C$7501,"4") -> 0 | BT27: =COUNTIFS('DETAIL SALES'!$Q$10:$Q$7501,'FILL RATE MANDATORY STOCK'!BK27,'DETAIL SALES'!$AB$10:$AB$7501,"No",'DETAIL SALES'!$C$10:$C$7501,"4") -> 0 | BU27: =COUNTIFS('DETAIL SALES'!$Q$10:$Q$7501,'FILL RATE MANDATORY STOCK'!BK27,'DETAIL SALES'!$AB$10:$AB$7501,"Full",'DETAIL SALES'!$C$10:$C$7501,"5") -> 0 | BV27: =COUNTIFS('DETAIL SALES'!$Q$10:$Q$7501,'FILL RATE MANDATORY STOCK'!BK27,'DETAIL SALES'!$AB$10:$AB$7501,"No",'DETAIL SALES'!$C$10:$C$7501,"5") -> 0 | BW27: =COUNTIFS('DETAIL SALES'!$Q$10:$Q$7501,'FILL RATE MANDATORY STOCK'!BK27,'DETAIL SALES'!$AB$10:$AB$7501,"Full",'DETAIL SALES'!$C$10:$C$7501,"6") -> 0 | BX27: =COUNTIFS('DETAIL SALES'!$Q$10:$Q$7501,'FILL RATE MANDATORY STOCK'!BK27,'DETAIL SALES'!$AB$10:$AB$7501,"No",'DETAIL SALES'!$C$10:$C$7501,"6") -> 0 | BY27: =COUNTIFS('DETAIL SALES'!$Q$10:$Q$7501,'FILL RATE MANDATORY STOCK'!BK27,'DETAIL SALES'!$AB$10:$AB$7501,"Full",'DETAIL SALES'!$C$10:$C$7501,"7") -> 0 | BZ27: =COUNTIFS('DETAIL SALES'!$Q$10:$Q$7501,'FILL RATE MANDATORY STOCK'!BK27,'DETAIL SALES'!$AB$10:$AB$7501,"No",'DETAIL SALES'!$C$10:$C$7501,"7") -> 0 | CA27: =COUNTIFS('DETAIL SALES'!$Q$10:$Q$7501,'FILL RATE MANDATORY STOCK'!BK27,'DETAIL SALES'!$AB$10:$AB$7501,"Full",'DETAIL SALES'!$C$10:$C$7501,"8") -> 0 | CB27: =COUNTIFS('DETAIL SALES'!$Q$10:$Q$7501,'FILL RATE MANDATORY STOCK'!BK27,'DETAIL SALES'!$AB$10:$AB$7501,"No",'DETAIL SALES'!$C$10:$C$7501,"8") -> 0 | CC27: =COUNTIFS('DETAIL SALES'!$Q$10:$Q$7501,'FILL RATE MANDATORY STOCK'!BK27,'DETAIL SALES'!$AB$10:$AB$7501,"Full",'DETAIL SALES'!$C$10:$C$7501,"9") -> 0 | CD27: =COUNTIFS('DETAIL SALES'!$Q$10:$Q$7501,'FILL RATE MANDATORY STOCK'!BK27,'DETAIL SALES'!$AB$10:$AB$7501,"No",'DETAIL SALES'!$C$10:$C$7501,"9") -> 0 | CE27: =COUNTIFS('DETAIL SALES'!$Q$10:$Q$7501,'FILL RATE MANDATORY STOCK'!BK27,'DETAIL SALES'!$AB$10:$AB$7501,"Full",'DETAIL SALES'!$C$10:$C$7501,"10") -> 0 | CF27: =COUNTIFS('DETAIL SALES'!$Q$10:$Q$7501,'FILL RATE MANDATORY STOCK'!BK27,'DETAIL SALES'!$AB$10:$AB$7501,"No",'DETAIL SALES'!$C$10:$C$7501,"10") -> 0 | CG27: =COUNTIFS('DETAIL SALES'!$Q$10:$Q$7501,'FILL RATE MANDATORY STOCK'!BK27,'DETAIL SALES'!$AB$10:$AB$7501,"Full",'DETAIL SALES'!$C$10:$C$7501,"11") -> 0 | CH27: =COUNTIFS('DETAIL SALES'!$Q$10:$Q$7501,'FILL RATE MANDATORY STOCK'!BK27,'DETAIL SALES'!$AB$10:$AB$7501,"No",'DETAIL SALES'!$C$10:$C$7501,"11") -> 0 | CI27: =COUNTIFS('DETAIL SALES'!$Q$10:$Q$7501,'FILL RATE MANDATORY STOCK'!BK27,'DETAIL SALES'!$AB$10:$AB$7501,"Full",'DETAIL SALES'!$C$10:$C$7501,"12") -> 0 | CJ27: =COUNTIFS('DETAIL SALES'!$Q$10:$Q$7501,'FILL RATE MANDATORY STOCK'!BK27,'DETAIL SALES'!$AB$10:$AB$7501,"No",'DETAIL SALES'!$C$10:$C$7501,"12") -> 0 | CK27: =COUNTIFS('DETAIL SALES'!$Q$10:$Q$7501,'FILL RATE MANDATORY STOCK'!BK27,'DETAIL SALES'!$AB$10:$AB$7501,"Full",'DETAIL SALES'!$C$10:$C$7501,"13") -> 0 | CL27: =COUNTIFS('DETAIL SALES'!$Q$10:$Q$7501,'FILL RATE MANDATORY STOCK'!BK27,'DETAIL SALES'!$AB$10:$AB$7501,"No",'DETAIL SALES'!$C$10:$C$7501,"13") -> 0 | CM27: =COUNTIFS('DETAIL SALES'!$Q$10:$Q$7501,'FILL RATE MANDATORY STOCK'!BK27,'DETAIL SALES'!$AB$10:$AB$7501,"Full",'DETAIL SALES'!$C$10:$C$7501,"14") -> 0 | CN27: =COUNTIFS('DETAIL SALES'!$Q$10:$Q$7501,'FILL RATE MANDATORY STOCK'!BK27,'DETAIL SALES'!$AB$10:$AB$7501,"No",'DETAIL SALES'!$C$10:$C$7501,"14") -> 0 | CO27: =COUNTIFS('DETAIL SALES'!$Q$10:$Q$7501,'FILL RATE MANDATORY STOCK'!BK27,'DETAIL SALES'!$AB$10:$AB$7501,"Full",'DETAIL SALES'!$C$10:$C$7501,"15") -> 0 | CP27: =COUNTIFS('DETAIL SALES'!$Q$10:$Q$7501,'FILL RATE MANDATORY STOCK'!BK27,'DETAIL SALES'!$AB$10:$AB$7501,"No",'DETAIL SALES'!$C$10:$C$7501,"15") -> 0 | CQ27: =COUNTIFS('DETAIL SALES'!$Q$10:$Q$7501,'FILL RATE MANDATORY STOCK'!BK27,'DETAIL SALES'!$AB$10:$AB$7501,"Full",'DETAIL SALES'!$C$10:$C$7501,"16") -> 0 | CR27: =COUNTIFS('DETAIL SALES'!$Q$10:$Q$7501,'FILL RATE MANDATORY STOCK'!BK27,'DETAIL SALES'!$AB$10:$AB$7501,"No",'DETAIL SALES'!$C$10:$C$7501,"16") -> 0 | CS27: =COUNTIFS('DETAIL SALES'!$Q$10:$Q$7501,'FILL RATE MANDATORY STOCK'!BK27,'DETAIL SALES'!$AB$10:$AB$7501,"Full",'DETAIL SALES'!$C$10:$C$7501,"17") -> 0 | CT27: =COUNTIFS('DETAIL SALES'!$Q$10:$Q$7501,'FILL RATE MANDATORY STOCK'!BK27,'DETAIL SALES'!$AB$10:$AB$7501,"No",'DETAIL SALES'!$C$10:$C$7501,"17") -> 0 | CU27: =COUNTIFS('DETAIL SALES'!$Q$10:$Q$7501,'FILL RATE MANDATORY STOCK'!BK27,'DETAIL SALES'!$AB$10:$AB$7501,"Full",'DETAIL SALES'!$C$10:$C$7501,"18") -> 0 | CV27: =COUNTIFS('DETAIL SALES'!$Q$10:$Q$7501,'FILL RATE MANDATORY STOCK'!BK27,'DETAIL SALES'!$AB$10:$AB$7501,"No",'DETAIL SALES'!$C$10:$C$7501,"18") -> 0 | CW27: =COUNTIFS('DETAIL SALES'!$Q$10:$Q$7501,'FILL RATE MANDATORY STOCK'!BK27,'DETAIL SALES'!$AB$10:$AB$7501,"Full",'DETAIL SALES'!$C$10:$C$7501,"19") -> 0 | CX27: =COUNTIFS('DETAIL SALES'!$Q$10:$Q$7501,'FILL RATE MANDATORY STOCK'!BK27,'DETAIL SALES'!$AB$10:$AB$7501,"No",'DETAIL SALES'!$C$10:$C$7501,"19") -> 0 | CY27: =COUNTIFS('DETAIL SALES'!$Q$10:$Q$7501,'FILL RATE MANDATORY STOCK'!BK27,'DETAIL SALES'!$AB$10:$AB$7501,"Full",'DETAIL SALES'!$C$10:$C$7501,"20") -> 0 | CZ27: =COUNTIFS('DETAIL SALES'!$Q$10:$Q$7501,'FILL RATE MANDATORY STOCK'!BK27,'DETAIL SALES'!$AB$10:$AB$7501,"No",'DETAIL SALES'!$C$10:$C$7501,"20") -> 0 | DA27: =COUNTIFS('DETAIL SALES'!$Q$10:$Q$7501,'FILL RATE MANDATORY STOCK'!BK27,'DETAIL SALES'!$AB$10:$AB$7501,"Full",'DETAIL SALES'!$C$10:$C$7501,"21") -> 0 | DB27: =COUNTIFS('DETAIL SALES'!$Q$10:$Q$7501,'FILL RATE MANDATORY STOCK'!BK27,'DETAIL SALES'!$AB$10:$AB$7501,"No",'DETAIL SALES'!$C$10:$C$7501,"21") -> 0 | DC27: =COUNTIFS('DETAIL SALES'!$Q$10:$Q$7501,'FILL RATE MANDATORY STOCK'!BK27,'DETAIL SALES'!$AB$10:$AB$7501,"Full",'DETAIL SALES'!$C$10:$C$7501,"22") -> 0 | DD27: =COUNTIFS('DETAIL SALES'!$Q$10:$Q$7501,'FILL RATE MANDATORY STOCK'!BK27,'DETAIL SALES'!$AB$10:$AB$7501,"No",'DETAIL SALES'!$C$10:$C$7501,"22") -> 0 | DE27: =COUNTIFS('DETAIL SALES'!$Q$10:$Q$7501,'FILL RATE MANDATORY STOCK'!BK27,'DETAIL SALES'!$AB$10:$AB$7501,"Full",'DETAIL SALES'!$C$10:$C$7501,"23") -> 0 | DF27: =COUNTIFS('DETAIL SALES'!$Q$10:$Q$7501,'FILL RATE MANDATORY STOCK'!BK27,'DETAIL SALES'!$AB$10:$AB$7501,"No",'DETAIL SALES'!$C$10:$C$7501,"23") -> 0 | DG27: =COUNTIFS('DETAIL SALES'!$Q$10:$Q$7501,'FILL RATE MANDATORY STOCK'!BK27,'DETAIL SALES'!$AB$10:$AB$7501,"Full",'DETAIL SALES'!$C$10:$C$7501,"24") -> 0 | DH27: =COUNTIFS('DETAIL SALES'!$Q$10:$Q$7501,'FILL RATE MANDATORY STOCK'!BK27,'DETAIL SALES'!$AB$10:$AB$7501,"No",'DETAIL SALES'!$C$10:$C$7501,"24") -> 0 | DI27: =COUNTIFS('DETAIL SALES'!$Q$10:$Q$7501,'FILL RATE MANDATORY STOCK'!BK27,'DETAIL SALES'!$AB$10:$AB$7501,"Full",'DETAIL SALES'!$C$10:$C$7501,"25") -> 0 | DJ27: =COUNTIFS('DETAIL SALES'!$Q$10:$Q$7501,'FILL RATE MANDATORY STOCK'!BK27,'DETAIL SALES'!$AB$10:$AB$7501,"No",'DETAIL SALES'!$C$10:$C$7501,"25") -> 0 | DK27: =COUNTIFS('DETAIL SALES'!$Q$10:$Q$7501,'FILL RATE MANDATORY STOCK'!BK27,'DETAIL SALES'!$AB$10:$AB$7501,"Full",'DETAIL SALES'!$C$10:$C$7501,"26") -> 0 | DL27: =COUNTIFS('DETAIL SALES'!$Q$10:$Q$7501,'FILL RATE MANDATORY STOCK'!BK27,'DETAIL SALES'!$AB$10:$AB$7501,"No",'DETAIL SALES'!$C$10:$C$7501,"26") -> 0 | DM27: =COUNTIFS('DETAIL SALES'!$Q$10:$Q$7501,'FILL RATE MANDATORY STOCK'!BK27,'DETAIL SALES'!$AB$10:$AB$7501,"Full",'DETAIL SALES'!$C$10:$C$7501,"27") -> 0 | DN27: =COUNTIFS('DETAIL SALES'!$Q$10:$Q$7501,'FILL RATE MANDATORY STOCK'!BK27,'DETAIL SALES'!$AB$10:$AB$7501,"No",'DETAIL SALES'!$C$10:$C$7501,"27") -> 0 | DO27: =COUNTIFS('DETAIL SALES'!$Q$10:$Q$7501,'FILL RATE MANDATORY STOCK'!BK27,'DETAIL SALES'!$AB$10:$AB$7501,"Full",'DETAIL SALES'!$C$10:$C$7501,"28") -> 0 | DP27: =COUNTIFS('DETAIL SALES'!$Q$10:$Q$7501,'FILL RATE MANDATORY STOCK'!BK27,'DETAIL SALES'!$AB$10:$AB$7501,"No",'DETAIL SALES'!$C$10:$C$7501,"28") -> 0 | DQ27: =COUNTIFS('DETAIL SALES'!$Q$10:$Q$7501,'FILL RATE MANDATORY STOCK'!BK27,'DETAIL SALES'!$AB$10:$AB$7501,"Full",'DETAIL SALES'!$C$10:$C$7501,"29") -> 0 | DR27: =COUNTIFS('DETAIL SALES'!$Q$10:$Q$7501,'FILL RATE MANDATORY STOCK'!BK27,'DETAIL SALES'!$AB$10:$AB$7501,"No",'DETAIL SALES'!$C$10:$C$7501,"29") -> 0 | DS27: =COUNTIFS('DETAIL SALES'!$Q$10:$Q$7501,'FILL RATE MANDATORY STOCK'!BK27,'DETAIL SALES'!$AB$10:$AB$7501,"Full",'DETAIL SALES'!$C$10:$C$7501,"30") -> 0 | DT27: =COUNTIFS('DETAIL SALES'!$Q$10:$Q$7501,'FILL RATE MANDATORY STOCK'!BK27,'DETAIL SALES'!$AB$10:$AB$7501,"No",'DETAIL SALES'!$C$10:$C$7501,"30") -> 0 | DU27: =COUNTIFS('DETAIL SALES'!$Q$10:$Q$7501,'FILL RATE MANDATORY STOCK'!\,'DETAIL SALES'!$AB$10:$AB$7501,"Full",'DETAIL SALES'!$C$10:$C$7501,"31") -> 0 | DV27: =COUNTIFS('DETAIL SALES'!$Q$10:$Q$7501,'FILL RATE MANDATORY STOCK'!BK27,'DETAIL SALES'!$AB$10:$AB$7501,"No",'DETAIL SALES'!$C$10:$C$7501,"31") -> 0 | DW27: =BM27+BO27+BQ27+BS27+BU27+BW27+BY27+CA27+CC27+CE27+CG27+CI27+CK27+CM27+CO27+CQ27+CS27+CU27+CW27+CY27+DA27+DC27+DE27+DG27+DI27+DK27+DM27+DO27+DQ27+DS27+DU27 -> 0 | DX27: =BN27+BP27+BR27+BT27+BV27+BX27+BZ27+CB27+CD27+CF27+CH27+CJ27+CL27+CN27+CP27+CR27+CT27+CV27+CX27+CZ27+DB27+DD27+DF27+DH27+DJ27+DL27+DN27+DP27+DR27+DT27+DV27 -> 0 | DY27: =DW27+DX27 -> 0 | DZ27: =DW27/DY27 -> #DIV/0!
A28: 19 | C28: =DAY(B28) -> 0 | D28: =MONTH(B28) -> 1 | E28: =YEAR(B28) -> 1900 | Y28: =X28*U28 -> 0 | Z28: =Y28*1.1 -> 0 | AB28: =IF(S28="","",IF(S28-U28=0,"Full","No")) | AC28: =IF(AND(S28>U28,V28=0),"Lost",IF(AND(S28>U28,V28<(S28-U28)),"Lost","")) | AD28: =IF(AND(S28>U28,V28=0),S28-U28,IF(AND(S28>U28,V28<(S28-U28)),S28-(U28+V28),"")) | AJ28: 17 | AK28: Public Transportation | AN28: PT. HIBAINDO ARMADA MOTOR | AQ28: Travel & Tourism | AW28: =AV28/$AV$40 -> #DIV/0! | AZ28: =AY28/(AX28+AY28) -> #DIV/0! | BE28: =MAX(BE25:BE27)+1 -> 17 | BF28: Oil Filter | BG28: J08E (Y230) | BH28: 15613JAA10 | BI28: =VLOOKUP(BH28,#REF!,8,FALSE) -> #REF! | BJ28: 20000 | BK28: 1 | BL28: 6.1666667 | BM28: =COUNTIFS('DETAIL SALES'!$Q$10:$Q$7501,'FILL RATE MANDATORY STOCK'!BK28,'DETAIL SALES'!$AB$10:$AB$7501,"Full",'DETAIL SALES'!$C$10:$C$7501,"1") -> 0 | BN28: =COUNTIFS('DETAIL SALES'!$Q$10:$Q$7501,'FILL RATE MANDATORY STOCK'!BK28,'DETAIL SALES'!$AB$10:$AB$7501,"No",'DETAIL SALES'!$C$10:$C$7501,"1") -> 0 | BO28: =COUNTIFS('DETAIL SALES'!$Q$10:$Q$7501,'FILL RATE MANDATORY STOCK'!BK28,'DETAIL SALES'!$AB$10:$AB$7501,"Full",'DETAIL SALES'!$C$10:$C$7501,"2") -> 0 | BP28: =COUNTIFS('DETAIL SALES'!$Q$10:$Q$7501,'FILL RATE MANDATORY STOCK'!BK28,'DETAIL SALES'!$AB$10:$AB$7501,"No",'DETAIL SALES'!$C$10:$C$7501,"2") -> 0 | BQ28: =COUNTIFS('DETAIL SALES'!$Q$10:$Q$7501,'FILL RATE MANDATORY STOCK'!BK28,'DETAIL SALES'!$AB$10:$AB$7501,"Full",'DETAIL SALES'!$C$10:$C$7501,"3") -> 0 | BR28: =COUNTIFS('DETAIL SALES'!$Q$10:$Q$7501,'FILL RATE MANDATORY STOCK'!BK28,'DETAIL SALES'!$AB$10:$AB$7501,"No",'DETAIL SALES'!$C$10:$C$7501,"3") -> 0 | BS28: =COUNTIFS('DETAIL SALES'!$Q$10:$Q$7501,'FILL RATE MANDATORY STOCK'!BK28,'DETAIL SALES'!$AB$10:$AB$7501,"Full",'DETAIL SALES'!$C$10:$C$7501,"4") -> 0 | BT28: =COUNTIFS('DETAIL SALES'!$Q$10:$Q$7501,'FILL RATE MANDATORY STOCK'!BK28,'DETAIL SALES'!$AB$10:$AB$7501,"No",'DETAIL SALES'!$C$10:$C$7501,"4") -> 0 | BU28: =COUNTIFS('DETAIL SALES'!$Q$10:$Q$7501,'FILL RATE MANDATORY STOCK'!BK28,'DETAIL SALES'!$AB$10:$AB$7501,"Full",'DETAIL SALES'!$C$10:$C$7501,"5") -> 0 | BV28: =COUNTIFS('DETAIL SALES'!$Q$10:$Q$7501,'FILL RATE MANDATORY STOCK'!BK28,'DETAIL SALES'!$AB$10:$AB$7501,"No",'DETAIL SALES'!$C$10:$C$7501,"5") -> 0 | BW28: =COUNTIFS('DETAIL SALES'!$Q$10:$Q$7501,'FILL RATE MANDATORY STOCK'!BK28,'DETAIL SALES'!$AB$10:$AB$7501,"Full",'DETAIL SALES'!$C$10:$C$7501,"6") -> 0 | BX28: =COUNTIFS('DETAIL SALES'!$Q$10:$Q$7501,'FILL RATE MANDATORY STOCK'!BK28,'DETAIL SALES'!$AB$10:$AB$7501,"No",'DETAIL SALES'!$C$10:$C$7501,"6") -> 0 | BY28: =COUNTIFS('DETAIL SALES'!$Q$10:$Q$7501,'FILL RATE MANDATORY STOCK'!BK28,'DETAIL SALES'!$AB$10:$AB$7501,"Full",'DETAIL SALES'!$C$10:$C$7501,"7") -> 0 | BZ28: =COUNTIFS('DETAIL SALES'!$Q$10:$Q$7501,'FILL RATE MANDATORY STOCK'!BK28,'DETAIL SALES'!$AB$10:$AB$7501,"No",'DETAIL SALES'!$C$10:$C$7501,"7") -> 0 | CA28: =COUNTIFS('DETAIL SALES'!$Q$10:$Q$7501,'FILL RATE MANDATORY STOCK'!BK28,'DETAIL SALES'!$AB$10:$AB$7501,"Full",'DETAIL SALES'!$C$10:$C$7501,"8") -> 0 | CB28: =COUNTIFS('DETAIL SALES'!$Q$10:$Q$7501,'FILL RATE MANDATORY STOCK'!BK28,'DETAIL SALES'!$AB$10:$AB$7501,"No",'DETAIL SALES'!$C$10:$C$7501,"8") -> 0 | CC28: =COUNTIFS('DETAIL SALES'!$Q$10:$Q$7501,'FILL RATE MANDATORY STOCK'!BK28,'DETAIL SALES'!$AB$10:$AB$7501,"Full",'DETAIL SALES'!$C$10:$C$7501,"9") -> 0 | CD28: =COUNTIFS('DETAIL SALES'!$Q$10:$Q$7501,'FILL RATE MANDATORY STOCK'!BK28,'DETAIL SALES'!$AB$10:$AB$7501,"No",'DETAIL SALES'!$C$10:$C$7501,"9") -> 0 | CE28: =COUNTIFS('DETAIL SALES'!$Q$10:$Q$7501,'FILL RATE MANDATORY STOCK'!BK28,'DETAIL SALES'!$AB$10:$AB$7501,"Full",'DETAIL SALES'!$C$10:$C$7501,"10") -> 0 | CF28: =COUNTIFS('DETAIL SALES'!$Q$10:$Q$7501,'FILL RATE MANDATORY STOCK'!BK28,'DETAIL SALES'!$AB$10:$AB$7501,"No",'DETAIL SALES'!$C$10:$C$7501,"10") -> 0 | CG28: =COUNTIFS('DETAIL SALES'!$Q$10:$Q$7501,'FILL RATE MANDATORY STOCK'!BK28,'DETAIL SALES'!$AB$10:$AB$7501,"Full",'DETAIL SALES'!$C$10:$C$7501,"11") -> 0 | CH28: =COUNTIFS('DETAIL SALES'!$Q$10:$Q$7501,'FILL RATE MANDATORY STOCK'!BK28,'DETAIL SALES'!$AB$10:$AB$7501,"No",'DETAIL SALES'!$C$10:$C$7501,"11") -> 0 | CI28: =COUNTIFS('DETAIL SALES'!$Q$10:$Q$7501,'FILL RATE MANDATORY STOCK'!BK28,'DETAIL SALES'!$AB$10:$AB$7501,"Full",'DETAIL SALES'!$C$10:$C$7501,"12") -> 0 | CJ28: =COUNTIFS('DETAIL SALES'!$Q$10:$Q$7501,'FILL RATE MANDATORY STOCK'!BK28,'DETAIL SALES'!$AB$10:$AB$7501,"No",'DETAIL SALES'!$C$10:$C$7501,"12") -> 0 | CK28: =COUNTIFS('DETAIL SALES'!$Q$10:$Q$7501,'FILL RATE MANDATORY STOCK'!BK28,'DETAIL SALES'!$AB$10:$AB$7501,"Full",'DETAIL SALES'!$C$10:$C$7501,"13") -> 0 | CL28: =COUNTIFS('DETAIL SALES'!$Q$10:$Q$7501,'FILL RATE MANDATORY STOCK'!BK28,'DETAIL SALES'!$AB$10:$AB$7501,"No",'DETAIL SALES'!$C$10:$C$7501,"13") -> 0 | CM28: =COUNTIFS('DETAIL SALES'!$Q$10:$Q$7501,'FILL RATE MANDATORY STOCK'!BK28,'DETAIL SALES'!$AB$10:$AB$7501,"Full",'DETAIL SALES'!$C$10:$C$7501,"14") -> 0 | CN28: =COUNTIFS('DETAIL SALES'!$Q$10:$Q$7501,'FILL RATE MANDATORY STOCK'!BK28,'DETAIL SALES'!$AB$10:$AB$7501,"No",'DETAIL SALES'!$C$10:$C$7501,"14") -> 0 | CO28: =COUNTIFS('DETAIL SALES'!$Q$10:$Q$7501,'FILL RATE MANDATORY STOCK'!BK28,'DETAIL SALES'!$AB$10:$AB$7501,"Full",'DETAIL SALES'!$C$10:$C$7501,"15") -> 0 | CP28: =COUNTIFS('DETAIL SALES'!$Q$10:$Q$7501,'FILL RATE MANDATORY STOCK'!BK28,'DETAIL SALES'!$AB$10:$AB$7501,"No",'DETAIL SALES'!$C$10:$C$7501,"15") -> 0 | CQ28: =COUNTIFS('DETAIL SALES'!$Q$10:$Q$7501,'FILL RATE MANDATORY STOCK'!BK28,'DETAIL SALES'!$AB$10:$AB$7501,"Full",'DETAIL SALES'!$C$10:$C$7501,"16") -> 0 | CR28: =COUNTIFS('DETAIL SALES'!$Q$10:$Q$7501,'FILL RATE MANDATORY STOCK'!BK28,'DETAIL SALES'!$AB$10:$AB$7501,"No",'DETAIL SALES'!$C$10:$C$7501,"16") -> 0 | CS28: =COUNTIFS('DETAIL SALES'!$Q$10:$Q$7501,'FILL RATE MANDATORY STOCK'!BK28,'DETAIL SALES'!$AB$10:$AB$7501,"Full",'DETAIL SALES'!$C$10:$C$7501,"17") -> 0 | CT28: =COUNTIFS('DETAIL SALES'!$Q$10:$Q$7501,'FILL RATE MANDATORY STOCK'!BK28,'DETAIL SALES'!$AB$10:$AB$7501,"No",'DETAIL SALES'!$C$10:$C$7501,"17") -> 0 | CU28: =COUNTIFS('DETAIL SALES'!$Q$10:$Q$7501,'FILL RATE MANDATORY STOCK'!BK28,'DETAIL SALES'!$AB$10:$AB$7501,"Full",'DETAIL SALES'!$C$10:$C$7501,"18") -> 0 | CV28: =COUNTIFS('DETAIL SALES'!$Q$10:$Q$7501,'FILL RATE MANDATORY STOCK'!BK28,'DETAIL SALES'!$AB$10:$AB$7501,"No",'DETAIL SALES'!$C$10:$C$7501,"18") -> 0 | CW28: =COUNTIFS('DETAIL SALES'!$Q$10:$Q$7501,'FILL RATE MANDATORY STOCK'!BK28,'DETAIL SALES'!$AB$10:$AB$7501,"Full",'DETAIL SALES'!$C$10:$C$7501,"19") -> 0 | CX28: =COUNTIFS('DETAIL SALES'!$Q$10:$Q$7501,'FILL RATE MANDATORY STOCK'!BK28,'DETAIL SALES'!$AB$10:$AB$7501,"No",'DETAIL SALES'!$C$10:$C$7501,"19") -> 0 | CY28: =COUNTIFS('DETAIL SALES'!$Q$10:$Q$7501,'FILL RATE MANDATORY STOCK'!BK28,'DETAIL SALES'!$AB$10:$AB$7501,"Full",'DETAIL SALES'!$C$10:$C$7501,"20") -> 0 | CZ28: =COUNTIFS('DETAIL SALES'!$Q$10:$Q$7501,'FILL RATE MANDATORY STOCK'!BK28,'DETAIL SALES'!$AB$10:$AB$7501,"No",'DETAIL SALES'!$C$10:$C$7501,"20") -> 0 | DA28: =COUNTIFS('DETAIL SALES'!$Q$10:$Q$7501,'FILL RATE MANDATORY STOCK'!BK28,'DETAIL SALES'!$AB$10:$AB$7501,"Full",'DETAIL SALES'!$C$10:$C$7501,"21") -> 0 | DB28: =COUNTIFS('DETAIL SALES'!$Q$10:$Q$7501,'FILL RATE MANDATORY STOCK'!BK28,'DETAIL SALES'!$AB$10:$AB$7501,"No",'DETAIL SALES'!$C$10:$C$7501,"21") -> 0 | DC28: =COUNTIFS('DETAIL SALES'!$Q$10:$Q$7501,'FILL RATE MANDATORY STOCK'!BK28,'DETAIL SALES'!$AB$10:$AB$7501,"Full",'DETAIL SALES'!$C$10:$C$7501,"22") -> 0 | DD28: =COUNTIFS('DETAIL SALES'!$Q$10:$Q$7501,'FILL RATE MANDATORY STOCK'!BK28,'DETAIL SALES'!$AB$10:$AB$7501,"No",'DETAIL SALES'!$C$10:$C$7501,"22") -> 0 | DE28: =COUNTIFS('DETAIL SALES'!$Q$10:$Q$7501,'FILL RATE MANDATORY STOCK'!BK28,'DETAIL SALES'!$AB$10:$AB$7501,"Full",'DETAIL SALES'!$C$10:$C$7501,"23") -> 0 | DF28: =COUNTIFS('DETAIL SALES'!$Q$10:$Q$7501,'FILL RATE MANDATORY STOCK'!BK28,'DETAIL SALES'!$AB$10:$AB$7501,"No",'DETAIL SALES'!$C$10:$C$7501,"23") -> 0 | DG28: =COUNTIFS('DETAIL SALES'!$Q$10:$Q$7501,'FILL RATE MANDATORY STOCK'!BK28,'DETAIL SALES'!$AB$10:$AB$7501,"Full",'DETAIL SALES'!$C$10:$C$7501,"24") -> 0 | DH28: =COUNTIFS('DETAIL SALES'!$Q$10:$Q$7501,'FILL RATE MANDATORY STOCK'!BK28,'DETAIL SALES'!$AB$10:$AB$7501,"No",'DETAIL SALES'!$C$10:$C$7501,"24") -> 0 | DI28: =COUNTIFS('DETAIL SALES'!$Q$10:$Q$7501,'FILL RATE MANDATORY STOCK'!BK28,'DETAIL SALES'!$AB$10:$AB$7501,"Full",'DETAIL SALES'!$C$10:$C$7501,"25") -> 0 | DJ28: =COUNTIFS('DETAIL SALES'!$Q$10:$Q$7501,'FILL RATE MANDATORY STOCK'!BK28,'DETAIL SALES'!$AB$10:$AB$7501,"No",'DETAIL SALES'!$C$10:$C$7501,"25") -> 0 | DK28: =COUNTIFS('DETAIL SALES'!$Q$10:$Q$7501,'FILL RATE MANDATORY STOCK'!BK28,'DETAIL SALES'!$AB$10:$AB$7501,"Full",'DETAIL SALES'!$C$10:$C$7501,"26") -> 0 | DL28: =COUNTIFS('DETAIL SALES'!$Q$10:$Q$7501,'FILL RATE MANDATORY STOCK'!BK28,'DETAIL SALES'!$AB$10:$AB$7501,"No",'DETAIL SALES'!$C$10:$C$7501,"26") -> 0 | DM28: =COUNTIFS('DETAIL SALES'!$Q$10:$Q$7501,'FILL RATE MANDATORY STOCK'!BK28,'DETAIL SALES'!$AB$10:$AB$7501,"Full",'DETAIL SALES'!$C$10:$C$7501,"27") -> 0 | DN28: =COUNTIFS('DETAIL SALES'!$Q$10:$Q$7501,'FILL RATE MANDATORY STOCK'!BK28,'DETAIL SALES'!$AB$10:$AB$7501,"No",'DETAIL SALES'!$C$10:$C$7501,"27") -> 0 | DO28: =COUNTIFS('DETAIL SALES'!$Q$10:$Q$7501,'FILL RATE MANDATORY STOCK'!BK28,'DETAIL SALES'!$AB$10:$AB$7501,"Full",'DETAIL SALES'!$C$10:$C$7501,"28") -> 0 | DP28: =COUNTIFS('DETAIL SALES'!$Q$10:$Q$7501,'FILL RATE MANDATORY STOCK'!BK28,'DETAIL SALES'!$AB$10:$AB$7501,"No",'DETAIL SALES'!$C$10:$C$7501,"28") -> 0 | DQ28: =COUNTIFS('DETAIL SALES'!$Q$10:$Q$7501,'FILL RATE MANDATORY STOCK'!BK28,'DETAIL SALES'!$AB$10:$AB$7501,"Full",'DETAIL SALES'!$C$10:$C$7501,"29") -> 0 | DR28: =COUNTIFS('DETAIL SALES'!$Q$10:$Q$7501,'FILL RATE MANDATORY STOCK'!BK28,'DETAIL SALES'!$AB$10:$AB$7501,"No",'DETAIL SALES'!$C$10:$C$7501,"29") -> 0 | DS28: =COUNTIFS('DETAIL SALES'!$Q$10:$Q$7501,'FILL RATE MANDATORY STOCK'!BK28,'DETAIL SALES'!$AB$10:$AB$7501,"Full",'DETAIL SALES'!$C$10:$C$7501,"30") -> 0 | DT28: =COUNTIFS('DETAIL SALES'!$Q$10:$Q$7501,'FILL RATE MANDATORY STOCK'!BK28,'DETAIL SALES'!$AB$10:$AB$7501,"No",'DETAIL SALES'!$C$10:$C$7501,"30") -> 0 | DU28: =COUNTIFS('DETAIL SALES'!$Q$10:$Q$7501,'FILL RATE MANDATORY STOCK'!\,'DETAIL SALES'!$AB$10:$AB$7501,"Full",'DETAIL SALES'!$C$10:$C$7501,"31") -> 0 | DV28: =COUNTIFS('DETAIL SALES'!$Q$10:$Q$7501,'FILL RATE MANDATORY STOCK'!BK28,'DETAIL SALES'!$AB$10:$AB$7501,"No",'DETAIL SALES'!$C$10:$C$7501,"31") -> 0 | DW28: =BM28+BO28+BQ28+BS28+BU28+BW28+BY28+CA28+CC28+CE28+CG28+CI28+CK28+CM28+CO28+CQ28+CS28+CU28+CW28+CY28+DA28+DC28+DE28+DG28+DI28+DK28+DM28+DO28+DQ28+DS28+DU28 -> 0 | DX28: =BN28+BP28+BR28+BT28+BV28+BX28+BZ28+CB28+CD28+CF28+CH28+CJ28+CL28+CN28+CP28+CR28+CT28+CV28+CX28+CZ28+DB28+DD28+DF28+DH28+DJ28+DL28+DN28+DP28+DR28+DT28+DV28 -> 0 | DY28: =DW28+DX28 -> 0 | DZ28: =DW28/DY28 -> #DIV/0!
